Workbook

Sheet Dashboard
I3: C&A ($CEAB3)
A7: Páginas
A8: Dashboard
A9: WACC | E9: Ticker | F9: CEAB3 | H9: WACC | I9: =I10-0.5% -> 0.15529878 | J9: =(NPV($I9,'DRE + DCF'!$M$47,'DRE + DCF'!$O$47:$T$47)+('DRE + DCF'!$U$47*(1+J$18)/(($I9-J$18)*(1+$I9)^COUNT('DRE + DCF'!$N$36:$T$36)))+SUM($F$13:$F$14)-$F$12)/$F$10 -> 4.9404396 | K9: =(NPV($I9,'DRE + DCF'!$M$47,'DRE + DCF'!$O$47:$T$47)+('DRE + DCF'!$U$47*(1+K$18)/(($I9-K$18)*(1+$I9)^COUNT('DRE + DCF'!$N$36:$T$36)))+SUM($F$13:$F$14)-$F$12)/$F$10 -> 5.2433816 | L9: =(NPV($I9,'DRE + DCF'!$M$47,'DRE + DCF'!$O$47:$T$47)+('DRE + DCF'!$U$47*(1+L$18)/(($I9-L$18)*(1+$I9)^COUNT('DRE + DCF'!$N$36:$T$36)))+SUM($F$13:$F$14)-$F$12)/$F$10 -> 5.5651869 | M9: =(NPV($I9,'DRE + DCF'!$M$47,'DRE + DCF'!$O$47:$T$47)+('DRE + DCF'!$U$47*(1+M$18)/(($I9-M$18)*(1+$I9)^COUNT('DRE + DCF'!$N$36:$T$36)))+SUM($F$13:$F$14)-$F$12)/$F$10 -> 5.9076741 | N9: =(NPV($I9,'DRE + DCF'!$M$47,'DRE + DCF'!$O$47:$T$47)+('DRE + DCF'!$U$47*(1+N$18)/(($I9-N$18)*(1+$I9)^COUNT('DRE + DCF'!$N$36:$T$36)))+SUM($F$13:$F$14)-$F$12)/$F$10 -> 6.2729032 | O9: =(NPV($I9,'DRE + DCF'!$M$47,'DRE + DCF'!$O$47:$T$47)+('DRE + DCF'!$U$47*(1+O$18)/(($I9-O$18)*(1+$I9)^COUNT('DRE + DCF'!$N$36:$T$36)))+SUM($F$13:$F$14)-$F$12)/$F$10 -> 6.6632172 | P9: =(NPV($I9,'DRE + DCF'!$M$47,'DRE + DCF'!$O$47:$T$47)+('DRE + DCF'!$U$47*(1+P$18)/(($I9-P$18)*(1+$I9)^COUNT('DRE + DCF'!$N$36:$T$36)))+SUM($F$13:$F$14)-$F$12)/$F$10 -> 7.0812922 | Q9: =(NPV($I9,'DRE + DCF'!$M$47,'DRE + DCF'!$O$47:$T$47)+('DRE + DCF'!$U$47*(1+Q$18)/(($I9-Q$18)*(1+$I9)^COUNT('DRE + DCF'!$N$36:$T$36)))+SUM($F$13:$F$14)-$F$12)/$F$10 -> 7.5301993 | ... S9: =(NPV($I9,'DRE + DCF'!$M$47,'DRE + DCF'!$O$47:$T$47)+('DRE + DCF'!$U$47*(1+S$18)/(($I9-S$18)*(1+$I9)^COUNT('DRE + DCF'!$N$36:$T$36)))+SUM($F$13:$F$14)-$F$12)/$F$10 -> 8.5352386
A10: DRE + DCF | E10: Ações Emitidas (mil) | F10: 308245.07 | I10: =I11-0.5% -> 0.16029878 | J10: =(NPV($I10,'DRE + DCF'!$M$47,'DRE + DCF'!$O$47:$T$47)+('DRE + DCF'!$U$47*(1+J$18)/(($I10-J$18)*(1+$I10)^COUNT('DRE + DCF'!$N$36:$T$36)))+SUM($F$13:$F$14)-$F$12)/$F$10 -> 4.0851241 | K10: =(NPV($I10,'DRE + DCF'!$M$47,'DRE + DCF'!$O$47:$T$47)+('DRE + DCF'!$U$47*(1+K$18)/(($I10-K$18)*(1+$I10)^COUNT('DRE + DCF'!$N$36:$T$36)))+SUM($F$13:$F$14)-$F$12)/$F$10 -> 4.3480919 | L10: =(NPV($I10,'DRE + DCF'!$M$47,'DRE + DCF'!$O$47:$T$47)+('DRE + DCF'!$U$47*(1+L$18)/(($I10-L$18)*(1+$I10)^COUNT('DRE + DCF'!$N$36:$T$36)))+SUM($F$13:$F$14)-$F$12)/$F$10 -> 4.6264743 | M10: =(NPV($I10,'DRE + DCF'!$M$47,'DRE + DCF'!$O$47:$T$47)+('DRE + DCF'!$U$47*(1+M$18)/(($I10-M$18)*(1+$I10)^COUNT('DRE + DCF'!$N$36:$T$36)))+SUM($F$13:$F$14)-$F$12)/$F$10 -> 4.9216674 | N10: =(NPV($I10,'DRE + DCF'!$M$47,'DRE + DCF'!$O$47:$T$47)+('DRE + DCF'!$U$47*(1+N$18)/(($I10-N$18)*(1+$I10)^COUNT('DRE + DCF'!$N$36:$T$36)))+SUM($F$13:$F$14)-$F$12)/$F$10 -> 5.2352414 | O10: =(NPV($I10,'DRE + DCF'!$M$47,'DRE + DCF'!$O$47:$T$47)+('DRE + DCF'!$U$47*(1+O$18)/(($I10-O$18)*(1+$I10)^COUNT('DRE + DCF'!$N$36:$T$36)))+SUM($F$13:$F$14)-$F$12)/$F$10 -> 5.5689684 | P10: =(NPV($I10,'DRE + DCF'!$M$47,'DRE + DCF'!$O$47:$T$47)+('DRE + DCF'!$U$47*(1+P$18)/(($I10-P$18)*(1+$I10)^COUNT('DRE + DCF'!$N$36:$T$36)))+SUM($F$13:$F$14)-$F$12)/$F$10 -> 5.9248555 | Q10: =(NPV($I10,'DRE + DCF'!$M$47,'DRE + DCF'!$O$47:$T$47)+('DRE + DCF'!$U$47*(1+Q$18)/(($I10-Q$18)*(1+$I10)^COUNT('DRE + DCF'!$N$36:$T$36)))+SUM($F$13:$F$14)-$F$12)/$F$10 -> 6.3051858 | ... S10: =(NPV($I10,'DRE + DCF'!$M$47,'DRE + DCF'!$O$47:$T$47)+('DRE + DCF'!$U$47*(1+S$18)/(($I10-S$18)*(1+$I10)^COUNT('DRE + DCF'!$N$36:$T$36)))+SUM($F$13:$F$14)-$F$12)/$F$10 -> 7.1499918
A11: Balanço Patrimonial | E11: Valor da Empresa (mil) | F11: =NPV(WACC!$K$20,'DRE + DCF'!M47,'DRE + DCF'!$O$47:$T$47)+(('DRE + DCF'!$U$47*(1+'DRE + DCF'!$W$37))/(WACC!$K$20-'DRE + DCF'!$W$37)*(1/(1+WACC!$K$20)^COUNT('DRE + DCF'!$N$36:$T$36))) -> 2974586.1 | I11: =I12-0.5% -> 0.16529878 | J11: =(NPV($I11,'DRE + DCF'!$M$47,'DRE + DCF'!$O$47:$T$47)+('DRE + DCF'!$U$47*(1+J$18)/(($I11-J$18)*(1+$I11)^COUNT('DRE + DCF'!$N$36:$T$36)))+SUM($F$13:$F$14)-$F$12)/$F$10 -> 3.3221661 | K11: =(NPV($I11,'DRE + DCF'!$M$47,'DRE + DCF'!$O$47:$T$47)+('DRE + DCF'!$U$47*(1+K$18)/(($I11-K$18)*(1+$I11)^COUNT('DRE + DCF'!$N$36:$T$36)))+SUM($F$13:$F$14)-$F$12)/$F$10 -> 3.5519071 | L11: =(NPV($I11,'DRE + DCF'!$M$47,'DRE + DCF'!$O$47:$T$47)+('DRE + DCF'!$U$47*(1+L$18)/(($I11-L$18)*(1+$I11)^COUNT('DRE + DCF'!$N$36:$T$36)))+SUM($F$13:$F$14)-$F$12)/$F$10 -> 3.7943694 | M11: =(NPV($I11,'DRE + DCF'!$M$47,'DRE + DCF'!$O$47:$T$47)+('DRE + DCF'!$U$47*(1+M$18)/(($I11-M$18)*(1+$I11)^COUNT('DRE + DCF'!$N$36:$T$36)))+SUM($F$13:$F$14)-$F$12)/$F$10 -> 4.0506395 | N11: =(NPV($I11,'DRE + DCF'!$M$47,'DRE + DCF'!$O$47:$T$47)+('DRE + DCF'!$U$47*(1+N$18)/(($I11-N$18)*(1+$I11)^COUNT('DRE + DCF'!$N$36:$T$36)))+SUM($F$13:$F$14)-$F$12)/$F$10 -> 4.3219314 | O11: =(NPV($I11,'DRE + DCF'!$M$47,'DRE + DCF'!$O$47:$T$47)+('DRE + DCF'!$U$47*(1+O$18)/(($I11-O$18)*(1+$I11)^COUNT('DRE + DCF'!$N$36:$T$36)))+SUM($F$13:$F$14)-$F$12)/$F$10 -> 4.609606 | P11: =(NPV($I11,'DRE + DCF'!$M$47,'DRE + DCF'!$O$47:$T$47)+('DRE + DCF'!$U$47*(1+P$18)/(($I11-P$18)*(1+$I11)^COUNT('DRE + DCF'!$N$36:$T$36)))+SUM($F$13:$F$14)-$F$12)/$F$10 -> 4.9151934 | Q11: =(NPV($I11,'DRE + DCF'!$M$47,'DRE + DCF'!$O$47:$T$47)+('DRE + DCF'!$U$47*(1+Q$18)/(($I11-Q$18)*(1+$I11)^COUNT('DRE + DCF'!$N$36:$T$36)))+SUM($F$13:$F$14)-$F$12)/$F$10 -> 5.2404203 | ... S11: =(NPV($I11,'DRE + DCF'!$M$47,'DRE + DCF'!$O$47:$T$47)+('DRE + DCF'!$U$47*(1+S$18)/(($I11-S$18)*(1+$I11)^COUNT('DRE + DCF'!$N$36:$T$36)))+SUM($F$13:$F$14)-$F$12)/$F$10 -> 5.9578864
A12: Projeções | E12: Dívida (mil) | F12: =WACC!K19 -> 3471349 | I12: =I13-0.5% -> 0.17029878 | J12: =(NPV($I12,'DRE + DCF'!$M$47,'DRE + DCF'!$O$47:$T$47)+('DRE + DCF'!$U$47*(1+J$18)/(($I12-J$18)*(1+$I12)^COUNT('DRE + DCF'!$N$36:$T$36)))+SUM($F$13:$F$14)-$F$12)/$F$10 -> 2.637741 | K12: =(NPV($I12,'DRE + DCF'!$M$47,'DRE + DCF'!$O$47:$T$47)+('DRE + DCF'!$U$47*(1+K$18)/(($I12-K$18)*(1+$I12)^COUNT('DRE + DCF'!$N$36:$T$36)))+SUM($F$13:$F$14)-$F$12)/$F$10 -> 2.8396159 | L12: =(NPV($I12,'DRE + DCF'!$M$47,'DRE + DCF'!$O$47:$T$47)+('DRE + DCF'!$U$47*(1+L$18)/(($I12-L$18)*(1+$I12)^COUNT('DRE + DCF'!$N$36:$T$36)))+SUM($F$13:$F$14)-$F$12)/$F$10 -> 3.0520825 | M12: =(NPV($I12,'DRE + DCF'!$M$47,'DRE + DCF'!$O$47:$T$47)+('DRE + DCF'!$U$47*(1+M$18)/(($I12-M$18)*(1+$I12)^COUNT('DRE + DCF'!$N$36:$T$36)))+SUM($F$13:$F$14)-$F$12)/$F$10 -> 3.2759969 | N12: =(NPV($I12,'DRE + DCF'!$M$47,'DRE + DCF'!$O$47:$T$47)+('DRE + DCF'!$U$47*(1+N$18)/(($I12-N$18)*(1+$I12)^COUNT('DRE + DCF'!$N$36:$T$36)))+SUM($F$13:$F$14)-$F$12)/$F$10 -> 3.5123097 | O12: =(NPV($I12,'DRE + DCF'!$M$47,'DRE + DCF'!$O$47:$T$47)+('DRE + DCF'!$U$47*(1+O$18)/(($I12-O$18)*(1+$I12)^COUNT('DRE + DCF'!$N$36:$T$36)))+SUM($F$13:$F$14)-$F$12)/$F$10 -> 3.7620802 | P12: =(NPV($I12,'DRE + DCF'!$M$47,'DRE + DCF'!$O$47:$T$47)+('DRE + DCF'!$U$47*(1+P$18)/(($I12-P$18)*(1+$I12)^COUNT('DRE + DCF'!$N$36:$T$36)))+SUM($F$13:$F$14)-$F$12)/$F$10 -> 4.0264916 | Q12: =(NPV($I12,'DRE + DCF'!$M$47,'DRE + DCF'!$O$47:$T$47)+('DRE + DCF'!$U$47*(1+Q$18)/(($I12-Q$18)*(1+$I12)^COUNT('DRE + DCF'!$N$36:$T$36)))+SUM($F$13:$F$14)-$F$12)/$F$10 -> 4.3068701 | ... S12: =(NPV($I12,'DRE + DCF'!$M$47,'DRE + DCF'!$O$47:$T$47)+('DRE + DCF'!$U$47*(1+S$18)/(($I12-S$18)*(1+$I12)^COUNT('DRE + DCF'!$N$36:$T$36)))+SUM($F$13:$F$14)-$F$12)/$F$10 -> 4.9216856
A13: Lojas | E13: Ativos Não-Operacionais | F13: ='Balanço Patrimonial'!L14+'Balanço Patrimonial'!L27 -> 528474.76 | I13: =WACC!K20 -> 0.17529878 | J13: =(NPV($I13,'DRE + DCF'!$M$47,'DRE + DCF'!$O$47:$T$47)+('DRE + DCF'!$U$47*(1+J$18)/(($I13-J$18)*(1+$I13)^COUNT('DRE + DCF'!$N$36:$T$36)))+SUM($F$13:$F$14)-$F$12)/$F$10 -> 2.0206484 | K13: =(NPV($I13,'DRE + DCF'!$M$47,'DRE + DCF'!$O$47:$T$47)+('DRE + DCF'!$U$47*(1+K$18)/(($I13-K$18)*(1+$I13)^COUNT('DRE + DCF'!$N$36:$T$36)))+SUM($F$13:$F$14)-$F$12)/$F$10 -> 2.1989647 | L13: =(NPV($I13,'DRE + DCF'!$M$47,'DRE + DCF'!$O$47:$T$47)+('DRE + DCF'!$U$47*(1+L$18)/(($I13-L$18)*(1+$I13)^COUNT('DRE + DCF'!$N$36:$T$36)))+SUM($F$13:$F$14)-$F$12)/$F$10 -> 2.3861703 | M13: =(NPV($I13,'DRE + DCF'!$M$47,'DRE + DCF'!$O$47:$T$47)+('DRE + DCF'!$U$47*(1+M$18)/(($I13-M$18)*(1+$I13)^COUNT('DRE + DCF'!$N$36:$T$36)))+SUM($F$13:$F$14)-$F$12)/$F$10 -> 2.5829467 | N13: =(NPV($I13,'DRE + DCF'!$M$47,'DRE + DCF'!$O$47:$T$47)+('DRE + DCF'!$U$47*(1+N$18)/(($I13-N$18)*(1+$I13)^COUNT('DRE + DCF'!$N$36:$T$36)))+SUM($F$13:$F$14)-$F$12)/$F$10 -> 2.7900474 | O13: =(NPV($I13,'DRE + DCF'!$M$47,'DRE + DCF'!$O$47:$T$47)+('DRE + DCF'!$U$47*(1+O$18)/(($I13-O$18)*(1+$I13)^COUNT('DRE + DCF'!$N$36:$T$36)))+SUM($F$13:$F$14)-$F$12)/$F$10 -> 3.0083067 | P13: =(NPV($I13,'DRE + DCF'!$M$47,'DRE + DCF'!$O$47:$T$47)+('DRE + DCF'!$U$47*(1+P$18)/(($I13-P$18)*(1+$I13)^COUNT('DRE + DCF'!$N$36:$T$36)))+SUM($F$13:$F$14)-$F$12)/$F$10 -> 3.2386514 | Q13: =(NPV($I13,'DRE + DCF'!$M$47,'DRE + DCF'!$O$47:$T$47)+('DRE + DCF'!$U$47*(1+Q$18)/(($I13-Q$18)*(1+$I13)^COUNT('DRE + DCF'!$N$36:$T$36)))+SUM($F$13:$F$14)-$F$12)/$F$10 -> 3.4821138 | ... S13: =(NPV($I13,'DRE + DCF'!$M$47,'DRE + DCF'!$O$47:$T$47)+('DRE + DCF'!$U$47*(1+S$18)/(($I13-S$18)*(1+$I13)^COUNT('DRE + DCF'!$N$36:$T$36)))+SUM($F$13:$F$14)-$F$12)/$F$10 -> 4.0131448
E14: Créditos Fiscais | F14: =1656613*50% -> 828306.5 | I14: =I13+0.5% -> 0.18029878 | J14: =(NPV($I14,'DRE + DCF'!$M$47,'DRE + DCF'!$O$47:$T$47)+('DRE + DCF'!$U$47*(1+J$18)/(($I14-J$18)*(1+$I14)^COUNT('DRE + DCF'!$N$36:$T$36)))+SUM($F$13:$F$14)-$F$12)/$F$10 -> 1.4617178 | K14: =(NPV($I14,'DRE + DCF'!$M$47,'DRE + DCF'!$O$47:$T$47)+('DRE + DCF'!$U$47*(1+K$18)/(($I14-K$18)*(1+$I14)^COUNT('DRE + DCF'!$N$36:$T$36)))+SUM($F$13:$F$14)-$F$12)/$F$10 -> 1.6199722 | L14: =(NPV($I14,'DRE + DCF'!$M$47,'DRE + DCF'!$O$47:$T$47)+('DRE + DCF'!$U$47*(1+L$18)/(($I14-L$18)*(1+$I14)^COUNT('DRE + DCF'!$N$36:$T$36)))+SUM($F$13:$F$14)-$F$12)/$F$10 -> 1.7857411 | M14: =(NPV($I14,'DRE + DCF'!$M$47,'DRE + DCF'!$O$47:$T$47)+('DRE + DCF'!$U$47*(1+M$18)/(($I14-M$18)*(1+$I14)^COUNT('DRE + DCF'!$N$36:$T$36)))+SUM($F$13:$F$14)-$F$12)/$F$10 -> 1.9595728 | N14: =(NPV($I14,'DRE + DCF'!$M$47,'DRE + DCF'!$O$47:$T$47)+('DRE + DCF'!$U$47*(1+N$18)/(($I14-N$18)*(1+$I14)^COUNT('DRE + DCF'!$N$36:$T$36)))+SUM($F$13:$F$14)-$F$12)/$F$10 -> 2.1420702 | O14: =(NPV($I14,'DRE + DCF'!$M$47,'DRE + DCF'!$O$47:$T$47)+('DRE + DCF'!$U$47*(1+O$18)/(($I14-O$18)*(1+$I14)^COUNT('DRE + DCF'!$N$36:$T$36)))+SUM($F$13:$F$14)-$F$12)/$F$10 -> 2.3338978 | P14: =(NPV($I14,'DRE + DCF'!$M$47,'DRE + DCF'!$O$47:$T$47)+('DRE + DCF'!$U$47*(1+P$18)/(($I14-P$18)*(1+$I14)^COUNT('DRE + DCF'!$N$36:$T$36)))+SUM($F$13:$F$14)-$F$12)/$F$10 -> 2.53579 | Q14: =(NPV($I14,'DRE + DCF'!$M$47,'DRE + DCF'!$O$47:$T$47)+('DRE + DCF'!$U$47*(1+Q$18)/(($I14-Q$18)*(1+$I14)^COUNT('DRE + DCF'!$N$36:$T$36)))+SUM($F$13:$F$14)-$F$12)/$F$10 -> 2.7485601 | ... S14: =(NPV($I14,'DRE + DCF'!$M$47,'DRE + DCF'!$O$47:$T$47)+('DRE + DCF'!$U$47*(1+S$18)/(($I14-S$18)*(1+$I14)^COUNT('DRE + DCF'!$N$36:$T$36)))+SUM($F$13:$F$14)-$F$12)/$F$10 -> 3.2104511
E15: Valor da Ação | F15: =(F11-F12+F13+F14)/F10 -> 2.7900474 | I15: =I14+0.5% -> 0.18529878 | J15: =(NPV($I15,'DRE + DCF'!$M$47,'DRE + DCF'!$O$47:$T$47)+('DRE + DCF'!$U$47*(1+J$18)/(($I15-J$18)*(1+$I15)^COUNT('DRE + DCF'!$N$36:$T$36)))+SUM($F$13:$F$14)-$F$12)/$F$10 -> 0.95336811 | K15: =(NPV($I15,'DRE + DCF'!$M$47,'DRE + DCF'!$O$47:$T$47)+('DRE + DCF'!$U$47*(1+K$18)/(($I15-K$18)*(1+$I15)^COUNT('DRE + DCF'!$N$36:$T$36)))+SUM($F$13:$F$14)-$F$12)/$F$10 -> 1.0944255 | L15: =(NPV($I15,'DRE + DCF'!$M$47,'DRE + DCF'!$O$47:$T$47)+('DRE + DCF'!$U$47*(1+L$18)/(($I15-L$18)*(1+$I15)^COUNT('DRE + DCF'!$N$36:$T$36)))+SUM($F$13:$F$14)-$F$12)/$F$10 -> 1.2418772 | M15: =(NPV($I15,'DRE + DCF'!$M$47,'DRE + DCF'!$O$47:$T$47)+('DRE + DCF'!$U$47*(1+M$18)/(($I15-M$18)*(1+$I15)^COUNT('DRE + DCF'!$N$36:$T$36)))+SUM($F$13:$F$14)-$F$12)/$F$10 -> 1.3961682 | N15: =(NPV($I15,'DRE + DCF'!$M$47,'DRE + DCF'!$O$47:$T$47)+('DRE + DCF'!$U$47*(1+N$18)/(($I15-N$18)*(1+$I15)^COUNT('DRE + DCF'!$N$36:$T$36)))+SUM($F$13:$F$14)-$F$12)/$F$10 -> 1.5577855 | O15: =(NPV($I15,'DRE + DCF'!$M$47,'DRE + DCF'!$O$47:$T$47)+('DRE + DCF'!$U$47*(1+O$18)/(($I15-O$18)*(1+$I15)^COUNT('DRE + DCF'!$N$36:$T$36)))+SUM($F$13:$F$14)-$F$12)/$F$10 -> 1.7272636 | P15: =(NPV($I15,'DRE + DCF'!$M$47,'DRE + DCF'!$O$47:$T$47)+('DRE + DCF'!$U$47*(1+P$18)/(($I15-P$18)*(1+$I15)^COUNT('DRE + DCF'!$N$36:$T$36)))+SUM($F$13:$F$14)-$F$12)/$F$10 -> 1.9051904 | Q15: =(NPV($I15,'DRE + DCF'!$M$47,'DRE + DCF'!$O$47:$T$47)+('DRE + DCF'!$U$47*(1+Q$18)/(($I15-Q$18)*(1+$I15)^COUNT('DRE + DCF'!$N$36:$T$36)))+SUM($F$13:$F$14)-$F$12)/$F$10 -> 2.0922138 | ... S15: =(NPV($I15,'DRE + DCF'!$M$47,'DRE + DCF'!$O$47:$T$47)+('DRE + DCF'!$U$47*(1+S$18)/(($I15-S$18)*(1+$I15)^COUNT('DRE + DCF'!$N$36:$T$36)))+SUM($F$13:$F$14)-$F$12)/$F$10 -> 2.496491
E16: Cotação | F16: 2.79 | I16: =I15+0.5% -> 0.19029878 | J16: =(NPV($I16,'DRE + DCF'!$M$47,'DRE + DCF'!$O$47:$T$47)+('DRE + DCF'!$U$47*(1+J$18)/(($I16-J$18)*(1+$I16)^COUNT('DRE + DCF'!$N$36:$T$36)))+SUM($F$13:$F$14)-$F$12)/$F$10 -> 0.48927769 | K16: =(NPV($I16,'DRE + DCF'!$M$47,'DRE + DCF'!$O$47:$T$47)+('DRE + DCF'!$U$47*(1+K$18)/(($I16-K$18)*(1+$I16)^COUNT('DRE + DCF'!$N$36:$T$36)))+SUM($F$13:$F$14)-$F$12)/$F$10 -> 0.61550521 | L16: =(NPV($I16,'DRE + DCF'!$M$47,'DRE + DCF'!$O$47:$T$47)+('DRE + DCF'!$U$47*(1+L$18)/(($I16-L$18)*(1+$I16)^COUNT('DRE + DCF'!$N$36:$T$36)))+SUM($F$13:$F$14)-$F$12)/$F$10 -> 0.74720667 | M16: =(NPV($I16,'DRE + DCF'!$M$47,'DRE + DCF'!$O$47:$T$47)+('DRE + DCF'!$U$47*(1+M$18)/(($I16-M$18)*(1+$I16)^COUNT('DRE + DCF'!$N$36:$T$36)))+SUM($F$13:$F$14)-$F$12)/$F$10 -> 0.88474602 | N16: =(NPV($I16,'DRE + DCF'!$M$47,'DRE + DCF'!$O$47:$T$47)+('DRE + DCF'!$U$47*(1+N$18)/(($I16-N$18)*(1+$I16)^COUNT('DRE + DCF'!$N$36:$T$36)))+SUM($F$13:$F$14)-$F$12)/$F$10 -> 1.0285202 | O16: =(NPV($I16,'DRE + DCF'!$M$47,'DRE + DCF'!$O$47:$T$47)+('DRE + DCF'!$U$47*(1+O$18)/(($I16-O$18)*(1+$I16)^COUNT('DRE + DCF'!$N$36:$T$36)))+SUM($F$13:$F$14)-$F$12)/$F$10 -> 1.1789631 | P16: =(NPV($I16,'DRE + DCF'!$M$47,'DRE + DCF'!$O$47:$T$47)+('DRE + DCF'!$U$47*(1+P$18)/(($I16-P$18)*(1+$I16)^COUNT('DRE + DCF'!$N$36:$T$36)))+SUM($F$13:$F$14)-$F$12)/$F$10 -> 1.3365495 | Q16: =(NPV($I16,'DRE + DCF'!$M$47,'DRE + DCF'!$O$47:$T$47)+('DRE + DCF'!$U$47*(1+Q$18)/(($I16-Q$18)*(1+$I16)^COUNT('DRE + DCF'!$N$36:$T$36)))+SUM($F$13:$F$14)-$F$12)/$F$10 -> 1.5018008 | ... S16: =(NPV($I16,'DRE + DCF'!$M$47,'DRE + DCF'!$O$47:$T$47)+('DRE + DCF'!$U$47*(1+S$18)/(($I16-S$18)*(1+$I16)^COUNT('DRE + DCF'!$N$36:$T$36)))+SUM($F$13:$F$14)-$F$12)/$F$10 -> 1.8576489
E17: =IFERROR(IF(F17=0,"",IF(F17>0,"Upside","Downside")),"") -> Upside | F17: =IFERROR(F15/F16-1,"") -> 1.6999272e-05 | I17: =I16+0.5% -> 0.19529878 | J17: =(NPV($I17,'DRE + DCF'!$M$47,'DRE + DCF'!$O$47:$T$47)+('DRE + DCF'!$U$47*(1+J$18)/(($I17-J$18)*(1+$I17)^COUNT('DRE + DCF'!$N$36:$T$36)))+SUM($F$13:$F$14)-$F$12)/$F$10 -> 0.064133143 | K17: =(NPV($I17,'DRE + DCF'!$M$47,'DRE + DCF'!$O$47:$T$47)+('DRE + DCF'!$U$47*(1+K$18)/(($I17-K$18)*(1+$I17)^COUNT('DRE + DCF'!$N$36:$T$36)))+SUM($F$13:$F$14)-$F$12)/$F$10 -> 0.17750161 | L17: =(NPV($I17,'DRE + DCF'!$M$47,'DRE + DCF'!$O$47:$T$47)+('DRE + DCF'!$U$47*(1+L$18)/(($I17-L$18)*(1+$I17)^COUNT('DRE + DCF'!$N$36:$T$36)))+SUM($F$13:$F$14)-$F$12)/$F$10 -> 0.29558203 | M17: =(NPV($I17,'DRE + DCF'!$M$47,'DRE + DCF'!$O$47:$T$47)+('DRE + DCF'!$U$47*(1+M$18)/(($I17-M$18)*(1+$I17)^COUNT('DRE + DCF'!$N$36:$T$36)))+SUM($F$13:$F$14)-$F$12)/$F$10 -> 0.4186744 | N17: =(NPV($I17,'DRE + DCF'!$M$47,'DRE + DCF'!$O$47:$T$47)+('DRE + DCF'!$U$47*(1+N$18)/(($I17-N$18)*(1+$I17)^COUNT('DRE + DCF'!$N$36:$T$36)))+SUM($F$13:$F$14)-$F$12)/$F$10 -> 0.54710475 | O17: =(NPV($I17,'DRE + DCF'!$M$47,'DRE + DCF'!$O$47:$T$47)+('DRE + DCF'!$U$47*(1+O$18)/(($I17-O$18)*(1+$I17)^COUNT('DRE + DCF'!$N$36:$T$36)))+SUM($F$13:$F$14)-$F$12)/$F$10 -> 0.68122799 | P17: =(NPV($I17,'DRE + DCF'!$M$47,'DRE + DCF'!$O$47:$T$47)+('DRE + DCF'!$U$47*(1+P$18)/(($I17-P$18)*(1+$I17)^COUNT('DRE + DCF'!$N$36:$T$36)))+SUM($F$13:$F$14)-$F$12)/$F$10 -> 0.82143123 | Q17: =(NPV($I17,'DRE + DCF'!$M$47,'DRE + DCF'!$O$47:$T$47)+('DRE + DCF'!$U$47*(1+Q$18)/(($I17-Q$18)*(1+$I17)^COUNT('DRE + DCF'!$N$36:$T$36)))+SUM($F$13:$F$14)-$F$12)/$F$10 -> 0.96813748 | ... S17: =(NPV($I17,'DRE + DCF'!$M$47,'DRE + DCF'!$O$47:$T$47)+('DRE + DCF'!$U$47*(1+S$18)/(($I17-S$18)*(1+$I17)^COUNT('DRE + DCF'!$N$36:$T$36)))+SUM($F$13:$F$14)-$F$12)/$F$10 -> 1.2829568
E18: TIR | J18: =K18-0.25% -> 0.07 | K18: =L18-0.25% -> 0.0725 | L18: =M18-0.25% -> 0.075 | M18: =N18-0.25% -> 0.0775 | N18: ='DRE + DCF'!W37 -> 0.08 | O18: =N18+0.25% -> 0.0825 | P18: =O18+0.25% -> 0.085 | Q18: =P18+0.25% -> 0.0875 | R18: =Q18+0.25% -> 0.09 | S18: =R18+0.25% -> 0.0925
J19: Growth

Sheet WACC
I5: C&A ($CEAB3)
A7: Páginas
A8: Dashboard
A9: WACC
A10: DRE + DCF | K10: Valor | N10: Descrição
A11: Balanço Patrimonial | E11: DI | K11: 0.1342 | N11: A ponto de partida para encontrar a taxa livre de risco no Brasil é pegar o título pós-fixado sem pagamentos períodicos emitido pelo governo de prazo mais longo.
A12: Projeções | E12: CDS | K12: 0.032 | N12: Credit Default Swap (CDS). Dados: bit.ly/cdsbrasil Como alternativa, usar último dado disponível do EMBI+:bit.ly/2u4NtEm
A13: Lojas | E13: Taxa Livre de Risco | K13: =K11-K12 -> 0.1022
E14: Beta | K14: 2
E15: Prêmio de Risco | K15: 0.065 | N15: Dados Alternativos FGV: https://goo.gl/bBfwGq
E16: Custo de Capital Próprio (Ke) | K16: 0.29675103
E17: Valor de Mercado | K17: 866000 | N17: Número de ações vezes a cotação da ação no último pregão.
E18: Custo de Capital de Terceiros (Kd) | K18: 0.145 | N18: Yield to Maturity da debênture de prazo mais longo da companhia negociada no mercado secundário.
E19: Dívida Bruta | K19: ='Balanço Patrimonial'!L52+'Balanço Patrimonial'!L63 -> 3471349
E20: WACC | K20: =(K16*K17+K18*K19)/SUM(K17,K19) -> 0.17529878

Sheet DRE + DCF
J5: C&A ($CEAB3)
A7: Páginas
A8: Dashboard
A9: WACC
A10: DRE + DCF | F10: 2016 | G10: 2017 | H10: 2018 | I10: 2019 | J10: 2020 | K10: 2021 | L10: 1T2022 | M10: YTG 2022E | N10: 2022 | O10: 2023 | P10: 2024 | Q10: 2025 | R10: =Q10+1 -> 2026 | S10: =R10+1 -> 2027 | T10: =S10+1 -> 2028
A11: Balanço Patrimonial | E11: Receita Líquida | F11: 4780694 | G11: 5035610 | H11: 5139114 | I11: 5285176 | J11: 4085486 | K11: 5153205 | L11: 1197024 | M11: =N11-L11 -> 4397145.6 | N11: ='Projeções - Receita'!L10 -> 5594169.6 | O11: ='Projeções - Receita'!M10 -> 6643601.4 | P11: ='Projeções - Receita'!N10 -> 7910445.7 | Q11: ='Projeções - Receita'!O10 -> 9223569.7 | R11: ='Projeções - Receita'!P10 -> 10319264 | S11: ='Projeções - Receita'!Q10 -> 11455213 | T11: ='Projeções - Receita'!R10 -> 12401748
A12: Projeções | E12: Crescimento da Receita (YoY)¹ | G12: =G11/F11-1 -> 0.053321965 | H12: =H11/G11-1 -> 0.020554411 | I12: =I11/H11-1 -> 0.028421631 | J12: =J11/I11-1 -> -0.22699149 | K12: =K11/J11-1 -> 0.26134443 | N12: =N11/K11-1 -> 0.085570943 | O12: =O11/N11-1 -> 0.18759385 | P12: =P11/O11-1 -> 0.19068637 | Q12: =Q11/P11-1 -> 0.16599874 | R12: =R11/Q11-1 -> 0.11879289 | S12: =S11/R11-1 -> 0.11008039 | T12: =T11/S11-1 -> 0.082629221
A13: Lojas | E13: Custos das Vendas e Serviços | F13: -2775856 | G13: -2614085 | H13: -2589971 | I13: -2717065 | J13: -2188859 | K13: -2755897 | L13: -629605
E14: Lucro Bruto | F14: =F11+F13 -> 2004838 | G14: =G11+G13 -> 2421525 | H14: =H11+H13 -> 2549143 | I14: =I11+I13 -> 2568111 | J14: =J11+J13 -> 1896627 | K14: =K11+K13 -> 2397308 | L14: =L11+L13 -> 567419
E15: Margem Bruta | F15: =F14/F11 -> 0.41936129 | G15: =G14/G11 -> 0.48088017 | H15: =H14/H11 -> 0.49602772 | I15: =I14/I11 -> 0.48590832 | J15: =J14/J11 -> 0.46423534 | K15: =K14/K11 -> 0.46520719 | L15: =L14/L11 -> 0.47402475
E16: Despesas/ Receitas Operacionais | F16: =F17+F18+F19 -> -2012392 | G16: =G17+G18+G19 -> -2124825 | H16: =H17+H18+H19 -> -2192922 | I16: =I17+I18+I19 -> -1535027 | J16: =J17+J18+J19 -> -2060865 | K16: =K17+K18+K19 -> -2304510 | L16: =L17+L18+L19 -> -738362
E17: Despesas com Vendas | F17: -1536151 | G17: -1596848 | H17: -1699883 | I17: -1755337 | J17: -1648437 | K17: -2025632 | L17: -559936
E18: Despesas Gerais e Administrativas | F18: -481679 | G18: -509821 | H18: -482233 | I18: -498019 | J18: -491704 | K18: -487881 | L18: -175828
E19: Resultado Operacional Outros | F19: 5438 | G19: -18156 | H19: -10806 | I19: =SUM(I20:I21) -> 718329 | J19: =SUM(J20:J21) -> 79276 | K19: =SUM(K20:K21) -> 209003 | L19: =SUM(L20:L21) -> -2598
E20: Outras Receitas Operacionais | F20: 0 | G20: 20964 | H20: 2106 | I20: 773960 | J20: 170721 | K20: 234525 | L20: 10197
E21: Outras Despesas Operacionais | F21: 0 | G21: -39120 | H21: -12912 | I21: -55631 | J21: -91445 | K21: -25522 | L21: -12795
E22: EBIT | F22: =F14+F16 -> -7554 | G22: =G14+G16 -> 296700 | H22: =H14+H16 -> 356221 | I22: =I14+I16 -> 1033084 | J22: =J14+J16 -> -164238 | K22: =K14+K16 -> 92798 | L22: =L14+L16 -> -170943
E23: Margem EBIT | F23: =F22/F11 -> -0.0015801053 | G23: =G22/G11 -> 0.058920369 | H23: =H22/H11 -> 0.069315645 | I23: =I22/I11 -> 0.19546823 | J23: =J22/J11 -> -0.040200358 | K23: =K22/K11 -> 0.018007822 | L23: =L22/L11 -> -0.14280666
E24: Eventos não recorrentes | F24: ='DRE - Contas Abertas'!F58 -> 0 | G24: ='DRE - Contas Abertas'!G58 -> 0 | H24: ='DRE - Contas Abertas'!H58 -> 0 | I24: ='DRE - Contas Abertas'!I58 -> 717165 | J24: ='DRE - Contas Abertas'!J58 -> 94779 | K24: ='DRE - Contas Abertas'!K58 -> 210451
E25: EBIT Recorrente | F25: ='DRE - Contas Abertas'!F59 -> -7554 | G25: ='DRE - Contas Abertas'!G59 -> 296700 | H25: ='DRE - Contas Abertas'!H59 -> 356221 | I25: ='DRE - Contas Abertas'!I59 -> 315919 | J25: ='DRE - Contas Abertas'!J59 -> -259017 | K25: ='DRE - Contas Abertas'!K59 -> -117653 | L25: =L22-L24 -> -170943 | M25: =N25-L25 -> -228503.67 | N25: ='Projeções - EBIT'!K10 -> -399446.67 | O25: ='Projeções - EBIT'!L10 -> -379456.58 | P25: ='Projeções - EBIT'!M10 -> -283298.24 | Q25: ='Projeções - EBIT'!N10 -> 365925.88 | R25: ='Projeções - EBIT'!O10 -> 604135.52 | S25: ='Projeções - EBIT'!P10 -> 900051.54 | T25: ='Projeções - EBIT'!Q10 -> 1090351.8
E26: Margem EBIT Recorrente | F26: ='DRE - Contas Abertas'!F60 -> -0.0015801053 | G26: ='DRE - Contas Abertas'!G60 -> 0.058920369 | H26: ='DRE - Contas Abertas'!H60 -> 0.069315645 | I26: ='DRE - Contas Abertas'!I60 -> 0.059774547 | J26: ='DRE - Contas Abertas'!J60 -> -0.063399312 | K26: =K22/K11 -> 0.018007822 | L26: =L22/L11 -> -0.14280666 | M26: =M22/M11 -> 0 | N26: =N25/N11 -> -0.071404104 | O26: =O25/O11 -> -0.057116097 | P26: =P25/P11 -> -0.035813183 | Q26: =Q25/Q11 -> 0.039672913 | R26: =R25/R11 -> 0.058544438 | S26: =S25/S11 -> 0.078571351 | T26: =T25/T11 -> 0.087919206
E27: Resultado Financeiro | F27: =SUM(F28:F29) -> -197360 | G27: =SUM(G28:G29) -> -155153 | H27: =SUM(H28:H29) -> -130671 | I27: =SUM(I28:I29) -> 388942 | J27: =SUM(J28:J29) -> -91435 | K27: =SUM(K28:K29) -> -91807 | L27: =SUM(L28:L29) -> -68568
E28: Receitas Financeiras | F28: 514398 | G28: 168253 | H28: 186189 | I28: 670833 | J28: 134345 | K28: 176189 | L28: 41764
E29: Despesas Financeiras | F29: -711758 | G29: -323406 | H29: -316860 | I29: -281891 | J29: -225780 | K29: -267996 | L29: -110332
E30: Resultado Antes dos Tributos Sobre o Lucro | F30: =F22+F27 -> -204914 | G30: =G22+G27 -> 141547 | H30: =H22+H27 -> 225550 | I30: =I22+I27 -> 1422026 | J30: =J22+J27 -> -255673 | K30: =K22+K27 -> 991 | L30: =L22+L27 -> -239511
E31: Imposto de Renda e CSLL | F31: 63642 | G31: -44667 | H31: -51914 | I31: -450033 | J31: 89341 | K31: 328018 | L31: 86781
E32: Lucro Líquido | F32: =F30+F31 -> -141272 | G32: =G30+G31 -> 96880 | H32: =H30+H31 -> 173636 | I32: =I30+I31 -> 971993 | J32: =J30+J31 -> -166332 | K32: =K30+K31 -> 329009 | L32: =L30+L31 -> -152730
E33: Margem Líquida | F33: =F32/F11 -> -0.029550521 | G33: =G32/G11 -> 0.01923898 | H33: =H32/H11 -> 0.033787147 | I33: =I32/I11 -> 0.1839093 | J33: =J32/J11 -> -0.040712904 | K33: =K32/K11 -> 0.06384551 | L33: =L32/L11 -> -0.12759143
F36: 2016 | G36: 2017 | H36: 2018 | I36: 2019 | J36: 2020 | K36: 2021 | L36: 1T2022 | M36: YTG 2022E | N36: 2022 | O36: 2023 | P36: 2024 | Q36: 2025 | R36: =Q36+1 -> 2026 | S36: =R36+1 -> 2027 | T36: =S36+1 -> 2028 | U36: Perpetuidade | V36: ROIC Perp. | W36: Growth
E37: Alíquota Efetiva | F37: =IFERROR(IF(F22>0,-F31/F22,"-"),"-") -> - | G37: =IFERROR(IF(G22>0,-G31/G22,"-"),"-") -> 0.15054601 | H37: =IFERROR(IF(H22>0,-H31/H22,"-"),"-") -> 0.14573537 | I37: =IFERROR(IF(I22>0,-I31/I22,"-"),"-") -> 0.43562092 | J37: =IFERROR(IF(J22>0,-J31/J22,"-"),"-") -> - | K37: =IFERROR(IF(K22>0,"-","-"),"-") -> - | L37: =IFERROR(IF(L22>0,"-","-"),"-") -> - | Q37: 0.0851 | R37: 0.0851 | S37: 0.0851 | T37: 0.0851 | U37: 0.34 | V37: 0.133 | W37: 0.08
E38: D&A do Arrendamento | F38: ='Projeções - Capex + CG'!F27 -> 0 | G38: ='Projeções - Capex + CG'!G27 -> 0 | H38: ='Projeções - Capex + CG'!H27 -> 0 | I38: ='Projeções - Capex + CG'!I27 -> 295675 | J38: ='Projeções - Capex + CG'!J27 -> 306443 | K38: ='Projeções - Capex + CG'!K27 -> 338325 | L38: 94542 | M38: =N38-L38 -> 290876.88 | N38: =N39*N11 -> 385418.88 | O38: =O39*O11 -> 457721.09 | P38: =P39*P11 -> 545002.26 | Q38: =Q39*Q11 -> 635471.95 | R38: =R39*R11 -> 710961.5 | S38: =S39*S11 -> 789224.42 | T38: =T39*T11 -> 854437.42 | U38: =U39*T11 -> 854437.42
E39: (%) da Receita Líquida | F39: =F38/F11 -> 0 | G39: =G38/G11 -> 0 | H39: =H38/H11 -> 0 | I39: =I38/I11 -> 0.055944211 | J39: =J38/J11 -> 0.075007722 | K39: =K38/K11 -> 0.065653317 | L39: =L38/L11 -> 0.078980873 | M39: =AVERAGE(I39:L39) -> 0.068896531 | N39: =M39 -> 0.068896531 | O39: =N39 -> 0.068896531 | P39: =O39 -> 0.068896531 | Q39: =P39 -> 0.068896531 | R39: =Q39 -> 0.068896531 | S39: =R39 -> 0.068896531 | T39: =S39 -> 0.068896531 | U39: =T39 -> 0.068896531
E40: NOPAT | F40: =F22+F31+F38 -> 56088 | G40: =G22+G31+G38 -> 252033 | H40: =H22+H31+H38 -> 304307 | I40: =(I22-'DRE - Contas Abertas'!I58*(1-N37))+I38 -> 611594 | J40: =J22+J31+J38 -> 231546 | K40: =K22+K31+K38 -> 759141 | L40: =L22+L31+L38 -> 10380 | M40: =N40-L40 -> -24407.788 | N40: =N25*(1-N37)+N38 -> -14027.788 | O40: =O25*(1-O37)+O38 -> 78264.509 | P40: =P25*(1-P37)+P38 -> 261704.02 | Q40: =Q25*(1-Q37)+Q38 -> 970257.54 | R40: =R25*(1-R37)+R38 -> 1263685.1 | S40: =S25*(1-S37)+S38 -> 1612681.6 | T40: =T25*(1-T37)+T38 -> 1852000.3 | U40: =T25*(1-U37)+U38 -> 1574069.6
E41: Taxa de Reinvestimento | F41: =IFERROR(SUM(F42,F46)/(F40),0) -> -1.6489089 | G41: =IFERROR(SUM(G42,G46)/(G40),0) -> -0.84268766 | H41: =IFERROR(SUM(H42,H46)/(H40),0) -> 0.42887479 | I41: =IFERROR(SUM(I42,I46)/(I40),0) -> -0.0041194812 | J41: =IFERROR(SUM(J42,J46)/(J40),0) -> -0.93123721 | K41: =IFERROR(SUM(K42,K46)/(K40),0) -> 0.55574126 | L41: =IFERROR(SUM(L42,L46)/(L40),0) -> 56.059163 | M41: =IFERROR(SUM(M42,M46)/(M40),0) -> 6.1872878 | ... T41: =IFERROR(SUM(T42,T46)/(T40),0) -> 0.45068205 | U41: =W37/V37 -> 0.60150376
E42: CAPEX Líquido | F42: =F43-F44 -> -92484 | G42: =G43-G44 -> -98997 | H42: =H43-H44 -> 34609 | I42: =I43-I44 -> 85658 | J42: =J43-J44 -> 56178 | K42: =K43-K44 -> 435445 | L42: =L43-L44 -> -25315 | M42: =N42-L42 -> 149763.77 | N42: =IF((N43-N44)>0,N43-N44,0) -> 124448.77 | O42: =IF((O43-O44)>0,O43-O44,0) -> 582096.09 | P42: =IF((P43-P44)>0,P43-P44,0) -> 77606.101 | Q42: =IF((Q43-Q44)>0,Q43-Q44,Q44) -> 532985.48 | R42: =IF((R43-R44)>0,R43-R44,R44) -> 596300.36 | S42: =IF((S43-S44)>0,S43-S44,S44) -> 661941.33 | T42: =IF((T43-T44)>0,T43-T44,T44) -> 716637.03
E43: CAPEX | F43: ='Projeções - Capex + CG'!F14 -> 110200 | G43: ='Projeções - Capex + CG'!G14 -> 98900 | H43: ='Projeções - Capex + CG'!H14 -> 239700 | I43: ='Projeções - Capex + CG'!I14 -> 318700 | J43: ='Projeções - Capex + CG'!J14 -> 302500 | K43: ='Projeções - Capex + CG'!K14 -> 682100 | L43: 55500 | M43: =N43-L43 -> 392208.77 | N43: ='Projeções - Capex + CG'!L14 -> 447708.77 | O43: ='Projeções - Capex + CG'!M14 -> 965997.68 | P43: ='Projeções - Capex + CG'!N14 -> 534712.49 | Q43: ='Projeções - Capex + CG'!O14 -> 517013.57 | R43: ='Projeções - Capex + CG'!P14 -> 327645.23 | S43: ='Projeções - Capex + CG'!Q14 -> 363130.11 | T43: ='Projeções - Capex + CG'!R14 -> 401381.77
E44: Depreciação & Amortização | F44: ='Projeções - Capex + CG'!F25 -> 202684 | G44: ='Projeções - Capex + CG'!G25 -> 197897 | H44: ='Projeções - Capex + CG'!H25 -> 205091 | I44: ='Projeções - Capex + CG'!I25 -> 233042 | J44: ='Projeções - Capex + CG'!J25 -> 246322 | K44: ='Projeções - Capex + CG'!K25 -> 246655 | L44: 80815 | M44: =N44-L44 -> 242445 | N44: =L44*4 -> 323260 | O44: =O45*O11 -> 383901.59 | P44: =P45*P11 -> 457106.39 | Q44: =Q45*Q11 -> 532985.48 | R44: =R45*R11 -> 596300.36 | S44: =S45*S11 -> 661941.33 | T44: =T45*T11 -> 716637.03
E45: (%) da Receita Líquida | F45: =F44/F11 -> 0.042396355 | G45: =G44/G11 -> 0.039299509 | H45: =H44/H11 -> 0.039907852 | I45: =I44/I11 -> 0.044093517 | J45: =J44/J11 -> 0.06029197 | K45: =K44/K11 -> 0.047864387 | L45: =L44/L11 -> 0.067513266 | M45: =M44/M11 -> 0.055136905 | N45: =N44/N11 -> 0.057785162 | O45: =N45 -> 0.057785162 | P45: =O45 -> 0.057785162 | Q45: =P45 -> 0.057785162 | R45: =Q45 -> 0.057785162 | S45: =R45 -> 0.057785162 | T45: =S45 -> 0.057785162
E46: ∆ Capital de Giro | G46: ='Projeções - Capex + CG'!G11-'Projeções - Capex + CG'!F11 -> -113388.1 | H46: ='Projeções - Capex + CG'!H11-'Projeções - Capex + CG'!G11 -> 95900.6 | I46: ='Projeções - Capex + CG'!I11-'Projeções - Capex + CG'!H11 -> -88177.45 | J46: ='Projeções - Capex + CG'!J11-'Projeções - Capex + CG'!I11 -> -271802.25 | K46: ='Projeções - Capex + CG'!K11-'Projeções - Capex + CG'!J11 -> -13559.025 | L46: ='Balanço Patrimonial'!L9-'Balanço Patrimonial'!K9 -> 607209.12 | M46: =N46-L46 -> -300781.78 | N46: ='Projeções - Capex + CG'!L11-'Projeções - Capex + CG'!K11 -> 306427.33 | O46: ='Projeções - Capex + CG'!M11-'Projeções - Capex + CG'!L11 -> 130856.74 | P46: ='Projeções - Capex + CG'!N11-'Projeções - Capex + CG'!M11 -> 157966.53 | Q46: ='Projeções - Capex + CG'!O11-'Projeções - Capex + CG'!N11 -> 163737.3 | R46: ='Projeções - Capex + CG'!P11-'Projeções - Capex + CG'!O11 -> 136625.36 | S46: ='Projeções - Capex + CG'!Q11-'Projeções - Capex + CG'!P11 -> 141644.77 | T46: ='Projeções - Capex + CG'!R11-'Projeções - Capex + CG'!Q11 -> 118026.27
E47: FCFF | F47: =(F40)*(1-F41) -> 148572 | G47: =(G40)*(1-G41) -> 464418.1 | H47: =(H40)*(1-H41) -> 173797.4 | I47: =(I40)*(1-I41) -> 614113.45 | J47: =(J40)*(1-J41) -> 447170.25 | K47: =(K40)*(1-K41) -> 337255.02 | L47: =(L40)*(1-L41) -> -571514.12 | M47: =(M40)*(1-M41) -> 126610.22 | ... U47: =(U40)*(1-U41) -> 627260.83
E48: ROIC | F48: =(F40)/('Balanço Patrimonial'!F57+'Balanço Patrimonial'!F52+'Balanço Patrimonial'!F64+'Balanço Patrimonial'!F65+'Balanço Patrimonial'!F67+'Balanço Patrimonial'!F82-'Balanço Patrimonial'!F14) -> 0.030416282 | G48: =(G40)/('Balanço Patrimonial'!G57+'Balanço Patrimonial'!G52+'Balanço Patrimonial'!G64+'Balanço Patrimonial'!G65+'Balanço Patrimonial'!G67+'Balanço Patrimonial'!G82-'Balanço Patrimonial'!G14) -> 0.14977 | H48: =(H40)/('Balanço Patrimonial'!H57+'Balanço Patrimonial'!H52+'Balanço Patrimonial'!H64+'Balanço Patrimonial'!H65+'Balanço Patrimonial'!H67+'Balanço Patrimonial'!H82-'Balanço Patrimonial'!H14) -> 0.16679988 | I48: =(I40)/('Balanço Patrimonial'!I57+'Balanço Patrimonial'!I52+'Balanço Patrimonial'!I64+'Balanço Patrimonial'!I65+'Balanço Patrimonial'!I67+'Balanço Patrimonial'!I82-'Balanço Patrimonial'!I14) -> 0.14983478 | J48: =(J40)/('Balanço Patrimonial'!J57+'Balanço Patrimonial'!J52+'Balanço Patrimonial'!J64+'Balanço Patrimonial'!J65+'Balanço Patrimonial'!J67+'Balanço Patrimonial'!J82-'Balanço Patrimonial'!J14) -> 0.055813151 | K48: =(K40)/('Balanço Patrimonial'!K57+'Balanço Patrimonial'!K52+'Balanço Patrimonial'!K64+'Balanço Patrimonial'!K65+'Balanço Patrimonial'!K67+'Balanço Patrimonial'!K82-'Balanço Patrimonial'!K14) -> 0.14265336 | N48: =AVERAGE($G$48:$K$48) -> 0.13297423 | O48: =AVERAGE($G$48:$K$48) -> 0.13297423 | P48: =AVERAGE($G$48:$K$48) -> 0.13297423 | Q48: =AVERAGE($G$48:$K$48) -> 0.13297423 | R48: =AVERAGE($G$48:$K$48) -> 0.13297423 | S48: =AVERAGE($G$48:$K$48) -> 0.13297423 | T48: =AVERAGE($G$48:$K$48) -> 0.13297423
E50: ¹- "YoY", ou "year over year", significa "de um ano pro outro".
P59: Aliquota | Q59: 0.34
P60: TR | Q60: 0.6
P61: ROIC | Q61: 0.13

Sheet DRE - Contas Abertas
A7: Páginas
A8: Dashboard
A9: WACC | F9: 2016 | G9: 2017 | H9: 2018 | I9: 2019 | J9: 2020 | K9: 2021
A10: DRE + DCF | E10: Pessoal | F10: -585593 | G10: -585653 | H10: -556853 | I10: -579633 | J10: -488088 | K10: -598914
A11: Balanço Patrimonial | E11: Material/Serviços de terceiros | F11: -147630 | G11: -143144 | H11: -208540 | I11: -203002 | J11: -275228 | K11: -324160
A12: Projeções | E12: Depreciação de direito de uso | F12: 0 | G12: 0 | H12: 0 | I12: -248687 | J12: -257798 | K12: -285667
A13: Lojas | E13: Depreciação e amortização | F13: -141898 | G13: -135358 | H13: -142604 | I13: -155499 | J13: -163352 | K13: -144330
E14: Ocupação | F14: -445775 | G14: -494621 | H14: -526073 | I14: -280085 | J14: -148137 | K14: -294022
E15: Publicidade e Promoção | F15: -115738 | G15: -96180 | H15: -122219 | I15: -109993 | J15: -185169 | K15: -211744
E16: Perdas em créditos, líquidas | F16: 0 | G16: 0 | H16: 0 | I16: 0 | J16: 0 | K16: 0
E17: Outros | F17: -99517 | G17: -141892 | H17: -163916 | I17: -178438 | J17: -130665 | K17: -166795
E18: Total: | F18: =F10+F11+F12+F13+F14+F15+F17+F16 -> -1536151 | G18: =G10+G11+G12+G13+G14+G15+G17+G16 -> -1596848 | H18: =H10+H11+H12+H13+H14+H15+H17+H16 -> -1720205 | I18: =I10+I11+I12+I13+I14+I15+I17+I16 -> -1755337 | J18: =J10+J11+J12+J13+J14+J15+J17+J16 -> -1648437 | K18: =K10+K11+K12+K13+K14+K15+K17+K16 -> -2025632
F22: 2016 | G22: 2017 | H22: 2018 | I22: 2019 | J22: 2020 | K22: 2021
E23: Pessoal | F23: -217453 | G23: -240665 | H23: -265938 | I23: -271698 | J23: -263249 | K23: -254763
E24: Material/Serviços de terceiros | F24: -149311 | G24: -155498 | H24: -115322 | I24: -104330 | J24: -123492 | K24: -127569
E25: Depreciação de direito de uso | F25: 0 | G25: 0 | H25: 0 | I25: -77544 | J25: -82981 | K25: -102325
E26: Depreciação e amortização | F26: -59975 | G26: -62258 | H26: -62620 | I26: -20066 | J26: -20816 | K26: -22319
E27: Ocupação | F27: -32088 | G27: -33185 | H27: -31283 | I27: -6621 | J27: -1746 | K27: -5727
E28: Outros | F28: -22852 | G28: -18215 | H28: 13252 | I28: -17760 | J28: 580 | K28: 24822
E29: Total: | F29: =F23+F24+F25+F26+F27+F28 -> -481679 | G29: =G23+G24+G25+G26+G27+G28 -> -509821 | H29: =H23+H24+H25+H26+H27+H28 -> -461911 | I29: =I23+I24+I25+I26+I27+I28 -> -498019 | J29: =J23+J24+J25+J26+J27+J28 -> -491704 | K29: =K23+K24+K25+K26+K27+K28 -> -487881
F33: 2016 | G33: 2017 | H33: 2018 | I33: 2019 | J33: 2020 | K33: 2021
E34: Resultado na baixa de ativos | F34: -1661 | G34: -20964 | H34: -12912 | I34: -34133 | J34: -7592 | K34: -2529
E35: Reversão (provisão) impairment: | F35: =F36+F37 -> 0 | G35: =G36+G37 -> 0 | H35: =H36+H37 -> 0 | I35: =I36+I37 -> 26382 | J35: =J36+J37 -> 6151 | K35: =K36+K37 -> 3901
E36: Encerramento/reforma de lojas | F36: 0 | G36: 0 | H36: 0 | I36: 15118 | J36: 5147 | K36: -2220
E37: Teste de recuperabilidade | F37: 0 | H37: 0 | I37: 11264 | J37: 1004 | K37: 6121
E38: Recuperação de créditos fiscais: | F38: =F39+F40+F41+F42+F43+F44 -> 0 | G38: =G39+G40+G41+G42+G43+G44 -> 0 | H38: =H39+H40+H41+H42+H43+H44 -> 0 | I38: =I39+I40+I41+I42+I43+I44 -> 644893 | J38: =J39+J40+J41+J42+J43+J44 -> 150429 | K38: 228404
E39: ICMS na base de cálculo PIS/COFINS | F39: 0 | G39: 0 | H39: 0 | I39: 663538 | J39: 0 | K39: 0
E40: Ação Judicial ZFM e Reintegra | F40: 0 | G40: 0 | H40: 0 | I40: 0 | J40: 94902 | K40: 0
E41: PIS/COFINS importação base de cálculo | F41: 0 | G41: 0 | H41: 0 | I41: 0 | J41: 47654 | K41: 0
E42: Créditos previdenciários | F42: 0 | G42: 0 | H42: 0 | I42: 0 | J42: 22014 | K42: 0
E43: Outros créditos fiscais | F43: 0 | G43: 0 | H43: 0 | I43: 2853 | J43: 0 | K43: 0
E44: Despesas relacionadas aos créditos fiscais | F44: 0 | G44: 0 | H44: 0 | I44: -21498 | J44: -14141 | K44: 0
E45: Reversão (provisão) contingências tributárias | F45: 0 | G45: 0 | H45: 0 | I45: 72272 | J45: -25791 | K45: -13644
E46: Consultorias estratégicas | F46: 0 | G46: 0 | H46: 0 | I46: 0 | J46: -29859 | K46: -4309
E47: Depreciação e amortizção | F47: -811 | G47: -281 | H47: 0 | I47: 0 | J47: 0 | K47: 0
E48: Perdas de Créditos Líquidas | F48: 0 | G48: 0 | H48: 0 | I48: 0 | J48: 0 | K48: -492
E49: Outros | F49: 7910 | G49: 3089 | H49: 2106 | I49: 8915 | J49: -14062 | K49: -2328
E50: Total: | F50: =F34+F35+F38+F45+F46+F47+F49+F48 -> 5438 | G50: =G34+G35+G38+G45+G46+G47+G49+G48 -> -18156 | H50: =H34+H35+H38+H45+H46+H47+H49+H48 -> -10806 | I50: =I34+I35+I38+I45+I46+I47+I49+I48 -> 718329 | J50: =J34+J35+J38+J45+J46+J47+J49+J48 -> 79276 | K50: =K34+K35+K38+K45+K46+K47+K49+K48 -> 209003
F54: 2016 | G54: 2017 | H54: 2018 | I54: 2019 | J54: 2020 | K54: 2021
E55: Lucro Bruto | F55: ='DRE + DCF'!F14 -> 2004838 | G55: ='DRE + DCF'!G14 -> 2421525 | H55: ='DRE + DCF'!H14 -> 2549143 | I55: ='DRE + DCF'!I14 -> 2568111 | J55: ='DRE + DCF'!J14 -> 1896627 | K55: ='DRE + DCF'!K14 -> 2397308
E56: EBIT | F56: =F55+F50+F29+F18 -> -7554 | G56: =G55+G50+G29+G18 -> 296700 | H56: =H55+H50+H29+H18 -> 356221 | I56: =I55+I50+I29+I18 -> 1033084 | J56: =J55+J50+J29+J18 -> -164238 | K56: =K55+K50+K29+K18 -> 92798
E57: Margem EBIT | F57: =F$56/'DRE + DCF'!F11 -> -0.0015801053 | G57: =G56/'DRE + DCF'!G11 -> 0.058920369 | H57: =H56/'DRE + DCF'!H11 -> 0.069315645 | I57: =I56/'DRE + DCF'!I11 -> 0.19546823 | J57: =J56/'DRE + DCF'!J11 -> -0.040200358 | K57: -0.040200358
E58: Eventos não recorrentes | F58: =F39+F40+F41+F42+F43+F44+F46+F45 -> 0 | G58: =G39+G40+G41+G42+G43+G44+G46+G45 -> 0 | H58: =H39+H40+H41+H42+H43+H44+H46+H45 -> 0 | I58: =I39+I40+I41+I42+I43+I44+I46+I45 -> 717165 | J58: =J39+J40+J41+J42+J43+J44+J46+J45 -> 94779 | K58: =K38+K46+K45 -> 210451
E59: EBIT recorrente | F59: =F56-F58 -> -7554 | G59: =G56-G58 -> 296700 | H59: =H56-H58 -> 356221 | I59: =I56-I58 -> 315919 | J59: =J56-J58 -> -259017 | K59: =K56-K58 -> -117653
E60: Margem EBIT recorrente | F60: =F59/'DRE + DCF'!F11 -> -0.0015801053 | G60: =G59/'DRE + DCF'!G11 -> 0.058920369 | H60: =H59/'DRE + DCF'!H11 -> 0.069315645 | I60: =I59/'DRE + DCF'!I11 -> 0.059774547 | J60: =J59/'DRE + DCF'!J11 -> -0.063399312 | K60: -0.069712147
F65: 2016 | G65: 2017 | H65: 2018 | I65: 2019 | J65: 2020 | K65: 2021
E66: Juros sobre empréstimos – partes relacionadas | F66: -96056 | G66: -69318 | H66: -41149 | I66: -60749 | J66: 0 | K66: 0
E67: Juros sobre empréstimos – terceiros | F67: 0 | G67: 0 | H67: 0 | I67: 0 | J67: -35805 | K67: -81458
E68: Despesas bancárias e IOF | F68: -5934 | G68: -5204 | H68: -3298 | I68: -4156 | J68: -1845 | K68: -2816
E69: Juros sobre impostos e contingências | F69: -37803 | G69: -35466 | H69: -27803 | I69: -28218 | J69: -27162 | K69: -14462
E70: Juros sobre arrendamento | F70: 0 | G70: 0 | H70: 0 | I70: -137478 | J70: -131790 | K70: -135412
E71: Despesa financeira de fornecedores – AVP | F71: -40795 | G71: -38859 | H71: -23132 | I71: -24983 | J71: -15377 | K71: -28604
E72: Resultados com derivativos | F72: -304257 | G72: -30206 | H72: 0 | I72: -26054 | J72: 0 | K72: 0
E73: Variação Cambial | F73: -226702 | G73: -144204 | H73: -221464 | I73: 29562 | J73: -11700 | K73: -691
E74: Compras | F74: 0 | G74: 0 | H74: 0 | I74: -2810 | J74: -11700 | K74: 0
E75: Empréstimos partes relacionadas | F75: 0 | G75: 0 | H75: 0 | I75: 32372 | J75: 0 | K75: 0
E76: Outros | F76: -211 | G76: -149 | H76: -14 | I76: -253 | J76: -2101 | K76: -4553
E77: Total: | F77: =F66+F68+F69+F71+F72+F73+F76 -> -711758 | G77: =G66+G68+G69+G71+G72+G73+G76 -> -323406 | H77: =H66+H68+H69+H71+H72+H73+H76 -> -316860 | I77: -252329 | J77: =J67+J68+J69+J70+J71+J73+J76 -> -225780 | K77: =K67+K68+K69+K70+K71+K73+K76 -> -267996
F81: 2016 | G81: 2017 | H81: 2018 | I81: 2019 | J81: 2020 | K81: 2021
E82: Juros sobre aplicação financeira | F82: 42864 | G82: 7606 | H82: 14339 | I82: 19443 | J82: 24418 | K82: 126381
E83: Juros e atualização monetária | F83: 0 | G83: 0 | H83: 0 | I83: 0 | J83: 0 | K83: 37368
E84: Atualização dos créditos tributários extemporâneos de PIS COFINS | F84: 0 | G84: 0 | H84: 0 | I84: 618492 | J84: 17683 | K84: 0
E85: Atualização dos créditos tributários da ação judicial da Zona Franca de Manaus | F85: 0 | G85: 0 | H85: 0 | I85: 0 | J85: 40642 | K85: 0
E86: Tributação pelo PIS/COFINS | F86: 0 | G86: 0 | H86: 0 | I86: -28760 | J86: 0 | K86: 0
E87: Créditos extemporâneos de PIS/COFINS - Importação | F87: 0 | G87: 0 | H87: 0 | I87: 0 | J87: 33539 | K87: 0
E88: Receita financeira de fornecedores | F88: 10787 | G88: 21662 | H88: 24432 | I88: 31730 | J88: 16969 | K88: 12438
E89: Resultados com derivativos | F89: 0 | G89: 0 | H89: 17192 | I89: 0 | J89: 0 | K89: 0
E90: Variação Cambial | F90: 448140 | G90: 115825 | H90: 122994 | I90: 0 | J90: 0 | K90: 0
E91: Outros | F91: 12607 | G91: 23160 | H91: 7232 | I91: 366 | J91: 1094 | K91: 2
E92: Total: | F92: =F82+F84+F85+F86+F87+F88+F89+F90+F91+F83 -> 514398 | G92: =G82+G84+G85+G86+G87+G88+G89+G90+G91+G83 -> 168253 | H92: =H82+H84+H85+H86+H87+H88+H89+H90+H91+H83 -> 186189 | I92: =I82+I84+I85+I86+I87+I88+I89+I90+I91+I83 -> 641271 | J92: =J82+J84+J85+J86+J87+J88+J89+J90+J91+J83 -> 134345 | K92: =K82+K84+K85+K86+K87+K88+K89+K90+K91+K83 -> 176189
F96: 2016 | G96: 2017 | H96: 2018 | I96: 2019 | J96: 2020 | K96: 2021
E97: EBIT Recorrente | F97: =F59 -> -7554 | G97: =G59 -> 296700 | H97: =H59 -> 356221 | I97: =I59 -> 315919 | J97: =J59 -> -259017 | K97: =K59 -> -117653
E98: Lucro antes do IR Não Recorrente | F98: =F59+F77+F92 -> -204914 | G98: =G59+G77+G92 -> 141547 | H98: =H59+H77+H92 -> 225550 | I98: =I59+I77+I92 -> 704861 | J98: =J59+J77+J92 -> -350452 | K98: =K59+K77+K92 -> -209460
E99: Eventos não recorrentes | F99: =F84+F86+F85+F87+F89 -> 0 | G99: =G84+G86+G85+G87+G89 -> 0 | H99: =H84+H86+H85+H87+H89 -> 17192 | I99: =I84+I86+I85+I87+I89 -> 589732 | J99: =J84+J86+J85+J87+J89 -> 91864 | K99: =K83 -> 37368
E100: Lucro Antes do IR Recorrente | F100: =F98-F99 -> -204914 | G100: =G98-G99 -> 141547 | H100: =H98-H99 -> 208358 | I100: =I98-I99 -> 115129 | J100: =J98-J99 -> -442316 | K100: =K98-K99 -> -246828
F104: 2016 | G104: 2017 | H104: 2018 | I104: 2019 | J104: 2020 | K104: 2021
E105: Lucro (prejuízo) líquido antes de imposto Recorrente | F105: =F100 -> -204914 | G105: =G100 -> 141547 | H105: =H100 -> 208358 | I105: =I100 -> 115129 | J105: =J100 -> -442316 | K105: =K100 -> -246828
E106: Alíquota Vigente | F106: 0.34 | G106: 0.34 | H106: 0.34 | I106: 0.34 | J106: 0.34 | K106: 0.34
E107: Expectativa de despesa de acordo com alíquota vigente | F107: =-F105*F106 -> 69670.76 | G107: =-G105*G106 -> -48125.98 | H107: =-H105*H106 -> -70841.72 | I107: =-I105*I106 -> -39143.86 | J107: =-J105*J106 -> 150387.44 | K107: =-K105*K106 -> 83921.52
E108: Efeito Fiscal das adiçoes e exclusões permanentes:
E109: Equivalência Patrimonial | F109: 0 | G109: 0 | H109: 0 | I109: 0 | J109: 0 | K109: 0
E110: Juros sobre Capital Próprio | F110: 0 | G110: 22329 | H110: 23432 | I110: 26565 | J110: 0 | K110: 0
E111: Doações não dedutíveis | F111: -1461 | G111: -2224 | H111: -1520 | I111: 0 | J111: -1894 | K111: -1872
E112: PAT e Lei de Incentivo à cultura | F112: 0 | G112: 52 | H112: 476 | I112: 4951 | J112: 607 | K112: 0
E113: Ajustes de transfer pricing e incentivo à Inovação tecnológica (P&D) | F113: -3515 | G113: -15427 | H113: 1109 | I113: 1973 | J113: 509 | K113: -70
E114: Brindes e multas não dedutíveis | F114: 0 | G114: -488 | H114: 536 | I114: 0 | J114: -611 | K114: -1114
E115: Subvenção para Investimento | F115: 0 | G115: 0 | H115: 0 | I115: 0 | J115: 637 | K115: 3291
E116: IR e CS de exercícios anteriores | F116: 0 | G116: 0 | H116: 0 | I116: 0 | J116: 0 | K116: -261
E117: Instrumentos Patrimoniais Outorgados | F117: 0 | G117: 0 | H117: 0 | I117: 0 | J117: 385 | K117: 0
E118: Outras adições e exclusões | F118: -1053 | G118: -783 | H118: 740 | I118: -81 | J118: 2755 | K118: 144
E119: Indébito tributário | F119: 0 | G119: 0 | H119: 0 | I119: 0 | J119: 0 | K119: 330631
E120: IRPJ + CSLL | F120: =F107+F109+F110+F111+F112+F113+F114+F115+F117+F118+F119+F116 -> 63641.76 | G120: =G107+G109+G110+G111+G112+G113+G114+G115+G117+G118+G119+G116 -> -44666.98 | H120: =H107+H109+H110+H111+H112+H113+H114+H115+H117+H118+H119+H116 -> -46068.72 | I120: =I107+I109+I110+I111+I112+I113+I114+I115+I117+I118+I119+I116 -> -5735.86 | J120: =J107+J109+J110+J111+J112+J113+J114+J115+J117+J118+J119+J116 -> 152775.44 | K120: =K107+K109+K110+K111+K112+K113+K114+K115+K117+K118+K119+K116 -> 414670.52
E121: Como % do EBIT Recorrente | F121: =F120/F97 -> -8.4249087 | G121: =G120/G97 -> -0.15054594 | H121: =H120/H97 -> -0.12932623 | I121: =I120/I97 -> -0.01815611 | J121: =J120/J97 -> -0.58982785 | K121: =K120/K97 -> -3.5245214
E122: IRPJ + CSLL - Não-Recorrentes | F122: =F107+F110+F111+F112+F114+F115+F117+F118 -> 67156.76 | G122: =G107+G110+G111+G112+G114+G115+G117+G118 -> -29239.98 | H122: =H107+H110+H111+H112+H114+H115+H117+H118 -> -47177.72 | I122: =I107+I110+I111+I112+I114+I115+I117+I118 -> -7708.86 | J122: =J107+J110+J111+J112+J114+J115+J117+J118 -> 152266.44 | K122: =K107+K110+K111+K112+K114+K115+K117+K118 -> 84370.52
E123: Como % do EBIT Recorrente | F123: =F122/F97 -> -8.8902251 | G123: =G122/G97 -> -0.098550657 | H123: =H122/H97 -> -0.13243947 | I123: =I122/I97 -> -0.024401381 | J123: =J122/J97 -> -0.58786273 | K123: =K122/K97 -> -0.71711321
E124: IRPJ + CSLL - Não-Recorrentes - Incentivos | F124: =F107+F110+F111+F112+F114+F117+F118 -> 67156.76 | G124: =G107+G110+G111+G112+G114+G117+G118 -> -29239.98 | H124: =H107+H110+H111+H112+H114+H117+H118 -> -47177.72 | I124: =I107+I110+I111+I112+I114+I117+I118 -> -7708.86 | J124: =J107+J110+J111+J112+J114+J117+J118 -> 151629.44 | K124: =K107+K110+K111+K112+K114+K117+K118 -> 81079.52
E125: Como % do EBIT Recorrente | F125: =F124/F97 -> -8.8902251 | G125: =G124/G97 -> -0.098550657 | H125: =H124/H97 -> -0.13243947 | I125: =I124/I97 -> -0.024401381 | J125: =J124/J97 -> -0.58540343 | K125: =K124/K97 -> -0.68914112

Sheet Balanço Patrimonial
A7: Páginas
A8: Dashboard | F8: 2016 | G8: 2017 | H8: 2018 | I8: 2019 | J8: 2020 | K8: 2021 | L8: 1T22
A9: WACC | E9: Capital de Giro | F9: =F13+F15+F17+-F42-F44-F47 -> 782152.35 | G9: =G13+G15+G17+-G42-G44-G47 -> 668764.25 | H9: =H13+H15+H17+-H42-H44-H47 -> 764664.85 | I9: =I13+I15+I17+-I42-I44-I47 -> 676487.4 | J9: =J13+J15+J17+-J42-J44-J47 -> 404685.15 | K9: =K13+K15+K17+-K42-K44-K47 -> 391126.12 | L9: =L13+L15+L17+-L42-L44-L47+K72 -> 998335.24
A10: DRE + DCF | E10: Ativo Total | F10: =F11+F25 -> 3631176 | G10: =G11+G25 -> 3394299 | H10: =H11+H25 -> 3478337 | I10: =I11+I25 -> 6037092 | J10: =J11+J25 -> 7309647 | K10: =K11+K25 -> 8672626 | L10: =L11+L25 -> 8256189
A11: Balanço Patrimonial | E11: Ativo Circulante | F11: =F12+F15+F17+F18+F20 -> 2144643 | G11: =G12+G15+G17+G18+G20 -> 2125587 | H11: =H12+H15+H17+H18+H20 -> 2195569 | I11: =I12+I15+I17+I18+I20 -> 2999575 | J11: =J12+J15+J17+J18+J20 -> 3519978 | K11: =K12+K15+K17+K18+K20 -> 3929358 | L11: =L12+L15+L17+L18+L20 -> 3626438
A12: Projeções | E12: Caixa e Equivalentes de Caixa | F12: 489705 | G12: 431759 | H12: 446006 | I12: 447109 | J12: 1509159 | K12: 1050251 | L12: =660373+3978 -> 664351
A13: Lojas | E13: Caixa Operacional | F13: ='DRE + DCF'!F11*0.025 -> 119517.35 | G13: ='DRE + DCF'!G11*0.025 -> 125890.25 | H13: ='DRE + DCF'!H11*0.025 -> 128477.85 | I13: ='DRE + DCF'!I11*0.025 -> 132129.4 | J13: ='DRE + DCF'!J11*0.025 -> 102137.15 | K13: ='DRE + DCF'!K11*0.025 -> 128830.12 | L13: ='DRE + DCF'!N11*0.025 -> 139854.24
E14: Excesso de caixa | F14: =F12-F13 -> 370187.65 | G14: =G12-G13 -> 305868.75 | H14: =H12-H13 -> 317528.15 | I14: =I12-I13 -> 314979.6 | J14: =J12-J13 -> 1407021.9 | K14: =K12-K13 -> 921420.88 | L14: =L12-L13 -> 524496.76
E15: Contas a Receber | F15: 1013011 | G15: 1070690 | H15: 1142836 | I15: 1151484 | J15: 1063844 | K15: 1145336 | L15: 986769
E16: Clientes | F16: 1013011 | G16: 1070690 | H16: 1142836 | I16: 1151484 | J16: 1063844 | K16: 1145336 | L16: 986769
E17: Estoques | F17: 536579 | G17: 479427 | H17: 490614 | I17: 544717 | J17: 641020 | K17: 849269 | L17: 979770
E18: Tributos a Recuperar | F18: 55725 | G18: 72877 | H18: 42847 | I18: 833649 | J18: 282660 | K18: 849115 | L18: 936586
E19: Tributos Correntes a Recuperar | F19: 55725 | G19: 7287 | H19: 42847 | I19: 833649 | J19: 282660 | K19: 849115 | L19: 936586
E20: Outros Ativos Circulantes | F20: 49623 | G20: 70834 | H20: 73266 | I20: 22616 | J20: 23295 | K20: 35387 | L20: 58962
E21: Outros | F21: 49623 | G21: 70834 | H21: 73266 | I21: 22616 | J21: 23295 | K21: 35387 | L21: 58962
E22: Outros Créditos | F22: 13393 | G22: 15968 | H22: 17940 | I22: 21609 | J22: 22933 | K22: 33348 | L22: 58892
E23: Instrumentos Financeiros Derivativos | F23: 35463 | G23: 53835 | H23: 55067 | I23: 651 | J23: 238 | K23: 1535 | L23: 0
E24: Partes Relacionadas | F24: 767 | G24: 1031 | H24: 259 | I24: 356 | J24: 124 | K24: 504 | L24: 70
E25: Ativo Não Circulante | F25: =F26+F34+F38 -> 1486533 | G25: =G26+G34+G38 -> 1268712 | H25: =H26+H34+H38 -> 1282768 | I25: =I26+I34+I38 -> 3037517 | J25: =J26+J34+J38 -> 3789669 | K25: =K26+K34+K38 -> 4743268 | L25: =L26+L34+L38 -> 4629751
E26: Ativo Realizável a Longo Prazo | F26: 546237 | G26: 457050 | H26: 448943 | I26: 624950 | J26: 1313046 | K26: 1291014 | L26: 1266451
E27: Aplicações Financeiras | F27: 0 | G27: 0 | H27: 0 | I27: 0 | J27: 0 | K27: 0 | L27: 3978
E28: Tributos Diferidos | F28: 440059 | G28: 398811 | H28: 370643 | I28: 0 | J28: 71492 | K28: 378803 | L28: 475718
E29: IRPJ + CSLL | F29: 440059 | G29: 398811 | H29: 370643 | I29: 0 | J29: 71492 | K29: 378803 | L29: 475718
E30: Outros Ativos Não Circulantes | F30: 106178 | G30: 58239 | H30: 78300 | I30: 624950 | J30: 1241554 | K30: 904302 | L30: 786637
E31: Tributos a Recuperar | F31: 1727 | G31: 2396 | H31: 7649 | I31: 521136 | J31: 1157357 | K31: 839778 | L31: 720027
E32: Depósito Judicial | F32: 50474 | G32: 52280 | H32: 67748 | I32: 101836 | J32: 81513 | K32: 61937 | L32: 62527
E33: Outros Créditos | F33: 53977 | G33: 3563 | H33: 2903 | I33: 1978 | J33: 2684 | K33: 2587 | L33: 4083
E34: Imobilizado | F34: 780251 | G34: 612572 | H34: 636927 | I34: 2225227 | J34: 2181663 | K34: 2476559 | L34: 2397442
E35: Imobilizado em Operação | F35: 705570 | G35: 588325 | H35: 607408 | I35: 665906 | J35: 651814 | K35: 817978 | L35: 796588
E36: Direito de Uso em Arrendamento | F36: 4736 | G36: 4473 | H36: 4210 | I36: 1507815 | J36: 1514438 | K36: 1640290 | L36: 1576101
E37: Imobilizado em Andamento | F37: 69945 | G37: 19774 | H37: 25309 | I37: 51506 | J37: 15411 | K37: 18291 | L37: 24753
... E39: Intangíveis | F39: 160045 | G39: 199090 | H39: 196898 | I39: 187340 | J39: 294960 | K39: 975695 | L39: 965858
E40: Passivo Total | F40: =F41+F62 -> 2804888 | G40: =G41+G62 -> 2387786 | H40: =H41+H62 -> 2363298 | I40: =I41+I62 -> 3297522 | J40: =J41+J62 -> 4654847 | K40: =K41+K62 -> 5677657 | L40: =L41+L62 -> 5430243
E41: Passivo Circulante | F41: =F42+F44+F47+F52+F55 -> 1746409 | G41: =G42+G44+G47+G52+G55 -> 2022855 | H41: =H42+H44+H47+H52+H55 -> 1750068 | I41: =I42+I44+I47+I52+I55 -> 1751077 | J41: =J42+J44+J47+J52+J55 -> 2251711 | K41: =K42+K44+K47+K52+K55 -> 2415055 | L41: =L42+L44+L47+L52+L55 -> 2381594
E42: Obrigações Sociais e Trabalhistas | F42: 104360 | G42: 136866 | H42: 130922 | I42: 128548 | J42: 136126 | K42: 155470 | L42: 160656
E43: Obrigações Trabalhistas | F43: 104360 | G43: 136866 | H43: 130922 | I43: 128548 | J43: 136126 | K43: 155470 | L43: 160656
E44: Fornecedores | F44: 609005 | G44: 686193 | H44: 678846 | I44: 804013 | J44: 1158914 | K44: 1400736 | L44: 1291227
E45: Nacionais | F45: 607021 | G45: 681917 | H45: 677120 | I45: 803651 | J45: 1151964 | K45: 1400736 | L45: 1291227
E46: Estrangeiros | F46: 1984 | G46: 4276 | H46: 1726 | I46: 362 | J46: 6950 | K46: 0 | L46: 0
E47: Obrigações Fiscais | F47: 173590 | G47: 184184 | H47: 187495 | I47: 219282 | J47: 107276 | K47: 176103 | L47: 91235
E48: Federais | F48: 63072 | G48: 70911 | H48: 70110 | I48: 116803 | J48: 7751 | K48: 7262 | L48: 0
E49: IRPJ + CSLL | F49: 348 | G49: 3014 | H49: 26566 | I49: 35672 | J49: 321 | K49: 463 | L49: 389
E50: Outros | F50: 62724 | G50: 67897 | H50: 43544 | I50: 81131 | J50: 7430 | K50: 0 | L50: 0
E51: Estaduais | F51: 110518 | G51: 113273 | H51: 117385 | I51: 102479 | J51: 99525 | K51: 175640 | L51: 90846
E52: Empréstimos e Financiamentos | F52: =F53+F54 -> 287 | G52: =G53+G54 -> 257 | H52: =H53+H54 -> 230 | I52: =I53+I54 -> 357891 | J52: =J53+J54 -> 781203 | K52: =K53+K54 -> 592901 | L52: =L53+L54 -> 680026
E53: Empréstimos | F53: 0 | G53: 0 | H53: 0 | I53: 0 | J53: 390600 | K53: 121178 | L53: 195286
E54: Financiamento por Arrendamento | F54: 287 | G54: 257 | H54: 230 | I54: 357891 | J54: 390603 | K54: 471723 | L54: 484740
E55: Outras Obrigações | F55: =F56+F58 -> 859167 | G55: =G56+G58 -> 1015355 | H55: =H56+H58 -> 752575 | I55: =I56+I58 -> 241343 | J55: =J56+J58 -> 68192 | K55: =K56+K58 -> 89845 | L55: =L56+L58 -> 158450
E56: Passivos com Partes Relacionadas | F56: 694914 | G56: 980051 | H56: 711575 | I56: 69519 | J56: 34766 | K56: 59016 | L56: 100917
E57: Débitos com Outras Partes Relacionadas | F57: 694914 | G57: 980051 | H57: 711575 | I57: 69519 | J57: 34766 | K57: 59016 | L57: 100917
E58: Outros | F58: =F59+F60+F61 -> 164253 | G58: =G59+G60+G61 -> 35304 | H58: =H59+H60+H61 -> 41000 | I58: =I59+I60+I61 -> 171824 | J58: =J59+J60+J61 -> 33426 | K58: =K59+K60+K61 -> 30829 | L58: =L59+L60+L61 -> 57533
E59: Operações com Derivativos | F59: 128302 | G59: 74 | H59: 403 | I59: 3938 | J59: 6788 | K59: 1910 | L59: 28758
E60: Outros Passivos | F60: 35951 | G60: 35230 | H60: 40597 | I60: 23052 | J60: 26637 | K60: 28918 | L60: 28774
E61: Dividendos e juros sobre capital | F61: 0 | G61: 0 | H61: 0 | I61: 144834 | J61: 1 | K61: 1 | L61: 1
E62: Passivo Não Circulante | F62: =F63+F66+F76+F74 -> 1058479 | G62: =G63+G66+G76+G74 -> 364931 | H62: =H63+H66+H76+H74 -> 613230 | I62: =I63+I66+I76+I74 -> 1546445 | J62: =J63+J66+J76+J74 -> 2403136 | K62: =K63+K66+K76+K74 -> 3262602 | L62: =L63+L66+L76+L74 -> 3048649
E63: Empréstimos e Financiamentos | F63: =F64+F65 -> 2105 | G63: =G64+G65 -> 1848 | H63: =H64+H65 -> 1618 | I63: =I64+I65 -> 1229789 | J63: =J64+J65 -> 2084845 | K63: =K64+K65 -> 2596073 | L63: =L64+L65 -> 2791323
E64: Financiamento por Arrendamento | F64: 2105 | G64: 1848 | H64: 1618 | I64: 1229789 | J64: 1264193 | K64: 1342425 | L64: 1276364 | M64: =L65+L53 -> 1710245
E65: Empréstimos | F65: 0 | G65: 0 | H65: 0 | I65: 0 | J65: 820652 | K65: 1253648 | L65: 1514959
E66: Outras Obrigações | F66: =F67+F69 -> 736725 | G66: =G67+G69 -> 42049 | H66: =H67+H69 -> 349005 | I66: =I67+I69 -> 37183 | J66: =J67+J69 -> 88167 | K66: =K67+K69 -> 497003 | L66: =L67+L69 -> 83044
E67: Passivos com Partes Relacionadas | F67: 690606 | G67: 0 | H67: 313450 | I67: 0 | J67: 0 | K67: 0 | L67: 0
E68: Débitos com Outras Partes Relacionadas | F68: 690606 | G68: 0 | H68: 313450 | I68: 0 | J68: 0 | K68: 0 | L68: 0
E69: Outros | F69: =F70+F71+F72+F73 -> 46119 | G69: =G70+G71+G72+G73 -> 42049 | H69: =H70+H71+H72+H73 -> 35555 | I69: =I70+I71+I72+I73 -> 37183 | J69: =J70+J71+J72+J73 -> 88167 | K69: =K70+K71+K72+K73 -> 497003 | L69: =L70+L71+L72+L73 -> 83044
E70: Impostos a Recolher | F70: 0 | G70: 0 | H70: 0 | I70: 1073 | J70: 24997 | K70: 16212 | L70: 15019
E71: Obrigações Trabalhistas | F71: 5199 | G71: 3971 | H71: 4058 | I71: 3551 | J71: 4442 | K71: 5675 | L71: 6326
E72: Fornecedores | F72: 0 | G72: 0 | H72: 0 | I72: 0 | J72: 24810 | K72: 435060 | L72: 20367
E73: Outros Passivos | F73: 40920 | G73: 38078 | H73: 31497 | I73: 32559 | J73: 33918 | K73: 40056 | L73: 41332
E74: Tributos Diferidos | F74: 0 | G74: 0 | H74: 0 | I74: 45631 | J74: 0 | K74: 0 | L74: 0
E75: Imposto de Renda e CSLL Diferidos | F75: 0 | G75: 0 | H75: 0 | I75: 45631 | J75: 0 | K75: 0 | L75: 0
E76: Provisões | F76: 319649 | G76: 321034 | H76: 262607 | I76: 233842 | J76: 230124 | K76: 169526 | L76: 174282
E77: Provisões Fiscais Previdenciárias Trabalhistas e Cíveis | F77: 260697 | G77: 321034 | H77: 262607 | I77: 233842 | J77: 230124 | K77: 169526 | L77: 174282
E78: Provisões Fiscais | F78: 186979 | G78: 240376 | H78: 170657 | I78: 140199 | J78: 146246 | K78: 135721 | L78: 140350
E79: Provisões Previdenciárias e Trabalhistas | F79: 63217 | G79: 73831 | H79: 85476 | I79: 89505 | J79: 74994 | K79: 30095 | L79: 30258
E80: Provisões Cíveis | F80: 10501 | G80: 6827 | H80: 6474 | I80: 4138 | J80: 8884 | K80: 3710 | L80: 3674
E81: Outras Previsões | F81: 58952 | G81: 0 | H81: 0 | I81: 0 | J81: 0 | K81: 0 | L81: 0
E82: Patrimônio Líquido | F82: =SUM(F83:F88) -> 826288 | G82: =SUM(G83:G88) -> 1006513 | H82: =SUM(H83:H88) -> 1115039 | I82: =SUM(I83:I88) -> 2739570 | J82: =SUM(J83:J88) -> 2654800 | K82: =SUM(K83:K88) -> 2995009 | L82: =SUM(L83:L88) -> 2825946
E83: Capital Social Realizado | F83: 890712 | G83: 1035720 | H83: 1035720 | I83: 1847177 | J83: 1847177 | K83: 1847177 | L83: 1847177
E84: Reservas de Capital | F84: 10516 | G84: 10516 | H84: 10516 | I84: 11647 | J84: 19375 | K84: 26499 | L84: 28899
E85: Reservas de Lucros | F85: 0 | G85: 0 | H85: 0 | I85: 882914 | J85: 792570 | K85: 1121578 | L85: 1121578
E86: Lucros/Prejuiízos Acumulados | F86: -70882 | G86: -39675 | H86: 65042 | I86: 0 | J86: 0 | K86: 0 | L86: -152724
E87: Outros Resultados Abrangentes | F87: -4067 | G87: -49 | H87: 3759 | I87: -2170 | J87: -4324 | K87: -248 | L87: -18981
E88: Participação dos Acionistas Não Controladores | F88: 9 | G88: 1 | H88: 2 | I88: 2 | J88: 2 | K88: 3 | L88: -3

Sheet Painel de Índices
A7: Páginas
A8: Dashboard
A9: WACC | F9: 2016 | G9: 2017 | H9: 2018 | I9: 2019 | J9: 2020 | K9: 2021 | L9: 1T22
A10: DRE + DCF | E10: Liquidez Geral | F10: ='Balanço Patrimonial'!F10/'Balanço Patrimonial'!F40 -> 1.2945886 | G10: ='Balanço Patrimonial'!G10/'Balanço Patrimonial'!G40 -> 1.4215256 | H10: ='Balanço Patrimonial'!H10/'Balanço Patrimonial'!H40 -> 1.4718148 | I10: ='Balanço Patrimonial'!I10/'Balanço Patrimonial'!I40 -> 1.8307966 | J10: ='Balanço Patrimonial'!J10/'Balanço Patrimonial'!J40 -> 1.5703302 | K10: ='Balanço Patrimonial'!K10/'Balanço Patrimonial'!K40 -> 1.5275009 | L10: ='Balanço Patrimonial'!L10/'Balanço Patrimonial'!L40 -> 1.5204088
A11: Balanço Patrimonial | E11: Liquidez Corrente | F11: ='Balanço Patrimonial'!F11/'Balanço Patrimonial'!F41 -> 1.2280302 | G11: ='Balanço Patrimonial'!G11/'Balanço Patrimonial'!G41 -> 1.0507856 | H11: ='Balanço Patrimonial'!H11/'Balanço Patrimonial'!H41 -> 1.2545621 | I11: ='Balanço Patrimonial'!I11/'Balanço Patrimonial'!I41 -> 1.7129886 | J11: ='Balanço Patrimonial'!J11/'Balanço Patrimonial'!J41 -> 1.5632459 | K11: ='Balanço Patrimonial'!K11/'Balanço Patrimonial'!K41 -> 1.6270263 | L11: ='Balanço Patrimonial'!L11/'Balanço Patrimonial'!L41 -> 1.5226936
A12: Projeções | E12: Liquidez Seca | F12: =('Balanço Patrimonial'!F11-'Balanço Patrimonial'!F17)/'Balanço Patrimonial'!F41 -> 0.92078316 | G12: =('Balanço Patrimonial'!G11-'Balanço Patrimonial'!G17)/'Balanço Patrimonial'!G41 -> 0.81378052 | H12: =('Balanço Patrimonial'!H11-'Balanço Patrimonial'!H17)/'Balanço Patrimonial'!H41 -> 0.97422214 | I12: =('Balanço Patrimonial'!I11-'Balanço Patrimonial'!I17)/'Balanço Patrimonial'!I41 -> 1.4019132 | J12: =('Balanço Patrimonial'!J11-'Balanço Patrimonial'!J17)/'Balanço Patrimonial'!J41 -> 1.2785646 | K12: =('Balanço Patrimonial'!K11-'Balanço Patrimonial'!K17)/'Balanço Patrimonial'!K41 -> 1.2753701 | L12: =('Balanço Patrimonial'!L11-'Balanço Patrimonial'!L17)/'Balanço Patrimonial'!L41 -> 1.1113011
A13: Lojas | E13: Liquidez Imediata | F13: ='Balanço Patrimonial'!F12/'Balanço Patrimonial'!F41 -> 0.28040682 | G13: ='Balanço Patrimonial'!G12/'Balanço Patrimonial'!G41 -> 0.21344041 | H13: ='Balanço Patrimonial'!H12/'Balanço Patrimonial'!H41 -> 0.25485067 | I13: ='Balanço Patrimonial'!I12/'Balanço Patrimonial'!I41 -> 0.25533372 | J13: ='Balanço Patrimonial'!J12/'Balanço Patrimonial'!J41 -> 0.67022766 | K13: ='Balanço Patrimonial'!K12/'Balanço Patrimonial'!K41 -> 0.43487664 | L13: ='Balanço Patrimonial'!L12/'Balanço Patrimonial'!L41 -> 0.27895225
F17: 2016 | G17: 2017 | H17: 2018 | I17: 2019 | J17: 2020 | K17: 2021 | L17: 1T22
E18: Retorno sobre o Equity (ROE) | F18: ='DRE + DCF'!F32/'Balanço Patrimonial'!F82 -> -0.17097186 | G18: ='DRE + DCF'!G32/'Balanço Patrimonial'!G82 -> 0.096253104 | H18: ='DRE + DCF'!H32/'Balanço Patrimonial'!H82 -> 0.15572191 | I18: ='DRE + DCF'!I32/'Balanço Patrimonial'!I82 -> 0.35479765 | J18: ='DRE + DCF'!J32/'Balanço Patrimonial'!J82 -> -0.062653307 | K18: ='DRE + DCF'!K32/'Balanço Patrimonial'!K82 -> 0.10985242 | L18: ='DRE + DCF'!L32*4/'Balanço Patrimonial'!L82 -> -0.21618247
E19: Retorno sobre o Ativo (ROA) | F19: ='DRE + DCF'!F32/'Balanço Patrimonial'!F10 -> -0.038905302 | G19: ='DRE + DCF'!G32/'Balanço Patrimonial'!G10 -> 0.028541976 | H19: ='DRE + DCF'!H32/'Balanço Patrimonial'!H10 -> 0.049919257 | I19: ='DRE + DCF'!I32/'Balanço Patrimonial'!I10 -> 0.16100351 | J19: ='DRE + DCF'!J32/'Balanço Patrimonial'!J10 -> -0.022755134 | K19: ='DRE + DCF'!K32/'Balanço Patrimonial'!K10 -> 0.037936491 | L19: ='DRE + DCF'!L32*4/'Balanço Patrimonial'!L10 -> -0.073995399
E20: ROIC | F20: ='DRE + DCF'!F40/('Balanço Patrimonial'!F57+'Balanço Patrimonial'!F52+'Balanço Patrimonial'!F64+'Balanço Patrimonial'!F65+'Balanço Patrimonial'!F67+'Balanço Patrimonial'!F82-'Balanço Patrimonial'!F14) -> 0.030416282 | G20: ='DRE + DCF'!G40/('Balanço Patrimonial'!G57+'Balanço Patrimonial'!G52+'Balanço Patrimonial'!G64+'Balanço Patrimonial'!G65+'Balanço Patrimonial'!G67+'Balanço Patrimonial'!G82-'Balanço Patrimonial'!G14) -> 0.14977 | H20: ='DRE + DCF'!H40/('Balanço Patrimonial'!H57+'Balanço Patrimonial'!H52+'Balanço Patrimonial'!H64+'Balanço Patrimonial'!H65+'Balanço Patrimonial'!H67+'Balanço Patrimonial'!H82-'Balanço Patrimonial'!H14) -> 0.16679988 | I20: ='DRE + DCF'!I40/('Balanço Patrimonial'!I57+'Balanço Patrimonial'!I52+'Balanço Patrimonial'!I64+'Balanço Patrimonial'!I65+'Balanço Patrimonial'!I67+'Balanço Patrimonial'!I82-'Balanço Patrimonial'!I14) -> 0.14983478 | J20: ='DRE + DCF'!J40/('Balanço Patrimonial'!J57+'Balanço Patrimonial'!J52+'Balanço Patrimonial'!J64+'Balanço Patrimonial'!J65+'Balanço Patrimonial'!J67+'Balanço Patrimonial'!J82-'Balanço Patrimonial'!J14) -> 0.055813151 | K20: ='DRE + DCF'!K40/('Balanço Patrimonial'!K57+'Balanço Patrimonial'!K52+'Balanço Patrimonial'!K64+'Balanço Patrimonial'!K65+'Balanço Patrimonial'!K67+'Balanço Patrimonial'!K82-'Balanço Patrimonial'!K14) -> 0.14265336 | L20: ='DRE + DCF'!L40*4/('Balanço Patrimonial'!L57+'Balanço Patrimonial'!L52+'Balanço Patrimonial'!L64+'Balanço Patrimonial'!L65+'Balanço Patrimonial'!L67+'Balanço Patrimonial'!L82-'Balanço Patrimonial'!L14) -> 0.0070687799
F24: 2016 | G24: 2017 | H24: 2018 | I24: 2019 | J24: 2020 | K24: 2021 | L24: 1T22
E25: Divida Líquida/EBITDA | F25: =('Balanço Patrimonial'!F52+'Balanço Patrimonial'!F63+'Balanço Patrimonial'!F56+'Balanço Patrimonial'!F67-'Balanço Patrimonial'!F12)/('DRE + DCF'!F22+'DRE + DCF'!F44+'DRE + DCF'!F38) -> 4.603121 | G25: =('Balanço Patrimonial'!G52+'Balanço Patrimonial'!G63+'Balanço Patrimonial'!G56+'Balanço Patrimonial'!G67-'Balanço Patrimonial'!G12)/('DRE + DCF'!G22+'DRE + DCF'!G44+'DRE + DCF'!G38) -> 1.1128191 | H25: =('Balanço Patrimonial'!H52+'Balanço Patrimonial'!H63+'Balanço Patrimonial'!H56+'Balanço Patrimonial'!H67-'Balanço Patrimonial'!H12)/('DRE + DCF'!H22+'DRE + DCF'!H44+'DRE + DCF'!H38) -> 1.034838 | I25: =('Balanço Patrimonial'!I52+'Balanço Patrimonial'!I63+'Balanço Patrimonial'!I56+'Balanço Patrimonial'!I67-'Balanço Patrimonial'!I12)/('DRE + DCF'!I22+'DRE + DCF'!I44+'DRE + DCF'!I38) -> 0.77480422 | J25: =('Balanço Patrimonial'!J52+'Balanço Patrimonial'!J63+'Balanço Patrimonial'!J56+'Balanço Patrimonial'!J67-'Balanço Patrimonial'!J12)/('DRE + DCF'!J22+'DRE + DCF'!J44+'DRE + DCF'!J38) -> 3.5818746 | K25: =('Balanço Patrimonial'!K52+'Balanço Patrimonial'!K63+'Balanço Patrimonial'!K56+'Balanço Patrimonial'!K67-'Balanço Patrimonial'!K12)/('DRE + DCF'!K22+'DRE + DCF'!K44+'DRE + DCF'!K38) -> 3.2425647 | L25: =('Balanço Patrimonial'!L52+'Balanço Patrimonial'!L63+'Balanço Patrimonial'!L56+'Balanço Patrimonial'!L67-'Balanço Patrimonial'!L12)/('DRE + DCF'!L22+'DRE + DCF'!L44+'DRE + DCF'!L38)/4 -> 164.6984
E26: Cobertura de Juros | F26: ='DRE + DCF'!F22/'DRE + DCF'!F29 -> 0.010613158 | G26: ='DRE + DCF'!G22/'DRE + DCF'!G29 -> -0.91742268 | H26: ='DRE + DCF'!H22/'DRE + DCF'!H29 -> -1.1242221 | I26: ='DRE + DCF'!I22/'DRE + DCF'!I29 -> -3.664835 | J26: ='DRE + DCF'!J22/'DRE + DCF'!J29 -> 0.72742493 | K26: ='DRE + DCF'!K22/'DRE + DCF'!K29 -> -0.34626636 | L26: ='DRE + DCF'!L22/'DRE + DCF'!L29 -> 1.549351
E27: Dívida/Ativo | F27: =('Balanço Patrimonial'!F52+'Balanço Patrimonial'!F63)/'Balanço Patrimonial'!F10 -> 0.00065873976 | G27: =('Balanço Patrimonial'!G52+'Balanço Patrimonial'!G63)/'Balanço Patrimonial'!G10 -> 0.00062015751 | H27: =('Balanço Patrimonial'!H52+'Balanço Patrimonial'!H63)/'Balanço Patrimonial'!H10 -> 0.00053128837 | I27: =('Balanço Patrimonial'!I52+'Balanço Patrimonial'!I63)/'Balanço Patrimonial'!I10 -> 0.26298754 | J27: =('Balanço Patrimonial'!J52+'Balanço Patrimonial'!J63)/'Balanço Patrimonial'!J10 -> 0.39209116 | K27: =('Balanço Patrimonial'!K52+'Balanço Patrimonial'!K63)/'Balanço Patrimonial'!K10 -> 0.3677057 | L27: =('Balanço Patrimonial'!L52+'Balanço Patrimonial'!L63)/'Balanço Patrimonial'!L10 -> 0.42045416
E28: Dívida/Patrimônio Líquido | F28: =('Balanço Patrimonial'!F53+'Balanço Patrimonial'!F64)/'Balanço Patrimonial'!F82 -> 0.0025475379 | G28: =('Balanço Patrimonial'!G53+'Balanço Patrimonial'!G64)/'Balanço Patrimonial'!G82 -> 0.0018360419 | H28: =('Balanço Patrimonial'!H53+'Balanço Patrimonial'!H64)/'Balanço Patrimonial'!H82 -> 0.0014510703 | I28: =('Balanço Patrimonial'!I53+'Balanço Patrimonial'!I64)/'Balanço Patrimonial'!I82 -> 0.44889855 | J28: =('Balanço Patrimonial'!J53+'Balanço Patrimonial'!J64)/'Balanço Patrimonial'!J82 -> 0.62332115 | K28: =('Balanço Patrimonial'!K53+'Balanço Patrimonial'!K64)/'Balanço Patrimonial'!K82 -> 0.48868067 | L28: =('Balanço Patrimonial'!L53+'Balanço Patrimonial'!L64)/'Balanço Patrimonial'!L82 -> 0.52076367
E29: Dívida/(Dívida + Patrimônio Líquido) | F29: =('Balanço Patrimonial'!F53+'Balanço Patrimonial'!F64)/('Balanço Patrimonial'!F53+'Balanço Patrimonial'!F64+'Balanço Patrimonial'!F82) -> 0.0025410644 | G29: =('Balanço Patrimonial'!G53+'Balanço Patrimonial'!G64)/('Balanço Patrimonial'!G53+'Balanço Patrimonial'!G64+'Balanço Patrimonial'!G82) -> 0.001832677 | H29: =('Balanço Patrimonial'!H53+'Balanço Patrimonial'!H64)/('Balanço Patrimonial'!H53+'Balanço Patrimonial'!H64+'Balanço Patrimonial'!H82) -> 0.0014489678 | I29: =('Balanço Patrimonial'!I53+'Balanço Patrimonial'!I64)/('Balanço Patrimonial'!I53+'Balanço Patrimonial'!I64+'Balanço Patrimonial'!I82) -> 0.30982055 | J29: =('Balanço Patrimonial'!J53+'Balanço Patrimonial'!J64)/('Balanço Patrimonial'!J53+'Balanço Patrimonial'!J64+'Balanço Patrimonial'!J82) -> 0.38397895 | K29: =('Balanço Patrimonial'!K53+'Balanço Patrimonial'!K64)/('Balanço Patrimonial'!K53+'Balanço Patrimonial'!K64+'Balanço Patrimonial'!K82) -> 0.32826427 | L29: =('Balanço Patrimonial'!L53+'Balanço Patrimonial'!L64)/('Balanço Patrimonial'!L53+'Balanço Patrimonial'!L64+'Balanço Patrimonial'!L82) -> 0.34243563
F33: 2016 | G33: 2017 | H33: 2018 | I33: 2019 | J33: 2020 | K33: 2021 | L33: 1T22
E34: Prazo Médio de Recebimento | F34: ='Balanço Patrimonial'!F15*365/'DRE + DCF'!F11 -> 77.342121 | G34: ='Balanço Patrimonial'!G15*365/'DRE + DCF'!G11 -> 77.607648 | H34: ='Balanço Patrimonial'!H15*365/'DRE + DCF'!H11 -> 81.168688 | I34: ='Balanço Patrimonial'!I15*365/'DRE + DCF'!I11 -> 79.522737 | J34: ='Balanço Patrimonial'!J15*365/'DRE + DCF'!J11 -> 95.044521 | K34: ='Balanço Patrimonial'!K15*365/'DRE + DCF'!K11 -> 81.123813 | L34: ='Balanço Patrimonial'!L15*365/'DRE + DCF'!L11/4 -> 75.22211
E35: Prazo Médio de Estoques | F35: ='Balanço Patrimonial'!F17*365/-'DRE + DCF'!F16 -> 97.322656 | G35: ='Balanço Patrimonial'!G17*365/-'DRE + DCF'!G16 -> 82.35542 | H35: ='Balanço Patrimonial'!H17*365/-'DRE + DCF'!H16 -> 81.660045 | I35: ='Balanço Patrimonial'!I17*365/-'DRE + DCF'!I16 -> 129.52326 | J35: ='Balanço Patrimonial'!J17*365/-'DRE + DCF'!J16 -> 113.53111 | K35: ='Balanço Patrimonial'!K17*365/-'DRE + DCF'!K16 -> 134.51154 | L35: ='Balanço Patrimonial'!L17*365/-'DRE + DCF'!L16/4 -> 121.08425
E36: Prazo Médio de Pagamento | F36: =('Balanço Patrimonial'!F44+'Balanço Patrimonial'!F42)*365/-('DRE + DCF'!F13+'DRE + DCF'!F16+'DRE + DCF'!F38+'DRE + DCF'!F44) -> 56.782159 | G36: =('Balanço Patrimonial'!G44+'Balanço Patrimonial'!G42)*365/-('DRE + DCF'!G13+'DRE + DCF'!G16+'DRE + DCF'!G38+'DRE + DCF'!G44) -> 66.156282 | H36: =('Balanço Patrimonial'!H44+'Balanço Patrimonial'!H42)*365/-('DRE + DCF'!H13+'DRE + DCF'!H16+'DRE + DCF'!H38+'DRE + DCF'!H44) -> 64.564898 | I36: =('Balanço Patrimonial'!I44+'Balanço Patrimonial'!I42)*365/-('DRE + DCF'!I13+'DRE + DCF'!I16+'DRE + DCF'!I38+'DRE + DCF'!I44) -> 91.418341 | J36: =('Balanço Patrimonial'!J44+'Balanço Patrimonial'!J42)*365/-('DRE + DCF'!J13+'DRE + DCF'!J16+'DRE + DCF'!J38+'DRE + DCF'!J44) -> 127.85903 | K36: =('Balanço Patrimonial'!K44+'Balanço Patrimonial'!K42)*365/-('DRE + DCF'!K13+'DRE + DCF'!K16+'DRE + DCF'!K38+'DRE + DCF'!K44) -> 126.91866 | L36: =('Balanço Patrimonial'!L44+'Balanço Patrimonial'!L42)*365/-('DRE + DCF'!L13+'DRE + DCF'!L16+'DRE + DCF'!L38+'DRE + DCF'!L44)/4 -> 111.08772
E37: Ciclo de Caixa | F37: =F34+F35-F36 -> 117.88262 | G37: =G34+G35-G36 -> 93.806787 | H37: =H34+H35-H36 -> 98.263835 | I37: =I34+I35-I36 -> 117.62766 | J37: =J34+J35-J36 -> 80.716603 | K37: =K34+K35-K36 -> 88.716693 | L37: =L34+L35-L36 -> 85.218647
F41: 2016 | G41: 2017 | H41: 2018 | I41: 2019 | J41: 2020 | K41: 2021 | L41: 1T22
E42: Proventos por ação | F42: 0 | G42: 0 | H42: 0 | I42: 0.25347738 | J42: 0 | K42: 0 | L42: 0
E43: Dividend Yield (12 meses) | F43: 0 | G43: 0 | H43: 0 | I43: 0.014004275 | J43: 0 | K43: 0 | L43: 0
E44: Payout | F44: 0 | G44: 0 | H44: 0 | I44: 0.08038448 | J44: 0 | K44: 0 | L44: 0

Sheet Provisões e Processos
M1: Remota | N1: Tributário
M2: Possível | N2: Cível
M3: Provável | N3: Trabalhista
N4: Administrativo
A7: Páginas
A8: Dashboard
A9: WACC | F9: Valor dos Processos | G9: Valor das Provisões | H9: Valor de Perdas Possiveis | I9: Valor de Perdas Remotas
A10: DRE + DCF | E10: Tributários | F10: =SUM(G19:G28) -> 604643.85 | G10: 90295.469 | H10: =SUMIF($H$19:$H$28,"Possível",$G$19:$G$28)+16764+8161 -> 282122.01 | I10: =SUMIF($H$19:$H$28,"Remota",$G$19:$G$28) -> 232224.97
A11: Balanço Patrimonial | E11: Cíveis | F11: 0 | G11: 0 | H11: 0 | I11: =F11-G11-H11 -> 0
A12: Provisões e Processos | E12: Trabalhistas | F12: 0 | G12: 0 | H12: 0 | I12: =F12-G12-H12 -> 0
A13: Projeções | E13: Administrativos | F13: 0 | G13: 0 | H13: 0 | I13: =F13-G13-H13 -> 0
A14: Lojas | E14: Total | F14: =SUM(F10:F13) -> 604643.85 | G14: =SUM(G10:G13) -> 90295.469 | H14: =SUM(H10:H13) -> 282122.01 | I14: =SUM(I10:I13) -> 232224.97
E18: Classificação | F18: Descrição | G18: Valor do Processo (R$ mil) | H18: Chance de Perda | I18: Comentário
E19: Tributário | F19: Ação judicial proposta pela Companhia para discutir o direito de fruição da alíquota zero do PIS e da COFINS, prevista pela Lei nº 11.196/2005 (“Lei do Bem”), para a venda a varejo de smartphones produzidos no país. A Companhia foi intimada da instauração de um processo administrativo para inclusão, controle e cobrança dos débitos confessados por meio de declaração. A Companhia ajuizou uma ação com pedido de tutela provisória de urgência, cautelar incidental e/ou tutela de evidência para a antecipação de garantia do débito mediante a apresentação de seguro garantia. | G19: 172197.42 | H19: Possível | I19: Em caso de perda a Companhia, estará sujeita ao pagamento do valor do débito em discussão, devidamente atualizado. Em caso positivo, a Companhia terá direito à restituir os valores indevidamente recolhidos.
E20: Tributário | F20: Ação judicial proposta pela Companhia para discutir o reconhecimento do seu direito líquido e certo de não incluir o valor do ICMS nas bases de cálculo do PIS e da COFINS à luz da Lei nº 12.973/14, a partir da sua vigência. | G20: 232224.97 | H20: Remota | I20: 0
E21: Tributário | F21: Trata-se de processo administrativo fiscal relativo a cobrança de contribuições previdenciárias incidentes sobre valores pagos a título de Assistência Médica e Hospitalar a seus funcionários e empregados segurados, dos períodos de 12/12/1997 e 28/02/2005. | G21: 8130.6528 | H21: Possível | I21: -
E22: Tributário | F22: Trata-se de Execução Fiscal ajuizada pela União, objetivando a cobrança de supostos créditos tributários inscritos nas Certidões de Dívida Ativa nº. 80.6.15.071746-61 e 80.7.15.017496-78, oriundos da não homologação das compensações relacionadas ao Processo Administrativo de Compensação nº 13896.722.554/2011-37, realizadas pela empresa para compensar débitos de PIS/COFINS com crédito decorrente de valores pagos indevidamente a título de PIS e COFINS sobre receitas de terceiros, referente ao ano-calendário de 2008. | G22: 17071.171 | H22: Possível | I22: 0
E23: Tributário | F23: Trata-se de pedido de compensação, em razão de pagamento indevido ou a maior de COFINS, relativo ao mês de agosto de 2012 e recolhido em 25/09/13, compensado com débito do mesmo tributo (cód. 5856-01), referente ao período de apuração de setembro de 2012, com vencimento em 25/10/2012. | G23: 14985.83 | H23: Possível | I23: 0
E24: Tributário | F24: Trata-se de processo administrativo decorrente ao Auto de Infração que visa à cobrança de Imposto sobre Importação, PIS/PASEP Importação e COFINS Importação ante a não inclusão de Royalties pagos por uso de marcas licenciadas, na base de cálculo de mercadorias importadas em 2012. | G24: 14082.918 | H24: Possível | I24: 0
E25: Tributário | F25: Trata-se de processo administrativo fiscal federal relativo a PIS e COFINS sobre frete de transferência, taxa de cartão de crédito, propaganda e publicidade, mão de obra temporário, energia elétrica, ajustes positivos de créditos e despesas de aluguéis de imóveis. | G25: 59142.234 | H25: Provável | I25: Chance de perda possível de R$ 16.764 e provável de R$ 42.377.
E26: Tributário | F26: Trata-se de processo administrativo fiscal federal relativo a PIS e COFINS sobre taxa de frete, mão de obra temporária, aquisição de cabides, aquisição de embalagens, cartão de terceiros, cartão PL, propaganda de televisão, jornal, rádio e contratos exclusivos de propaganda. | G26: 39331.939 | H26: Provável | I26: Chance de perda possível de R$ 8.161 e provável de R$ 31.170.
E27: Tributário | F27: Trata-se de Ação Ordinária na qual se busca afastar o recolhimento da Contribuição instituída pelo ar. 1º da LC nº. 110/01, bem como a repetição dos valores indevidamente recolhidos no curso da ação ora ajuizada e nos 5 anos anteriores à propositura da demanda. | G27: 16747.701 | H27: Provável | I27: 0
E28: Tributário | F28: Trata-se de Mandado de Segurança impetrado para assegurar o direito líquido e certo da Impetrante excluir o ICMS e o ISS da base de cálculo da Contribuição Previdenciária Substitutiva (Lei nº 12.546/2011), bem como o seu direito de crédito, no que concerne aos pagamentos indevidamente realizados àquele título nos últimos 5 (cinco) anos. | G28: 30729.018 | H28: Possível | I28: 0

Sheet Projeções - Receita
L4: C&A (CEAB3)
A7: Páginas
A8: Dashboard
A9: WACC | F9: 2016 | G9: 2017 | H9: 2018 | I9: 2019 | J9: 2020 | K9: 2021 | L9: 2022 | M9: 2023 | N9: 2024 | O9: 2025 | P9: =O9+1 -> 2026 | Q9: =P9+1 -> 2027 | R9: =Q9+1 -> 2028 | S9: CAGR (16 - 19) | T9: Premissa | U9: Nível de Otimismo (0-5)
A10: DRE + DCF | E10: Receita Total | F10: ='DRE + DCF'!F11 -> 4780694 | G10: ='DRE + DCF'!G11 -> 5035610 | H10: ='DRE + DCF'!H11 -> 5139114 | I10: =I11+I12+I14 -> 5285178 | J10: ='DRE + DCF'!J11 -> 4085486 | K10: =K11+K12+K14 -> 5153206 | L10: =L11+L12+L14 -> 5594169.6 | M10: =M11+M12+M14 -> 6643601.4 | N10: =N11+N12+N14 -> 7910445.7 | O10: =O11+O12+O14 -> 9223569.7 | P10: =P11+P12+P14 -> 10319264 | Q10: =Q11+Q12+Q14 -> 11455213 | R10: =R11+R12+R14 -> 12401748 | S10: =(I10/F10)^(1/COUNT($G$9:$I$9))-1 -> 0.0340056
A11: Balanço Patrimonial | E11: Receita de Varejo | F11: 4601147 | G11: 4779324.6 | H11: 4882089 | I11: 5051851 | J11: 3922889 | K11: 4960633 | L11: =L31*L32 -> 5310679 | M11: =M31*M32 -> 6306929.8 | N11: =N31*N32 -> 7438955.5 | O11: =O31*O32 -> 8673812.8 | P11: =P31*P32 -> 9704200 | Q11: =Q31*Q32 -> 10672082 | R11: =R31*R32 -> 11553908 | S11: =(I11/F11)^(1/COUNT($G$9:$I$9))-1 -> 0.031639928
A12: Projeções | E12: Receita Líquida Financeiro | F12: 179547.03 | G12: 256285.38 | H12: 241271 | I12: 216402 | J12: 149259 | K12: 174974 | L12: =L13*L11 -> 265533.95 | M12: =M13*M11 -> 315346.49 | N12: =N13*N11 -> 446337.33 | O12: =O13*O11 -> 520428.77 | P12: =P13*P11 -> 582252 | Q12: =Q13*Q11 -> 747045.76 | R12: =R13*R11 -> 808773.57 | S12: =(I12/F12)^(1/COUNT($G$9:$I$9))-1 -> 0.064210848
A13: Lojas | E13: (%) da Receita de Varejo | F13: =F12/F11 -> 0.039022233 | G13: =G12/G11 -> 0.053623765 | H13: =H12/H11 -> 0.049419623 | I13: =I12/I11 -> 0.04283618 | J13: =J12/J11 -> 0.038048234 | K13: =K12/K11 -> 0.035272515 | L13: 0.05 | M13: 0.05 | N13: 0.06 | O13: 0.06 | P13: 0.06 | Q13: 0.07 | R13: 0.07
E14: Receita Outros | F14: - | G14: - | H14: 15754 | I14: 16925 | J14: 13338 | K14: 17599 | L14: =L15*L11 -> 17956.644 | M14: =M15*M11 -> 21325.2 | N14: =N15*N11 -> 25152.843 | O14: =O15*O11 -> 29328.183 | P14: =P15*P11 -> 32812.162 | Q14: =Q15*Q11 -> 36084.798 | R14: =R15*R11 -> 39066.457
E15: (%) da Receita de Varejo | F15: - | G15: - | H15: =H14/H11 -> 0.0032268973 | I15: =I14/I11 -> 0.0033502572 | J15: =J14/J11 -> 0.0034000452 | K15: =K14/K11 -> 0.0035477327 | L15: =AVERAGE(H15:K15) -> 0.0033812331 | M15: =L15 -> 0.0033812331 | N15: =M15 -> 0.0033812331 | O15: =N15 -> 0.0033812331 | P15: =O15 -> 0.0033812331 | Q15: =P15 -> 0.0033812331 | R15: =Q15 -> 0.0033812331 | T15: A Receita de "Outros" se refere a receita de comissões sobre recarga de celular e venda de planos em parceria com operadoras. Como não é o foco da empresa, vamos considerar que ela vai permanecer como 0,34% da Receita de Varejo. Qualquer erro aqui gera um impacto muito pequeno no valor final da ação. | U15: 3
F19: 2016 | G19: 2017 | H19: 2018 | I19: 2019 | J19: 2020 | K19: 2021 | L19: 2022 | M19: 2023 | N19: 2024 | O19: 2025 | P19: =O19+1 -> 2026 | Q19: =P19+1 -> 2027 | R19: =Q19+1 -> 2028 | S19: CAGR (16 - 19) | T19: Premissa | U19: Nível de Otimismo (0-5)
E20: Número de Lojas | F20: 279 | G20: 276 | H20: 279 | I20: 287 | J20: 295 | K20: 319 | L20: =L21+K20 -> 344 | M20: =M21+L20 -> 369 | N20: =N21+M20 -> 394 | O20: =O21+N20 -> 419 | P20: =P21+O20 -> 419 | Q20: =Q21+P20 -> 419 | R20: =R21+Q20 -> 419
E21: Número de Lojas Abertas | F21: 2 | G21: 0 | H21: 4 | I21: 10 | J21: 10 | K21: 26 | L21: 25 | M21: 25 | N21: 25 | O21: 25 | P21: 0 | Q21: 0 | R21: 0 | T21: Vão abrir 25 lojas por ano seguindo, o guidance fornecido pela empresa, até 2025. | U21: 3
E22: Área Total (m²) - Considera lojas fechadas | F22: 524400 | G22: 518500 | H22: 525800 | I22: 544000 | J22: 559000 | K22: 597000 | L22: - | M22: - | N22: - | O22: -
E23: Área de Lojas Fechadas | F23: 0 | G23: 0 | H23: =H22-H26 -> 9807.05 | I23: =I22-I26 -> 8526.8 | J23: =J22-J26 -> 6381.8 | K23: =K22-K26 -> 3199.46 | L23: =L24*L26 -> 8187.799 | M23: =M24*M26 -> 8789.5547 | N23: =N24*N26 -> 9391.3104 | O23: =O24*O26 -> 9993.0661 | P23: =P24*P26 -> 9993.0661 | Q23: =Q24*Q26 -> 9993.0661 | R23: =R24*R26 -> 9993.0661
E24: (% do total) | F24: 0 | G24: 0 | H24: =H23/H22 -> 0.018651674 | I24: =I23/I22 -> 0.015674265 | J24: =J23/J22 -> 0.011416458 | K24: =K23/K22 -> 0.0053592295 | L24: =AVERAGE(H24:K24) -> 0.012775406 | M24: =L24 -> 0.012775406 | N24: =M24 -> 0.012775406 | O24: =N24 -> 0.012775406 | P24: =O24 -> 0.012775406 | Q24: =P24 -> 0.012775406 | R24: =Q24 -> 0.012775406 | T24: A C&A vai fechar, em média, o mesmo % de m² que fechou ao longo dos últimos 3 anos (2018 até 2020) | U24: 1
E25: Tamanho médio de uma loja (m²) | F25: =F22/F20 -> 1879.5699 | G25: =G22/G20 -> 1878.6232 | H25: =H22/H20 -> 1884.5878 | I25: =I22/I20 -> 1895.4704 | J25: =J22/J20 -> 1894.9153 | K25: =K22/K20 -> 1871.4734 | L25: =AVERAGE(F25:K25) -> 1884.1066 | M25: =L25 -> 1884.1066 | N25: =M25 -> 1884.1066 | O25: =N25 -> 1884.1066 | P25: =O25 -> 1884.1066 | Q25: =P25 -> 1884.1066 | R25: =Q25 -> 1884.1066 | T25: As lojas que serão abertas terão o tamanho médio das lojas abertas desde 2015. | U25: 3
E26: Área Total | F26: =SUM(F27:F30) -> 508002.81 | G26: =SUM(G27:G30) -> 508002.81 | H26: =SUM(H27:H30) -> 515992.95 | I26: =SUM(I27:I30) -> 535473.2 | J26: =SUM(J27:J30) -> 552618.2 | K26: =SUM(K27:K30) -> 593800.54 | L26: =SUM(L27:L30) -> 640903.21 | M26: =SUM(M27:M30) -> 688005.87 | ... R26: =SUM(R27:R30) -> 782211.2
E27: Ano 4 | F27: =SUMIF(Lojas!$E$10:$E$328,"<="&(F19-3),Lojas!$G$10:$G$328) -> 448662.15 | G27: =SUMIF(Lojas!$E$10:$E$328,"<="&(G19-3),Lojas!$G$10:$G$328) -> 483069.25 | H27: =SUMIF(Lojas!$E$10:$E$328,"<="&(H19-3),Lojas!$G$10:$G$328) -> 503640.08 | I27: =SUMIF(Lojas!$E$10:$E$328,"<="&(I19-3),Lojas!$G$10:$G$328) -> 508002.81 | J27: =SUMIF(Lojas!$E$10:$E$328,"<="&(J19-3),Lojas!$G$10:$G$328) -> 508002.81 | K27: =SUMIF(Lojas!$E$10:$E$328,"<="&(K19-3),Lojas!$G$10:$G$328) -> 515992.95 | L27: =K27+K28 -> 535473.2 | M27: =L27+L28 -> 552618.2 | N27: =M27+M28 -> 593800.54 | O27: =N27+N28 -> 640903.21 | P27: =O27+O28 -> 688005.87 | Q27: =P27+P28 -> 735108.54 | R27: =Q27+Q28 -> 782211.2
E28: Ano 3 | F28: =SUMIF(Lojas!$E$10:$E$328,F19-2,Lojas!$G$10:$G$328) -> 34407.1 | G28: =SUMIF(Lojas!$E$10:$E$328,G19-2,Lojas!$G$10:$G$328) -> 20570.83 | H28: =SUMIF(Lojas!$E$10:$E$328,H19-2,Lojas!$G$10:$G$328) -> 4362.73 | I28: =SUMIF(Lojas!$E$10:$E$328,I19-2,Lojas!$G$10:$G$328) -> 0 | J28: =SUMIF(Lojas!$E$10:$E$328,J19-2,Lojas!$G$10:$G$328) -> 7990.14 | K28: =J29 -> 19480.25 | L28: =K29 -> 17145 | M28: =L29 -> 41182.34 | N28: =M29 -> 47102.666 | O28: =N29 -> 47102.666 | P28: =O29 -> 47102.666 | Q28: =P29 -> 47102.666 | R28: =Q29 -> 0
E29: Ano 2 | F29: =SUMIF(Lojas!$E$10:$E$328,F19-1,Lojas!$G$10:$G$328) -> 20570.83 | G29: =SUMIF(Lojas!$E$10:$E$328,G19-1,Lojas!$G$10:$G$328) -> 4362.73 | H29: =SUMIF(Lojas!$E$10:$E$328,H19-1,Lojas!$G$10:$G$328) -> 0 | I29: =SUMIF(Lojas!$E$10:$E$328,I19-1,Lojas!$G$10:$G$328) -> 7990.14 | J29: =SUMIF(Lojas!$E$10:$E$328,J19-1,Lojas!$G$10:$G$328) -> 19480.25 | K29: =J30 -> 17145 | L29: =K30 -> 41182.34 | M29: =L30 -> 47102.666 | N29: =M30 -> 47102.666 | O29: =N30 -> 47102.666 | P29: =O30 -> 47102.666 | Q29: =P30 -> 0 | R29: =Q30 -> 0
E30: Ano 1 | F30: =SUMIF(Lojas!$E$10:$E$328,F19,Lojas!$G$10:$G$328) -> 4362.73 | G30: =SUMIF(Lojas!$E$10:$E$328,G19,Lojas!$G$10:$G$328) -> 0 | H30: =SUMIF(Lojas!$E$10:$E$328,H19,Lojas!$G$10:$G$328) -> 7990.14 | I30: =SUMIF(Lojas!$E$10:$E$328,I19,Lojas!$G$10:$G$328) -> 19480.25 | J30: =SUMIF(Lojas!$E$10:$E$328,J19,Lojas!$G$10:$G$328) -> 17145 | K30: =SUMIF(Lojas!$E$10:$E$328,K19,Lojas!$G$10:$G$328) -> 41182.34 | L30: =L21*L25 -> 47102.666 | M30: =M21*M25 -> 47102.666 | N30: =N21*N25 -> 47102.666 | O30: =O21*O25 -> 47102.666 | P30: =P21*P25 -> 0 | Q30: =Q21*Q25 -> 0 | R30: =R21*R25 -> 0
E31: m² 100% Maduro | F31: =(F30*'Projeções - Receita'!$E$36)+(F29*'Projeções - Receita'!$F$36)+(F28*'Projeções - Receita'!$G$36)+(F27*'Projeções - Receita'!$H$36)+(F23*'Projeções - Receita'!$H$36) -> 493229.98 | G31: =(G30*'Projeções - Receita'!$E$36)+(G29*'Projeções - Receita'!$F$36)+(G28*'Projeções - Receita'!$G$36)+(G27*'Projeções - Receita'!$H$36)+(G23*'Projeções - Receita'!$H$36) -> 503120.1 | H31: =(H30*'Projeções - Receita'!$E$36)+(H29*'Projeções - Receita'!$F$36)+(H28*'Projeções - Receita'!$G$36)+(H27*'Projeções - Receita'!$H$36)+(H23*'Projeções - Receita'!$H$36) -> 521077.81 | I31: =(I30*'Projeções - Receita'!$E$36)+(I29*'Projeções - Receita'!$F$36)+(I28*'Projeções - Receita'!$G$36)+(I27*'Projeções - Receita'!$H$36)+(I23*'Projeções - Receita'!$H$36) -> 531596.5 | J31: =(J30*'Projeções - Receita'!$E$36)+(J29*'Projeções - Receita'!$F$36)+(J28*'Projeções - Receita'!$G$36)+(J27*'Projeções - Receita'!$H$36)+(J23*'Projeções - Receita'!$H$36) -> 542602.39 | K31: =(K30*'Projeções - Receita'!$E$36)+(K29*'Projeções - Receita'!$F$36)+(K28*'Projeções - Receita'!$G$36)+(K27*'Projeções - Receita'!$H$36)-(K23*'Projeções - Receita'!$H$36) -> 561048.2 | L31: =(L30*'Projeções - Receita'!$E$36)+(L29*'Projeções - Receita'!$F$36)+(L28*'Projeções - Receita'!$G$36)+(L27*'Projeções - Receita'!$H$36)-(L23*'Projeções - Receita'!$H$36) -> 592579.13 | M31: =(M30*'Projeções - Receita'!$E$36)+(M29*'Projeções - Receita'!$F$36)+(M28*'Projeções - Receita'!$G$36)+(M27*'Projeções - Receita'!$H$36)-(M23*'Projeções - Receita'!$H$36) -> 633100.37 | N31: =(N30*'Projeções - Receita'!$E$36)+(N29*'Projeções - Receita'!$F$36)+(N28*'Projeções - Receita'!$G$36)+(N27*'Projeções - Receita'!$H$36)-(N23*'Projeções - Receita'!$H$36) -> 678614.56 | O31: =(O30*'Projeções - Receita'!$E$36)+(O29*'Projeções - Receita'!$F$36)+(O28*'Projeções - Receita'!$G$36)+(O27*'Projeções - Receita'!$H$36)-(O23*'Projeções - Receita'!$H$36) -> 725115.47 | P31: =(P30*'Projeções - Receita'!$E$36)+(P29*'Projeções - Receita'!$F$36)+(P28*'Projeções - Receita'!$G$36)+(P27*'Projeções - Receita'!$H$36)-(P23*'Projeções - Receita'!$H$36) -> 748666.81 | Q31: =(Q30*'Projeções - Receita'!$E$36)+(Q29*'Projeções - Receita'!$F$36)+(Q28*'Projeções - Receita'!$G$36)+(Q27*'Projeções - Receita'!$H$36)-(Q23*'Projeções - Receita'!$H$36) -> 764367.69 | R31: =(R30*'Projeções - Receita'!$E$36)+(R29*'Projeções - Receita'!$F$36)+(R28*'Projeções - Receita'!$G$36)+(R27*'Projeções - Receita'!$H$36)-(R23*'Projeções - Receita'!$H$36) -> 772218.14
E32: Receita por m² 100% Maduro | F32: =F11/F31 -> 9.3286035 | G32: =G11/G31 -> 9.4993714 | H32: =H11/H31 -> 9.369213 | I32: =I11/I31 -> 9.5031684 | J32: =J11/J31 -> 7.2297672 | K32: =K11/K31 -> 8.8417234 | L32: =AVERAGE(F32:K32) -> 8.9619745 | M32: =L32+1 -> 9.9619745 | N32: =M32+1 -> 10.961974 | O32: =N32+1 -> 11.961974 | P32: =O32+1 -> 12.961974 | Q32: =P32+1 -> 13.961974 | R32: =Q32+1 -> 14.961974
E35: Ano 1 | F35: Ano 2 | G35: Ano 3 | H35: Ano 4
E36: 0.5 | F36: 0.66666667 | G36: 0.83333333 | H36: 1

Sheet Projeções - EBIT
G5: C&A ($CEAB3)
A7: Páginas
A8: Dashboard
A9: WACC | F9: 2018 | G9: 2019 | H9: 2020 | I9: 2021 | K9: 2022 | L9: 2023 | M9: 2024 | N9: 2025 | O9: =N9+1 -> 2026 | P9: =O9+1 -> 2027 | Q9: =P9+1 -> 2028
A10: DRE + DCF | E10: EBIT Recorrente C&A | F10: ='DRE - Contas Abertas'!H59 -> 356221 | G10: ='DRE - Contas Abertas'!I59 -> 315919 | H10: ='DRE - Contas Abertas'!J59 -> -259017 | I10: ='DRE - Contas Abertas'!K59 -> -117653 | K10: =K11+K12 -> -399446.67 | L10: =L11+L12 -> -379456.58 | M10: =M11+M12 -> -283298.24 | N10: =N11+N12 -> 365925.88 | O10: =O11+O12 -> 604135.52 | P10: =P11+P12 -> 900051.54 | Q10: =Q11+Q12 -> 1090351.8
A11: Balanço Patrimonial | E11: EBIT Recorrente Varejo + Outros | F11: =F10-F12 -> 307621 | G11: =G10-G12 -> 308619 | H11: =H10-H12 -> -227817 | I11: =I10-I12 -> -152853 | K11: =K25 -> -452934.03 | L11: =L25 -> -442977.85 | M11: =M25 -> -373205.42 | N11: =N25 -> 261094.23 | O11: =O25 -> 486850.61 | P11: =P25 -> 749571.69 | Q11: =Q25 -> 927437.96
A12: Projeções | E12: EBIT Bradescard/ C&A Pay | F12: 48600 | G12: 7300 | H12: -31200 | I12: 35200 | K12: =K18 -> 53487.365 | L12: =L18 -> 63521.266 | M12: =M18 -> 89907.176 | N12: =N18 -> 104831.65 | O12: =O18 -> 117284.91 | P12: =P18 -> 150479.85 | Q12: =Q18 -> 162913.88
A13: Lojas
F16: 2018 | G16: 2019 | H16: 2020 | I16: 2021 | J16: 1T22 | K16: =I16+1 -> 2022 | L16: =K16+1 -> 2023 | M16: =L16+1 -> 2024 | N16: =M16+1 -> 2025 | O16: =N16+1 -> 2026 | P16: =O16+1 -> 2027 | Q16: =P16+1 -> 2028
E17: Receita Líquida de Produtos Financeiros | F17: ='Projeções - Receita'!H12 -> 241271 | G17: ='Projeções - Receita'!I12 -> 216402 | H17: ='Projeções - Receita'!J12 -> 149259 | I17: ='Projeções - Receita'!K12 -> 174974 | J17: =56400+9900 -> 66300 | K17: ='Projeções - Receita'!L12 -> 265533.95 | L17: ='Projeções - Receita'!M12 -> 315346.49 | M17: ='Projeções - Receita'!N12 -> 446337.33 | N17: ='Projeções - Receita'!O12 -> 520428.77 | O17: ='Projeções - Receita'!P12 -> 582252 | P17: ='Projeções - Receita'!Q12 -> 747045.76 | Q17: ='Projeções - Receita'!R12 -> 808773.57
E18: EBIT de Produtos Financeiros | F18: 48600 | G18: 7300 | H18: -31200 | I18: 35174 | J18: 17100 | K18: =K19*K17 -> 53487.365 | L18: =L19*L17 -> 63521.266 | M18: =M19*M17 -> 89907.176 | N18: =N19*N17 -> 104831.65 | O18: =O19*O17 -> 117284.91 | P18: =P19*P17 -> 150479.85 | Q18: =Q19*Q17 -> 162913.88
E19: Margem EBIT | F19: 0.20143324 | G19: 0.033733514 | H19: -0.20903262 | I19: 0.20102415 | J19: 0.25791855 | K19: =F19 -> 0.20143324 | L19: =K19 -> 0.20143324 | M19: =L19 -> 0.20143324 | N19: =M19 -> 0.20143324 | O19: =N19 -> 0.20143324 | P19: =O19 -> 0.20143324 | Q19: =P19 -> 0.20143324
F23: 2018 | G23: 2019 | H23: 2020 | I23: 2021 | J23: 1T22 | K23: =I23+1 -> 2022 | L23: =K23+1 -> 2023 | M23: =L23+1 -> 2024 | N23: =M23+1 -> 2025 | O23: =N23+1 -> 2026 | P23: =O23+1 -> 2027 | Q23: =P23+1 -> 2028
E24: Receita Líquida de Varejo + Outros | F24: ='Projeções - Receita'!H11+'Projeções - Receita'!H14 -> 4897843 | G24: ='Projeções - Receita'!I11+'Projeções - Receita'!I14 -> 5068776 | H24: ='Projeções - Receita'!J11+'Projeções - Receita'!J14 -> 3936227 | I24: ='Projeções - Receita'!K11+'Projeções - Receita'!K14 -> 4978232 | J24: ='DRE + DCF'!L11-J17 -> 1130724 | K24: ='Projeções - Receita'!L11+'Projeções - Receita'!L14 -> 5328635.7 | L24: ='Projeções - Receita'!M11+'Projeções - Receita'!M14 -> 6328255 | M24: ='Projeções - Receita'!N11+'Projeções - Receita'!N14 -> 7464108.4 | N24: ='Projeções - Receita'!O11+'Projeções - Receita'!O14 -> 8703141 | O24: ='Projeções - Receita'!P11+'Projeções - Receita'!P14 -> 9737012.2 | P24: ='Projeções - Receita'!Q11+'Projeções - Receita'!Q14 -> 10708167 | Q24: ='Projeções - Receita'!R11+'Projeções - Receita'!R14 -> 11592975
E25: EBIT do Varejo + Outras Receitas | F25: 307621 | G25: 308621 | H25: -227817 | I25: -152826 | J25: -188043 | K25: =K26*K24 -> -452934.03 | L25: =L26*L24 -> -442977.85 | M25: =M26*M24 -> -373205.42 | N25: =N26*N24 -> 261094.23 | O25: =O26*O24 -> 486850.61 | P25: =P26*P24 -> 749571.69 | Q25: =Q26*Q24 -> 927437.96
E26: Margem EBIT | F26: 0.062807444 | G26: 0.060886691 | H26: -0.057876997 | I26: -0.030698851 | J26: -0.16630318 | K26: -0.085 | L26: -0.07 | M26: -0.05 | N26: 0.03 | O26: 0.05 | P26: 0.07 | Q26: 0.08
K37: -0.085 | L37: -0.07 | M37: -0.05 | N37: 0.03 | O37: 0.05 | P37: 0.07 | Q37: 0.08

Sheet Projeções - Capex + CG
E3: C&A ($CEAB3)
A7: Páginas
A8: Dashboard
A9: WACC | F9: 2016 | G9: =F9+1 -> 2017 | H9: =G9+1 -> 2018 | I9: =H9+1 -> 2019 | J9: =I9+1 -> 2020 | K9: 2021 | L9: 2022 | M9: 2023 | N9: 2024 | O9: 2025 | P9: =O9+1 -> 2026 | Q9: =P9+1 -> 2027 | R9: =Q9+1 -> 2028
A10: DRE + DCF | E10: Inflação Implícita | F10: 0.062879882 | G10: 0.029474213 | H10: 0.037455812 | I10: 0.043061516 | J10: 0.045174569 | K10: 0.10060983 | L10: 0.0697 | M10: 0.07177 | N10: 0.05508 | O10: 0.0608 | P10: 0.0626 | Q10: 0.06116 | R10: 0.06639
A11: Balanço Patrimonial | E11: Capital de Giro | F11: ='Balanço Patrimonial'!F9 -> 782152.35 | G11: ='Balanço Patrimonial'!G9 -> 668764.25 | H11: ='Balanço Patrimonial'!H9 -> 764664.85 | I11: ='Balanço Patrimonial'!I9 -> 676487.4 | J11: ='Balanço Patrimonial'!J9 -> 404685.15 | K11: ='Balanço Patrimonial'!K9 -> 391126.12 | L11: =L12*'DRE + DCF'!N11 -> 697553.46 | M11: =M12*'DRE + DCF'!O11 -> 828410.2 | N11: =N12*'DRE + DCF'!P11 -> 986376.73 | O11: =O12*'DRE + DCF'!Q11 -> 1150114 | P11: =P12*'DRE + DCF'!R11 -> 1286739.4 | Q11: =Q12*'DRE + DCF'!S11 -> 1428384.2 | R11: =R12*'DRE + DCF'!T11 -> 1546410.4
A12: Projeções | E12: Como % da Receita Líquida | F12: =F11/'DRE + DCF'!F11 -> 0.16360645 | G12: =G11/'DRE + DCF'!G11 -> 0.132807 | H12: =H11/'DRE + DCF'!H11 -> 0.14879313 | I12: =I11/'DRE + DCF'!I11 -> 0.12799714 | J12: =J11/'DRE + DCF'!J11 -> 0.099054348 | K12: =K11/'DRE + DCF'!K11 -> 0.075899586 | L12: =AVERAGE($F$12:$K$12) -> 0.12469294 | M12: =AVERAGE($F$12:$K$12) -> 0.12469294 | N12: =AVERAGE($F$12:$K$12) -> 0.12469294 | O12: =AVERAGE($F$12:$K$12) -> 0.12469294 | P12: =AVERAGE($F$12:$K$12) -> 0.12469294 | Q12: =AVERAGE($F$12:$K$12) -> 0.12469294 | R12: =AVERAGE($F$12:$K$12) -> 0.12469294
A13: Lojas | E13: CAPEX Líquido (R$ mil) | F13: - | G13: - | H13: - | I13: - | J13: - | K13: =K14-K25 -> 435445 | L13: =L14-L25 -> 124448.77 | M13: =M14-M25 -> 582096.09 | N13: =N14-N25 -> 77606.101 | O13: =O14-O25 -> 193753.57 | P13: =P14-P25 -> -56256.359 | Q13: =Q14-Q25 -> -93976.281 | R13: =R14-R25 -> -131603.71
E14: CAPEX (R$ mil) | F14: =F15+F18+F20+F22+F24 -> 110200 | G14: =G15+G18+G20+G22+G24 -> 98900 | H14: =H15+H18+H20+H22+H24 -> 239700 | I14: =I15+I18+I20+I22+I24 -> 318700 | J14: =J15+J18+J20+J22+J24 -> 302500 | K14: =K15+K18+K20+K22+K24 -> 682100 | L14: =L15+L18+L20+L22+L24 -> 447708.77 | M14: =M15+M18+M20+M22+M24 -> 965997.68 | ... R14: =R15+R18+R20+R22+R24 -> 401381.77
E15: Novas lojas | F15: 16300 | G15: 0 | H15: 24100 | I15: 65700 | J15: 63700 | K15: 178700 | L15: =L16*L17 -> 183803.26 | M15: =M16*M17 -> 196994.82 | N15: =N16*N17 -> 207845.29 | O15: =O16*O17 -> 220482.29 | P15: =P16*P17 -> 0 | Q15: =Q16*Q17 -> 0 | R15: =R16*R17 -> 0
E16: Lojas Abertas | F16: 2 | G16: =COUNTIF(Lojas!$E$10:$E$313,G9) -> 0 | H16: 4 | I16: 10 | J16: 10 | K16: 26 | L16: 25 | M16: 25 | N16: 25 | O16: 25
E17: CAPEX por loja | F17: =IFERROR(F15/F16,0) -> 8150 | G17: =IFERROR(G15/G16,0) -> 0 | H17: =IFERROR(H15/H16,0) -> 6025 | I17: =IFERROR(I15/I16,0) -> 6570 | J17: =IFERROR(J15/J16,0) -> 6370 | K17: =IFERROR(K15/K16,0) -> 6873.0769 | L17: =K17*(1+L$10) -> 7352.1304 | M17: =L17*(1+M$10) -> 7879.7928 | N17: =M17*(1+N$10) -> 8313.8118 | O17: =N17*(1+O$10) -> 8819.2915
E18: Reformas e manutenções | F18: 29800 | G18: 20100 | H18: 132500 | I18: 131600 | J18: 74400 | K18: 59800 | L18: =L19*'DRE + DCF'!N$11 -> 85181.671 | M18: =M19*'DRE + DCF'!O$11 -> 101161.23 | N18: =N19*'DRE + DCF'!P$11 -> 120451.3 | O18: =O19*'DRE + DCF'!N$11 -> 85181.671 | P18: =P19*'DRE + DCF'!O$11 -> 101161.23 | Q18: =Q19*'DRE + DCF'!P$11 -> 120451.3 | R18: =R19*'DRE + DCF'!Q$11 -> 140446.06
E19: Como % da Receita Líquida | F19: =F18/'DRE + DCF'!F$11 -> 0.0062334046 | G19: =G18/'DRE + DCF'!G$11 -> 0.003991572 | H19: =H18/'DRE + DCF'!H$11 -> 0.025782654 | I19: =I18/'DRE + DCF'!I$11 -> 0.024899833 | J19: =J18/'DRE + DCF'!J$11 -> 0.018210808 | K19: =K18/'DRE + DCF'!K$11 -> 0.011604429 | L19: =AVERAGE($F19:$I19) -> 0.015226866 | M19: =AVERAGE($F19:$I19) -> 0.015226866 | N19: =AVERAGE($F19:$I19) -> 0.015226866 | O19: =AVERAGE($F19:$I19) -> 0.015226866 | P19: =AVERAGE($F19:$I19) -> 0.015226866 | Q19: =AVERAGE($F19:$I19) -> 0.015226866 | R19: =AVERAGE($F19:$I19) -> 0.015226866
E20: Centros de distribuição | F20: 4600 | G20: 31200 | H20: 4600 | I20: 15000 | J20: 45000 | K20: 144500 | L20: =L21*'DRE + DCF'!N$11 -> 15231.944 | M20: =M21*'DRE + DCF'!O$11 -> 18089.363 | N20: =N21*'DRE + DCF'!P$11 -> 21538.758 | O20: =O21*'DRE + DCF'!N$11 -> 15231.944 | P20: =P21*'DRE + DCF'!O$11 -> 18089.363 | Q20: =Q21*'DRE + DCF'!P$11 -> 21538.758 | R20: =R21*'DRE + DCF'!Q$11 -> 25114.164
E21: Como % da Receita Líquida | F21: =F20/'DRE + DCF'!F$11 -> 0.0009622034 | G21: =G20/'DRE + DCF'!G$11 -> 0.006195873 | H21: =H20/'DRE + DCF'!H$11 -> 0.00089509593 | I21: =I20/'DRE + DCF'!I$11 -> 0.0028381269 | J21: =J20/'DRE + DCF'!J$11 -> 0.011014601 | K21: =K20/'DRE + DCF'!K$11 -> 0.028040802 | L21: =AVERAGE($F21:$I21) -> 0.0027228248 | M21: =AVERAGE($F21:$I21) -> 0.0027228248 | N21: =AVERAGE($F21:$I21) -> 0.0027228248 | O21: =AVERAGE($F21:$I21) -> 0.0027228248 | P21: =AVERAGE($F21:$I21) -> 0.0027228248 | Q21: =AVERAGE($F21:$I21) -> 0.0027228248 | R21: =AVERAGE($F21:$I21) -> 0.0027228248
E22: TI e outros | F22: 59500 | G22: 47600 | H22: 78500 | I22: 106400 | J22: 119400 | K22: 299100 | L22: =L23*'DRE + DCF'!N11 -> 163491.9 | M22: =L22*(1+M10) -> 175225.71 | N22: =M22*(1+N10) -> 184877.14 | O22: =N22*(1+O10) -> 196117.67 | P22: =O22*(1+P10) -> 208394.64 | Q22: =P22*(1+Q10) -> 221140.05 | R22: =Q22*(1+R10) -> 235821.54
E23: Como % da Receita Líquida | F23: =F22/'DRE + DCF'!F$11 -> 0.012445892 | G23: =G22/'DRE + DCF'!G$11 -> 0.009452678 | H23: =H22/'DRE + DCF'!H$11 -> 0.015275007 | I23: =I22/'DRE + DCF'!I$11 -> 0.02013178 | J23: =J22/'DRE + DCF'!J$11 -> 0.029225409 | K23: =K22/'DRE + DCF'!K$11 -> 0.058041549 | L23: =J23 -> 0.029225409 | M23: =M22/'DRE + DCF'!N$11 -> 0.031322917 | N23: =N22/'DRE + DCF'!O$11 -> 0.02782785 | O23: =O22/'DRE + DCF'!M$11 -> 0.044601132 | P23: =P22/'DRE + DCF'!N$11 -> 0.037252113 | Q23: =Q22/'DRE + DCF'!O$11 -> 0.033286171 | R23: =R22/'DRE + DCF'!P$11 -> 0.02981141
E24: Aquisições | F24: 0 | G24: 0 | H24: 0 | I24: 0 | J24: 0 | K24: 0 | L24: 0 | M24: =415000*(1+(112.5%*12.75%)) -> 474526.56 | N24: 0 | O24: 0 | P24: 0 | Q24: 0 | R24: 0
E25: Depreciação & Amortização | F25: 202684 | G25: 197897 | H25: 205091 | I25: 233042 | J25: 246322 | K25: 246655 | L25: ='DRE + DCF'!N44 -> 323260 | M25: ='DRE + DCF'!O44 -> 383901.59 | N25: ='DRE + DCF'!P44 -> 457106.39 | O25: ='DRE + DCF'!N44 -> 323260 | P25: ='DRE + DCF'!O44 -> 383901.59 | Q25: ='DRE + DCF'!P44 -> 457106.39 | R25: ='DRE + DCF'!Q44 -> 532985.48
E26: Depreciação e Amortização como % da Receita Líquida | F26: =F25/'DRE + DCF'!F11 -> 0.042396355 | G26: =G25/'DRE + DCF'!G11 -> 0.039299509 | H26: =H25/'DRE + DCF'!H11 -> 0.039907852 | I26: =I25/'DRE + DCF'!I11 -> 0.044093517 | J26: =J25/'DRE + DCF'!J11 -> 0.06029197 | K26: =K25/'DRE + DCF'!K11 -> 0.047864387 | L26: =L25/'DRE + DCF'!N11 -> 0.057785162 | M26: =M25/'DRE + DCF'!O11 -> 0.057785162 | N26: =N25/'DRE + DCF'!P11 -> 0.057785162 | O26: =O25/'DRE + DCF'!N11 -> 0.057785162 | P26: =P25/'DRE + DCF'!O11 -> 0.057785162 | Q26: =Q25/'DRE + DCF'!P11 -> 0.057785162 | R26: =R25/'DRE + DCF'!Q11 -> 0.057785162
E27: Depreciação & Amortização do Arrendamento | F27: 0 | G27: 0 | H27: 0 | I27: 295675 | J27: 306443 | K27: 338325 | L27: ='DRE + DCF'!N38 -> 385418.88 | M27: ='DRE + DCF'!O38 -> 457721.09 | N27: ='DRE + DCF'!P38 -> 545002.26 | O27: ='DRE + DCF'!N38 -> 385418.88 | P27: ='DRE + DCF'!O38 -> 457721.09 | Q27: ='DRE + DCF'!P38 -> 545002.26 | R27: ='DRE + DCF'!Q38 -> 635471.95
E31: Renner | F31: Marisa | G31: Guararapes
E32: 0.35144073 | F32: 0.27306588 | G32: 0.21498377
F36: 2005 | G36: 2006 | H36: 2007 | I36: 2008 | J36: 2009 | K36: 2010 | L36: 2011 | M36: 2012 | N36: 2013 | O36: 2014 | P36: 2015 | Q36: 2016 | R36: 2017 | S36: 2018 | T36: 2019 | U36: 2020 | V36: 2021 | W36: CAGR
E37: Cartões emitidos | F37: 1.1072 | G37: 1.6 | H37: 1.734 | I37: 1.6 | J37: 1.66 | K37: 1.878 | L37: 1.904 | M37: 1.739 | N37: 1.7359 | O37: 1.7901 | P37: 1.7 | Q37: 1.392573 | R37: 1.468117 | S37: 1.735974 | T37: 1.944848 | U37: 1.236141 | V37: 0.930935
E38: Total de Cartões | F38: 8.7 | G38: 10.3 | H38: 12 | I38: 13.6 | J38: 15.2 | K38: 17.1 | L38: 19 | M38: 20.8 | N38: 22.5 | O38: 24.3 | P38: 26 | Q38: 27.4 | R38: 28.847245 | S38: 30.583219 | T38: 32.528067 | U38: 33.764208 | V38: 34.695143 | W38: =(O38/F38)^(1/COUNT(G36:O36))-1 -> 0.12089576

Sheet Trimestres 2022
E3: C&A ($CEAB3)
A7: Páginas
A8: Dashboard
A9: WACC | F9: 1T22R | G9: 2T22E | H9: 3T22E | I9: 4T22E | J9: 2022E
A10: DRE + DCF | E10: Receita Líquida | F10: 1197024 | G10: =($J$10-$F$10)*SUM(G21,G23)/SUM($G$21:$I$21,$G$23:$I$23) -> 1309906 | H10: =($J$10-$F$10)*SUM(H21,H23)/SUM($G$21:$I$21,$G$23:$I$23) -> 1288114.5 | I10: =($J$10-$F$10)*SUM(I21,I23)/SUM($G$21:$I$21,$G$23:$I$23) -> 1799125.1 | J10: ='Projeções - Receita'!L10 -> 5594169.6
A11: Balanço Patrimonial | E11: Margem Bruta | F11: =F12/F10 -> 0.47402475 | G11: =AVERAGE(G33,G35) -> 0.49794031 | H11: =AVERAGE(H33,H35) -> 0.47615169 | I11: =AVERAGE(I33,I35) -> 0.50400742 | J11: =J12/J10 -> 0.4897571
A12: Projeções | E12: Lucro Bruto | F12: 567419 | G12: =G11*G10 -> 652255.01 | H12: =H11*H10 -> 613337.89 | I12: =I11*I10 -> 906772.4 | J12: =SUM(F12:I12) -> 2739784.3
A13: Lojas | E13: Despesas Operacionais | F13: -738362 | G13: =F13 -> -738362 | H13: =G13 -> -738362 | I13: =H13*(1+AVERAGE(I45,I47)) -> -827671.76 | J13: =SUM(F13:I13) -> -3042757.8
E14: EBIT Recorrente | F14: =F12+F13 -> -170943 | G14: =G12+G13 -> -86106.988 | H14: =H12+H13 -> -125024.11 | I14: =I12+I13 -> 79100.633 | J14: =SUM(F14:I14) -> -302973.46
E15: Margem EBIT | F15: =F14/F10 -> -0.14280666 | G15: =G14/G10 -> -0.065735241 | H15: =H14/H10 -> -0.097059777 | I15: =I14/I10 -> 0.043966166 | J15: =J14/J10 -> -0.054158791
F19: 1º Trimestre | G19: 2º Trimestre | H19: 3º Trimestre | I19: 4º Trimestre
E20: 2018 | F20: 998905.99 | G20: 1235291.1 | H20: 1214187.8 | I20: 1690728.8
E21: % sobre total do ano | F21: =F20/SUM($F20:$I20) -> 0.19437321 | G21: =G20/SUM($F20:$I20) -> 0.24037045 | H21: =H20/SUM($F20:$I20) -> 0.23626404 | I21: =I20/SUM($F20:$I20) -> 0.3289923
E22: 2019 | F22: 1035006.9 | G22: 1264140.6 | H22: 1243679.2 | I22: 1742349.8
E23: % sobre total do ano | F23: =F22/SUM($F22:$I22) -> 0.19583203 | G23: =G22/SUM($F22:$I22) -> 0.23918607 | H23: =H22/SUM($F22:$I22) -> 0.2353146 | I23: =I22/SUM($F22:$I22) -> 0.32966729
E24: 2020 | F24: 976850 | G24: 294492 | H24: 1067151 | I24: 1746993
E25: % sobre total do ano | F25: =F24/SUM($F24:$I24) -> 0.23910252 | G25: =G24/SUM($F24:$I24) -> 0.072082489 | H25: =H24/SUM($F24:$I24) -> 0.2612054 | I25: =I24/SUM($F24:$I24) -> 0.42760959
E26: 2021 | F26: 776075 | G26: 1175590 | H26: 1339407 | I26: 1862133 | J26: =I26/I27 -> 5153205
E27: % sobre total do ano | F27: =F26/SUM($F26:$I26) -> 0.15060045 | G27: =G26/SUM($F26:$I26) -> 0.22812793 | H27: =H26/SUM($F26:$I26) -> 0.25991727 | I27: =I26/SUM($F26:$I26) -> 0.36135434 | J27: =J26/'Projeções - Receita'!#REF! -> #REF!
J28: =J27/'Projeções - Receita'!K31*1000 -> #REF!
F31: 1º Trimestre | G31: 2º Trimestre | H31: 3º Trimestre | I31: 4º Trimestre
E32: 2018 | F32: 471531 | G32: 624212 | H32: 582358 | I32: 871042
E33: Margem Bruta | F33: =F32/F20 -> 0.47204742 | G33: =G32/G20 -> 0.50531573 | H33: =H32/H20 -> 0.47962763 | I33: =I32/I20 -> 0.51518729
E34: 2019 | F34: 501433 | G34: 620143 | H34: 587857 | I34: 858678
E35: Margem Bruta | F35: =F34/F22 -> 0.48447312 | G35: =G34/G22 -> 0.49056489 | H35: =H34/H22 -> 0.47267575 | I35: =I34/I22 -> 0.49282756
E36: 2020 | F36: 476331 | G36: 143255 | H36: 455025 | I36: 822015
E37: Margem Bruta | F37: =F36/F24 -> 0.48761939 | G37: =G36/G24 -> 0.48644785 | H37: =H36/H24 -> 0.42639233 | I37: =I36/I24 -> 0.47053136
E38: 2021 | F38: 350996 | G38: 548437 | H38: 599338 | I38: 898538
E39: Margem Bruta | F39: =F38/F26 -> 0.45227072 | G39: =G38/G26 -> 0.46652064 | H39: =H38/H26 -> 0.44746518 | I39: =I38/I26 -> 0.48253159
F43: 1º Trimestre | G43: 2º Trimestre | H43: 3º Trimestre | I43: 4º Trimestre
E44: 2018 | F44: -535662 | G44: -517007 | H44: -520616 | I44: -610726
E45: Como % da Receita Líquida | F45: 0 | G45: =G44/F44-1 -> -0.034826066 | H45: =H44/G44-1 -> 0.0069805631 | I45: =I44/H44-1 -> 0.17308342
E46: 2019 | F46: =109414-'DRE - Contas Abertas'!I58 -> -607751 | G46: -548015 | H46: -529974 | I46: -566452
E47: Como % da Receita Líquida | F47: 0 | G47: =G46/F46-1 -> -0.098290254 | H47: =H46/G46-1 -> -0.032920632 | I47: =I46/H46-1 -> 0.068829792
E48: 2020 | F48: -526250 | G48: -387740 | H48: -494227 | I48: -652648
E49: Como % da Receita Líquida | F49: 0 | G49: =G48/F48-1 -> -0.2632019 | H49: =H48/G48-1 -> 0.27463506 | I49: =I48/H48-1 -> 0.32054299
E50: 2021 | F50: -520090 | G50: -462696 | H50: -639956 | I50: -681768
E51: Como % da Receita Líquida | F51: 0 | G51: =G50/F50-1 -> -0.11035398 | H51: =H50/G50-1 -> 0.38310251 | I51: =I50/H50-1 -> 0.065335742
F55: 1º Trimestre | G55: 2º Trimestre | H55: 3º Trimestre | I55: 4º Trimestre
E56: 2018 | F56: =F32+F44 -> -64131 | G56: =G32+G44 -> 107205 | H56: =H32+H44 -> 61742 | I56: =I32+I44 -> 260316
E57: Margem EBIT | F57: =F56/F20 -> -0.064201237 | G57: =G56/G20 -> 0.086785215 | H57: =H56/H20 -> 0.050850455 | I57: =I56/I20 -> 0.15396674
E58: 2019 | F58: =F34+F46 -> -106318 | G58: =G34+G46 -> 72128 | H58: =H34+H46 -> 57883 | I58: =I34+I46 -> 292226
E59: Margem EBIT | F59: =F58/F22 -> -0.10272202 | G59: =G58/G22 -> 0.057056944 | H59: =H58/H22 -> 0.046541745 | I59: =I58/I22 -> 0.16771948
E60: 2020 | F60: =F36+F48 -> -49919 | G60: =G36+G48 -> -244485 | H60: =H36+H48 -> -39202 | I60: =I36+I48 -> 169367
E61: Margem EBIT | F61: =F60/F24 -> -0.051102012 | G61: =G60/G24 -> -0.83019233 | H61: =H60/H24 -> -0.036735195 | I61: =I60/I24 -> 0.096947727
E62: 2021 | F62: =F38+F50 -> -169094 | G62: =G38+G50 -> 85741 | H62: =H38+H50 -> -40618 | I62: =I38+I50 -> 216770
E63: Margem EBIT | F63: =F62/F26 -> -0.21788358 | G63: =G62/G26 -> 0.072934441 | H63: =H62/H26 -> -0.03032536 | I63: =I62/I26 -> 0.11640952

Sheet Lojas
E4: C&A ($CEAB3)
A7: Páginas
A8: Dashboard
A9: WACC | E9: Data de Abertura | F9: Localização | G9: Tamanho (m²) | H9: Cidade | I9: Local | J9: Estado | K9: Região
A10: DRE + DCF | E10: 1976 | F10: SHOPPING MALL | G10: 2705.09 | H10: SÃO PAULO | I10: SHOPPING IBIRAPUERA | J10: SP | K10: Sudeste
A11: Balanço Patrimonial | E11: 1977 | F11: STREET | G11: 2256.38 | H11: CAMPINAS | I11: CAMPINAS - CENTRO | J11: SP | K11: Sudeste
A12: Projeções | E12: 1977 | F12: STREET | G12: 3651.86 | H12: CURITIBA | I12: CURITIBA-CENTRO | J12: PR | K12: Sul
A13: Lojas | E13: 1978 | F13: STREET | G13: 3366.36 | H13: PORTO ALEGRE | I13: PORTO ALEGRE | J13: RS | K13: Sul
E14: 1979 | F14: STREET | G14: 2172.77 | H14: RIO DE JANEIRO | I14: COPACABANA | J14: RJ | K14: Sudeste
E15: 1979 | F15: SHOPPING MALL | G15: 2029.82 | H15: BELO HORIZONTE | I15: BH SHOPPING | J15: MG | K15: Sudeste
E16: 1980 | F16: STREET | G16: 1882.06 | H16: SANTO ANDRE | I16: SANTO ANDRE CENTRO | J16: SP | K16: Sudeste
E17: 1980 | F17: SHOPPING MALL | G17: 2034.47 | H17: CAMPINAS | I17: SHOPPING IGUATEMI CAMPINAS | J17: SP | K17: Sudeste
E18: 1981 | F18: SHOPPING MALL | G18: 2118.11 | H18: RIBEIRÃO PRETO | I18: RIBEIRAO SHOPPING | J18: SP | K18: Sudeste
E19: 1981 | F19: STREET | G19: 2737 | H19: RIO DE JANEIRO | I19: TIJUCA | J19: RJ | K19: Sudeste
E20: 1981 | F20: SHOPPING MALL | G20: 1930.23 | H20: GOIANIA | I20: FLAMBOYANT SHOPPING CENTER | J20: GO | K20: Centro oeste
E21: 1981 | F21: SHOPPING MALL | G21: 3490.36 | H21: RIO DE JANEIRO | I21: BARRA SHOPPING | J21: RJ | K21: Sudeste
E22: 1982 | F22: SHOPPING MALL | G22: 3163.96 | H22: SÃO PAULO | I22: SHOPPING MORUMBI | J22: SP | K22: Sudeste
E23: 1982 | F23: STREET | G23: 3348.48 | H23: BELO HORIZONTE | I23: BELO HORIZONTE | J23: MG | K23: Sudeste
E24: 1982 | F24: STREET | G24: 2678.02 | H24: SANTOS | I24: CONJTO ATLANTICO (SHOPPING) | J24: SP | K24: Sudeste
E25: 1983 | F25: SHOPPING MALL | G25: 2641.58 | H25: CAXIAS DO SUL | I25: SHOPPING CENTER IGUATEMI | J25: RS | K25: Sul
... E328: 2022 | F328: SHOPPING MALL | G328: 1712 | H328: SÃO PAULO | I328: Shopping Trimais Hiper Center | J328: SP | K328: Sudeste
