Workbook

Sheet PROJETO 1
B2: COMPANHIA REAL ESTATE - PROJETO 1
B3: Em Milhoes de Reais
C5: Lançamentos (R$Mn)
D7: Ano 1 | E7: Ano 2 | F7: Ano 3 | G7: Ano 4 | H7: Ano 5 | I7: Ano 6 | J7: Ano 7 | K7: Ano 8 | L7: Ano 9 | M7: Ano 10
D8: 100
C10: Comissão Vendas | E10: 0.04
C12: Lançamentos (R$Mn)
D14: Ano 1 | E14: Ano 2 | F14: Ano 3 | G14: Ano 4 | H14: Ano 5 | I14: Ano 6 | J14: Ano 7 | K14: Ano 8 | L14: Ano 9 | M14: Ano 10
C15: Ano 1 | D15: =+D$8*(1-$E$10) -> 96
C16: Ano 2 | E16: =+E$8*(1-$E$10) -> 0
C17: Ano 3 | F17: =+F$8*(1-$E$10) -> 0
C18: Ano 4 | G18: =+G$8*(1-$E$10) -> 0
C19: Ano 5 | H19: =+H$8*(1-$E$10) -> 0
C20: Ano 6 | I20: =+I$8*(1-$E$10) -> 0
C21: Ano 7 | J21: =+J$8*(1-$E$10) -> 0
C22: Ano 8 | K22: =+K$8*(1-$E$10) -> 0
C23: Ano 9 | L23: =+L$8*(1-$E$10) -> 0
C24: Ano 10 | M24: =+M$8*(1-$E$10) -> 0
D25: =SUM(D15:D24) -> 96 | E25: =SUM(E15:E24) -> 0 | F25: =SUM(F15:F24) -> 0 | G25: =SUM(G15:G24) -> 0 | H25: =SUM(H15:H24) -> 0 | I25: =SUM(I15:I24) -> 0 | J25: =SUM(J15:J24) -> 0 | K25: =SUM(K15:K24) -> 0 | ... M25: =SUM(M15:M24) -> 0
C27: Vendas %
D29: Ano 1 | E29: Ano 2 | F29: Ano 3 | G29: Ano 4 | H29: Ano 5 | I29: Ano 6 | J29: Ano 7 | K29: Ano 8 | L29: Ano 9 | M29: Ano 10
C30: Ano 1 | D30: 0.4 | E30: 0.2 | F30: 0.3 | G30: 0.1
C31: Ano 2
C32: Ano 3
C33: Ano 4
C34: Ano 5
C35: Ano 6
C36: Ano 7
C37: Ano 8
C38: Ano 9
C39: Ano 10
C41: Captação Pre-Chaves | F41: 0.9
D43: Ano 1 | E43: Ano 2 | F43: Ano 3 | G43: Ano 4 | H43: Ano 5 | I43: Ano 6 | J43: Ano 7 | K43: Ano 8 | L43: Ano 9 | M43: Ano 10 | N43: TOTAL
C44: 1 | D44: =+$F$41/3 -> 0.3 | E44: =+F41/3 -> 0.3 | F44: =+F41/3 -> 0.3 | G44: =+(1-$F$41) -> 0.1 | N44: =SUM(D44:M44) -> 1
C45: 2 | E45: =+$F$41/2 -> 0.45 | F45: =+$F$41/2 -> 0.45 | G45: =+(1-$F$41) -> 0.1 | N45: =SUM(D45:M45) -> 1
C46: 3 | F46: =+$F$41 -> 0.9 | G46: =+(1-$F$41) -> 0.1 | N46: =SUM(D46:M46) -> 1
C47: 4 | G47: 1 | N47: =SUM(D47:M47) -> 1
C49: Receita Bruta (R$Mn)
D51: Ano 1 | E51: Ano 2 | F51: Ano 3 | G51: Ano 4 | H51: Ano 5 | I51: Ano 6 | J51: Ano 7 | K51: Ano 8 | L51: Ano 9 | M51: Ano 10 | Q51: TOTAL
C52: Ano 1 | D52: =+$D$15*$D$30*D$44 -> 11.52 | E52: =+$D$15*$D$30*E$44 -> 11.52 | F52: =+$D$15*$D$30*F$44 -> 11.52 | G52: =+$D$15*$D$30*G$44 -> 3.84 | Q52: =SUM(D52:P52) -> 38.4
C53: Ano 1 | E53: =+$D$15*$E$30*$E$45 -> 8.64 | F53: =+$D$15*$E$30*$F$45 -> 8.64 | G53: =+$D$15*$E$30*$G$45 -> 1.92 | Q53: =SUM(D53:P53) -> 19.2
C54: Ano 1 | F54: =+$D$15*$F$30*$F$46 -> 25.92 | G54: =+$D$15*$F$30*$G$46 -> 2.88 | Q54: =SUM(D54:P54) -> 28.8
C55: Ano 1 | G55: =+$D$15*$G$30*$G$47 -> 9.6 | Q55: =SUM(D55:P55) -> 9.6
C56: Ano 2 | E56: =+$E$16*$E$31*D$44 -> 0 | F56: =+$E$16*$E$31*E$44 -> 0 | G56: =+$E$16*$E$31*F$44 -> 0 | H56: =+$E$16*$E$31*G$44 -> 0 | Q56: =SUM(D56:P56) -> 0
C57: Ano 2 | F57: =+$E$16*$F$31*E$45 -> 0 | G57: =+$E$16*$F$31*F$45 -> 0 | H57: =+$E$16*$F$31*G$45 -> 0 | Q57: =SUM(D57:P57) -> 0
C58: Ano 2 | G58: =+$E$16*$G$31*$F$46 -> 0 | H58: =+$E$16*$G$31*$G$46 -> 0 | Q58: =SUM(D58:P58) -> 0
C59: Ano 2 | H59: =+$E$16*$H$31*$G$47 -> 0 | Q59: =SUM(D59:P59) -> 0
C60: Ano 3 | F60: =+$F$17*$F$32*D$44 -> 0 | G60: =+$F$17*$F$32*E$44 -> 0 | H60: =+$F$17*$F$32*F$44 -> 0 | I60: =+$F$17*$F$32*G$44 -> 0 | Q60: =SUM(D60:P60) -> 0
C61: Ano 3 | G61: =+$F$17*$G$32*E$45 -> 0 | H61: =+$F$17*$G$32*F$45 -> 0 | I61: =+$F$17*$G$32*G$45 -> 0 | Q61: =SUM(D61:P61) -> 0
C62: Ano 3 | H62: =+$F$17*$H$32*F$46 -> 0 | I62: =+$F$17*$H$32*G$46 -> 0 | Q62: =SUM(D62:P62) -> 0
C63: Ano 3 | I63: =+$F$17*$I$32*$G$47 -> 0 | Q63: =SUM(D63:P63) -> 0
C64: Ano 4 | G64: =+$G$18*$G$33*D$44 -> 0 | H64: =+$G$18*$G$33*E$44 -> 0 | I64: =+$G$18*$G$33*F$44 -> 0 | J64: =+$G$18*$G$33*G$44 -> 0 | Q64: =SUM(D64:P64) -> 0
C65: Ano 4 | H65: =+$G$18*$H$33*E$45 -> 0 | I65: =+$G$18*$H$33*F$45 -> 0 | J65: =+$G$18*$H$33*G$45 -> 0 | Q65: =SUM(D65:P65) -> 0
C66: Ano 4 | I66: =+$G$18*$I$33*F$46 -> 0 | J66: =+$G$18*$I$33*G$46 -> 0 | Q66: =SUM(D66:P66) -> 0
C67: Ano 4 | J67: =+$G$18*$J$33*G$47 -> 0 | Q67: =SUM(D67:P67) -> 0
C68: Ano 5 | H68: =+$H$19*$H$34*D$44 -> 0 | I68: =+$H$19*$H$34*E$44 -> 0 | J68: =+$H$19*$H$34*F$44 -> 0 | K68: =+$H$19*$H$34*G$44 -> 0 | Q68: =SUM(D68:P68) -> 0
C69: Ano 5 | I69: =+$H$19*$I$34*E$45 -> 0 | J69: =+$H$19*$I$34*F$45 -> 0 | K69: =+$H$19*$I$34*G$45 -> 0 | Q69: =SUM(D69:P69) -> 0
C70: Ano 5 | J70: =+$H$19*$J$34*F$46 -> 0 | K70: =+$H$19*$J$34*G$46 -> 0 | Q70: =SUM(D70:P70) -> 0
C71: Ano 5 | K71: =+$H$19*$K$34*G$47 -> 0 | Q71: =SUM(D71:P71) -> 0
C72: Ano 6 | I72: =+$I$20*$I$35*D$44 -> 0 | J72: =+$I$20*$I$35*E$44 -> 0 | K72: =+$I$20*$I$35*F$44 -> 0 | L72: =+$I$20*$I$35*G$44 -> 0 | Q72: =SUM(D72:P72) -> 0
C73: Ano 6 | J73: =+$I$20*$J$35*E$45 -> 0 | K73: =+$I$20*$J$35*F$45 -> 0 | L73: =+$I$20*$J$35*G$45 -> 0 | Q73: =SUM(D73:P73) -> 0
C74: Ano 6 | K74: =+$I$20*$K$35*F$46 -> 0 | L74: =+$I$20*$K$35*G$46 -> 0 | Q74: =SUM(D74:P74) -> 0
C75: Ano 6 | L75: =+$I$20*$L$35*G$47 -> 0 | Q75: =SUM(D75:P75) -> 0
C76: Ano 7 | J76: =+$J$21*$J$36*D$44 -> 0 | K76: =+$J$21*$J$36*E$44 -> 0 | L76: =+$J$21*$J$36*F$44 -> 0 | M76: =+$J$21*$J$36*G$44 -> 0 | Q76: =SUM(D76:P76) -> 0
C77: Ano 7 | K77: =+$J$21*$K$36*E$45 -> 0 | L77: =+$J$21*$K$36*F$45 -> 0 | M77: =+$J$21*$K$36*G$45 -> 0 | Q77: =SUM(D77:P77) -> 0
C78: Ano 7 | L78: =+$J$21*$L$36*F$46 -> 0 | M78: =+$J$21*$L$36*G$46 -> 0 | Q78: =SUM(D78:P78) -> 0
C79: Ano 7 | M79: =+$J$21*$M$36*G$47 -> 0 | Q79: =SUM(D79:P79) -> 0
C80: Ano 8 | K80: =+$K$22*$K$37*D$44 -> 0 | L80: =+$K$22*$K$37*E$44 -> 0 | M80: =+$K$22*$K$37*F$44 -> 0 | N80: =+$K$22*$K$37*G$44 -> 0 | Q80: =SUM(D80:P80) -> 0
C81: Ano 8 | L81: =+$K$22*$L$37*E$45 -> 0 | M81: =+$K$22*$L$37*F$45 -> 0 | N81: =+$K$22*$L$37*G$45 -> 0 | Q81: =SUM(D81:P81) -> 0
C82: Ano 8 | M82: =+$K$22*$M$37*F$46 -> 0 | N82: =+$K$22*$M$37*G$46 -> 0 | Q82: =SUM(D82:P82) -> 0
C83: Ano 8 | N83: =+$K$22*$N$37*G$47 -> 0 | Q83: =SUM(D83:P83) -> 0
C84: Ano 9 | L84: =+$L$23*$L$38*D$44 -> 0 | M84: =+$L$23*$L$38*E$44 -> 0 | N84: =+$L$23*$L$38*F$44 -> 0 | O84: =+$L$23*$L$38*G$44 -> 0 | Q84: =SUM(D84:P84) -> 0
C85: Ano 9 | M85: =+$L$23*$M$38*E$45 -> 0 | N85: =+$L$23*$M$38*F$45 -> 0 | O85: =+$L$23*$M$38*G$45 -> 0 | Q85: =SUM(D85:P85) -> 0
C86: Ano 9 | N86: =+$L$23*$N$38*F$46 -> 0 | O86: =+$L$23*$N$38*G$46 -> 0 | Q86: =SUM(D86:P86) -> 0
C87: Ano 9 | O87: =+$L$23*$O$38*G$47 -> 0 | Q87: =SUM(D87:P87) -> 0
C88: Ano 10 | M88: =+$M$24*$M$39*D$44 -> 0 | N88: =+$M$24*$M$39*E$44 -> 0 | O88: =+$M$24*$M$39*F$44 -> 0 | P88: =+$M$24*$M$39*G$44 -> 0 | Q88: =SUM(D88:P88) -> 0
C89: Ano 10 | N89: =+$M$24*$N$39*E$45 -> 0 | O89: =+$M$24*$N$39*F$45 -> 0 | P89: =+$M$24*$N$39*G$45 -> 0 | Q89: =SUM(D89:P89) -> 0
C90: Ano 10 | O90: =+$M$24*$O$39*F$46 -> 0 | P90: =+$M$24*$O$39*G$46 -> 0 | Q90: =SUM(D90:P90) -> 0
C91: Ano 10 | P91: =+$M$24*$P$39*G$47 -> 0 | Q91: =SUM(D91:P91) -> 0
D92: =SUM(D52:D91) -> 11.52 | E92: =SUM(E52:E91) -> 20.16 | F92: =SUM(F52:F91) -> 46.08 | G92: =SUM(G52:G91) -> 18.24 | H92: =SUM(H52:H91) -> 0 | I92: =SUM(I52:I91) -> 0 | J92: =SUM(J52:J91) -> 0 | K92: =SUM(K52:K91) -> 0 | ... M92: =SUM(M52:M91) -> 0
C94: Custo Terreno/ VGV | F94: 0.2
C96: Percentual Medio Permuta | F96: 0.3
C98: Parcela Cash | F98: 1 | G98: (mesmo ano)
D100: Ano 1 | E100: Ano 2 | F100: Ano 3 | G100: Ano 4 | H100: Ano 5 | I100: Ano 6 | J100: Ano 7 | K100: Ano 8 | L100: Ano 9 | M100: Ano 10
C101: Permuta | D101: =-$F$94*$F$96*D104 -> -0.6912 | E101: =-$F$94*$F$96*E104 -> -1.2096 | F101: =-$F$94*$F$96*F104 -> -2.7648 | G101: =-$F$94*$F$96*G104 -> -1.0944 | H101: =-$F$94*$F$96*H104 -> 0 | I101: =-$F$94*$F$96*I104 -> 0 | J101: =-$F$94*$F$96*J104 -> 0 | K101: =-$F$94*$F$96*K104 -> 0 | ... M101: =-$F$94*$F$96*M104 -> 0
C102: Cash | D102: =-$F$94*$F$96*D25 -> -5.76 | E102: =-$F$94*$F$96*E25 -> 0 | F102: =-$F$94*$F$96*F25 -> 0 | G102: =-$F$94*$F$96*G25 -> 0 | H102: =-$F$94*$F$96*H25 -> 0 | I102: =-$F$94*$F$96*I25 -> 0 | J102: =-$F$94*$F$96*J25 -> 0 | K102: =-$F$94*$F$96*K25 -> 0 | ... M102: =-$F$94*$F$96*M25 -> 0
C104: Receita Bruta | D104: =+D92 -> 11.52 | E104: =+E92 -> 20.16 | F104: =+F92 -> 46.08 | G104: =+G92 -> 18.24 | H104: =+H92 -> 0 | I104: =+I92 -> 0 | J104: =+J92 -> 0 | K104: =+K92 -> 0 | ... M104: =+M92 -> 0
C105: Cresc % | E105: =IFERROR(E104/D104-1,0) -> 0.75 | F105: =IFERROR(F104/E104-1,0) -> 1.2857143 | G105: =IFERROR(G104/F104-1,0) -> -0.60416667 | H105: =IFERROR(H104/G104-1,0) -> -1 | I105: =IFERROR(I104/H104-1,0) -> 0 | J105: =IFERROR(J104/I104-1,0) -> 0 | K105: =IFERROR(K104/J104-1,0) -> 0 | L105: =IFERROR(L104/K104-1,0) -> 0 | M105: =IFERROR(M104/L104-1,0) -> 0
C106: Impostos | D106: =-D107*D104 -> -0.4608 | E106: =-E107*E104 -> -0.8064 | F106: =-F107*F104 -> -1.8432 | G106: =-G107*G104 -> -0.7296 | H106: =-H107*H104 -> 0 | I106: =-I107*I104 -> 0 | J106: =-J107*J104 -> 0 | K106: =-K107*K104 -> 0 | ... M106: =-M107*M104 -> 0
C107: Impostos % | D107: 0.04 | E107: =+D107 -> 0.04 | F107: =+E107 -> 0.04 | G107: =+F107 -> 0.04 | H107: =+G107 -> 0.04 | I107: =+H107 -> 0.04 | J107: =+I107 -> 0.04 | K107: =+J107 -> 0.04 | L107: =+K107 -> 0.04 | M107: =+L107 -> 0.04
C109: Receita Líquida | D109: =+D104+D106 -> 11.0592 | E109: =+E104+E106 -> 19.3536 | F109: =+F104+F106 -> 44.2368 | G109: =+G104+G106 -> 17.5104 | H109: =+H104+H106 -> 0 | I109: =+I104+I106 -> 0 | J109: =+J104+J106 -> 0 | K109: =+K104+K106 -> 0 | ... M109: =+M104+M106 -> 0
C111: Custo | D111: =D112+D113 -> -6.4512 | E111: =E112+E113 -> -20.4096 | F111: =F112+F113 -> -31.5648 | G111: =G112+G113 -> -1.0944 | H111: =H112+H113 -> 0 | I111: =I112+I113 -> 0 | J111: =J112+J113 -> 0 | K111: =K112+K113 -> 0 | ... M111: =M112+M113 -> 0
C112: Terreno | D112: =+D101+D102 -> -6.4512 | E112: =+E101+E102 -> -1.2096 | F112: =+F101+F102 -> -2.7648 | G112: =+G101+G102 -> -1.0944 | H112: =+H101+H102 -> 0 | I112: =+I101+I102 -> 0 | J112: =+J101+J102 -> 0 | K112: =+K101+K102 -> 0 | ... M112: =+M101+M102 -> 0
C113: Construção | D113: =+D134 -> 0 | E113: =+E134 -> -19.2 | F113: =+F134 -> -28.8 | G113: =+G134 -> 0 | H113: =+H134 -> 0 | I113: =+I134 -> 0 | J113: =+J134 -> 0 | K113: =+K134 -> 0 | ... M113: =+M134 -> 0
D115: 0.5 | E115: Obra/VGV
D117: 1o Ano | E117: 2o Ano
D118: 0.4 | E118: 0.6 | F118: Custo Obra/ Ano
C120: Custo de Construção
D122: Ano 1 | E122: Ano 2 | F122: Ano 3 | G122: Ano 4 | H122: Ano 5 | I122: Ano 6 | J122: Ano 7 | K122: Ano 8 | L122: Ano 9 | M122: Ano 10
C123: Ano 1 | E123: =-D15*$D$115*$D$118 -> -19.2 | F123: =-D15*$D$115*$E$118 -> -28.8
...

Sheet PROJETO 2
B2: COMPANHIA REAL ESTATE - PROJETO 2
B3: Em Milhoes de Reais
C5: Lançamentos (R$Mn)
D7: Ano 1 | E7: Ano 2 | F7: Ano 3 | G7: Ano 4 | H7: Ano 5 | I7: Ano 6 | J7: Ano 7 | K7: Ano 8 | L7: Ano 9 | M7: Ano 10
D8: 50
C10: Comissão Vendas | E10: 0.05
C12: Lançamentos (R$Mn)
D14: Ano 1 | E14: Ano 2 | F14: Ano 3 | G14: Ano 4 | H14: Ano 5 | I14: Ano 6 | J14: Ano 7 | K14: Ano 8 | L14: Ano 9 | M14: Ano 10
C15: Ano 1 | D15: =+D$8*(1-$E$10) -> 47.5
C16: Ano 2 | E16: =+E$8*(1-$E$10) -> 0
C17: Ano 3 | F17: =+F$8*(1-$E$10) -> 0
C18: Ano 4 | G18: =+G$8*(1-$E$10) -> 0
C19: Ano 5 | H19: =+H$8*(1-$E$10) -> 0
C20: Ano 6 | I20: =+I$8*(1-$E$10) -> 0
C21: Ano 7 | J21: =+J$8*(1-$E$10) -> 0
C22: Ano 8 | K22: =+K$8*(1-$E$10) -> 0
C23: Ano 9 | L23: =+L$8*(1-$E$10) -> 0
C24: Ano 10 | M24: =+M$8*(1-$E$10) -> 0
D25: =SUM(D15:D24) -> 47.5 | E25: =SUM(E15:E24) -> 0 | F25: =SUM(F15:F24) -> 0 | G25: =SUM(G15:G24) -> 0 | H25: =SUM(H15:H24) -> 0 | I25: =SUM(I15:I24) -> 0 | J25: =SUM(J15:J24) -> 0 | K25: =SUM(K15:K24) -> 0 | ... M25: =SUM(M15:M24) -> 0
C27: Vendas %
D29: Ano 1 | E29: Ano 2 | F29: Ano 3 | G29: Ano 4 | H29: Ano 5 | I29: Ano 6 | J29: Ano 7 | K29: Ano 8 | L29: Ano 9 | M29: Ano 10
C30: Ano 1 | D30: 0.5 | E30: 0.35 | F30: 0.1 | G30: 0.05
C31: Ano 2
C32: Ano 3
C33: Ano 4
C34: Ano 5
C35: Ano 6
C36: Ano 7
C37: Ano 8
C38: Ano 9
C39: Ano 10
C41: Captação Pre-Chaves | F41: 0.3
D43: Ano 1 | E43: Ano 2 | F43: Ano 3 | G43: Ano 4 | H43: Ano 5 | I43: Ano 6 | J43: Ano 7 | K43: Ano 8 | L43: Ano 9 | M43: Ano 10 | N43: TOTAL
C44: 1 | D44: =+$F$41/3 -> 0.1 | E44: =+F41/3 -> 0.1 | F44: =+F41/3 -> 0.1 | G44: =+(1-$F$41) -> 0.7 | N44: =SUM(D44:M44) -> 1
C45: 2 | E45: =+$F$41/2 -> 0.15 | F45: =+$F$41/2 -> 0.15 | G45: =+(1-$F$41) -> 0.7 | N45: =SUM(D45:M45) -> 1
C46: 3 | F46: =+$F$41 -> 0.3 | G46: =+(1-$F$41) -> 0.7 | N46: =SUM(D46:M46) -> 1
C47: 4 | G47: 1 | N47: =SUM(D47:M47) -> 1
C49: Receita Bruta (R$Mn)
D51: Ano 1 | E51: Ano 2 | F51: Ano 3 | G51: Ano 4 | H51: Ano 5 | I51: Ano 6 | J51: Ano 7 | K51: Ano 8 | L51: Ano 9 | M51: Ano 10 | Q51: TOTAL
C52: Ano 1 | D52: =+$D$15*$D$30*D$44 -> 2.375 | E52: =+$D$15*$D$30*E$44 -> 2.375 | F52: =+$D$15*$D$30*F$44 -> 2.375 | G52: =+$D$15*$D$30*G$44 -> 16.625 | Q52: =SUM(D52:P52) -> 23.75
C53: Ano 1 | E53: =+$D$15*$E$30*$E$45 -> 2.49375 | F53: =+$D$15*$E$30*$F$45 -> 2.49375 | G53: =+$D$15*$E$30*$G$45 -> 11.6375 | Q53: =SUM(D53:P53) -> 16.625
C54: Ano 1 | F54: =+$D$15*$F$30*$F$46 -> 1.425 | G54: =+$D$15*$F$30*$G$46 -> 3.325 | Q54: =SUM(D54:P54) -> 4.75
C55: Ano 1 | G55: =+$D$15*$G$30*$G$47 -> 2.375 | Q55: =SUM(D55:P55) -> 2.375
C56: Ano 2 | E56: =+$E$16*$E$31*D$44 -> 0 | F56: =+$E$16*$E$31*E$44 -> 0 | G56: =+$E$16*$E$31*F$44 -> 0 | H56: =+$E$16*$E$31*G$44 -> 0 | Q56: =SUM(D56:P56) -> 0
C57: Ano 2 | F57: =+$E$16*$F$31*E$45 -> 0 | G57: =+$E$16*$F$31*F$45 -> 0 | H57: =+$E$16*$F$31*G$45 -> 0 | Q57: =SUM(D57:P57) -> 0
C58: Ano 2 | G58: =+$E$16*$G$31*$F$46 -> 0 | H58: =+$E$16*$G$31*$G$46 -> 0 | Q58: =SUM(D58:P58) -> 0
C59: Ano 2 | H59: =+$E$16*$H$31*$G$47 -> 0 | Q59: =SUM(D59:P59) -> 0
C60: Ano 3 | F60: =+$F$17*$F$32*D$44 -> 0 | G60: =+$F$17*$F$32*E$44 -> 0 | H60: =+$F$17*$F$32*F$44 -> 0 | I60: =+$F$17*$F$32*G$44 -> 0 | Q60: =SUM(D60:P60) -> 0
C61: Ano 3 | G61: =+$F$17*$G$32*E$45 -> 0 | H61: =+$F$17*$G$32*F$45 -> 0 | I61: =+$F$17*$G$32*G$45 -> 0 | Q61: =SUM(D61:P61) -> 0
C62: Ano 3 | H62: =+$F$17*$H$32*F$46 -> 0 | I62: =+$F$17*$H$32*G$46 -> 0 | Q62: =SUM(D62:P62) -> 0
C63: Ano 3 | I63: =+$F$17*$I$32*$G$47 -> 0 | Q63: =SUM(D63:P63) -> 0
C64: Ano 4 | G64: =+$G$18*$G$33*D$44 -> 0 | H64: =+$G$18*$G$33*E$44 -> 0 | I64: =+$G$18*$G$33*F$44 -> 0 | J64: =+$G$18*$G$33*G$44 -> 0 | Q64: =SUM(D64:P64) -> 0
C65: Ano 4 | H65: =+$G$18*$H$33*E$45 -> 0 | I65: =+$G$18*$H$33*F$45 -> 0 | J65: =+$G$18*$H$33*G$45 -> 0 | Q65: =SUM(D65:P65) -> 0
C66: Ano 4 | I66: =+$G$18*$I$33*F$46 -> 0 | J66: =+$G$18*$I$33*G$46 -> 0 | Q66: =SUM(D66:P66) -> 0
C67: Ano 4 | J67: =+$G$18*$J$33*G$47 -> 0 | Q67: =SUM(D67:P67) -> 0
C68: Ano 5 | H68: =+$H$19*$H$34*D$44 -> 0 | I68: =+$H$19*$H$34*E$44 -> 0 | J68: =+$H$19*$H$34*F$44 -> 0 | K68: =+$H$19*$H$34*G$44 -> 0 | Q68: =SUM(D68:P68) -> 0
C69: Ano 5 | I69: =+$H$19*$I$34*E$45 -> 0 | J69: =+$H$19*$I$34*F$45 -> 0 | K69: =+$H$19*$I$34*G$45 -> 0 | Q69: =SUM(D69:P69) -> 0
C70: Ano 5 | J70: =+$H$19*$J$34*F$46 -> 0 | K70: =+$H$19*$J$34*G$46 -> 0 | Q70: =SUM(D70:P70) -> 0
C71: Ano 5 | K71: =+$H$19*$K$34*G$47 -> 0 | Q71: =SUM(D71:P71) -> 0
C72: Ano 6 | I72: =+$I$20*$I$35*D$44 -> 0 | J72: =+$I$20*$I$35*E$44 -> 0 | K72: =+$I$20*$I$35*F$44 -> 0 | L72: =+$I$20*$I$35*G$44 -> 0 | Q72: =SUM(D72:P72) -> 0
C73: Ano 6 | J73: =+$I$20*$J$35*E$45 -> 0 | K73: =+$I$20*$J$35*F$45 -> 0 | L73: =+$I$20*$J$35*G$45 -> 0 | Q73: =SUM(D73:P73) -> 0
C74: Ano 6 | K74: =+$I$20*$K$35*F$46 -> 0 | L74: =+$I$20*$K$35*G$46 -> 0 | Q74: =SUM(D74:P74) -> 0
C75: Ano 6 | L75: =+$I$20*$L$35*G$47 -> 0 | Q75: =SUM(D75:P75) -> 0
C76: Ano 7 | J76: =+$J$21*$J$36*D$44 -> 0 | K76: =+$J$21*$J$36*E$44 -> 0 | L76: =+$J$21*$J$36*F$44 -> 0 | M76: =+$J$21*$J$36*G$44 -> 0 | Q76: =SUM(D76:P76) -> 0
C77: Ano 7 | K77: =+$J$21*$K$36*E$45 -> 0 | L77: =+$J$21*$K$36*F$45 -> 0 | M77: =+$J$21*$K$36*G$45 -> 0 | Q77: =SUM(D77:P77) -> 0
C78: Ano 7 | L78: =+$J$21*$L$36*F$46 -> 0 | M78: =+$J$21*$L$36*G$46 -> 0 | Q78: =SUM(D78:P78) -> 0
C79: Ano 7 | M79: =+$J$21*$M$36*G$47 -> 0 | Q79: =SUM(D79:P79) -> 0
C80: Ano 8 | K80: =+$K$22*$K$37*D$44 -> 0 | L80: =+$K$22*$K$37*E$44 -> 0 | M80: =+$K$22*$K$37*F$44 -> 0 | N80: =+$K$22*$K$37*G$44 -> 0 | Q80: =SUM(D80:P80) -> 0
C81: Ano 8 | L81: =+$K$22*$L$37*E$45 -> 0 | M81: =+$K$22*$L$37*F$45 -> 0 | N81: =+$K$22*$L$37*G$45 -> 0 | Q81: =SUM(D81:P81) -> 0
C82: Ano 8 | M82: =+$K$22*$M$37*F$46 -> 0 | N82: =+$K$22*$M$37*G$46 -> 0 | Q82: =SUM(D82:P82) -> 0
C83: Ano 8 | N83: =+$K$22*$N$37*G$47 -> 0 | Q83: =SUM(D83:P83) -> 0
C84: Ano 9 | L84: =+$L$23*$L$38*D$44 -> 0 | M84: =+$L$23*$L$38*E$44 -> 0 | N84: =+$L$23*$L$38*F$44 -> 0 | O84: =+$L$23*$L$38*G$44 -> 0 | Q84: =SUM(D84:P84) -> 0
C85: Ano 9 | M85: =+$L$23*$M$38*E$45 -> 0 | N85: =+$L$23*$M$38*F$45 -> 0 | O85: =+$L$23*$M$38*G$45 -> 0 | Q85: =SUM(D85:P85) -> 0
C86: Ano 9 | N86: =+$L$23*$N$38*F$46 -> 0 | O86: =+$L$23*$N$38*G$46 -> 0 | Q86: =SUM(D86:P86) -> 0
C87: Ano 9 | O87: =+$L$23*$O$38*G$47 -> 0 | Q87: =SUM(D87:P87) -> 0
C88: Ano 10 | M88: =+$M$24*$M$39*D$44 -> 0 | N88: =+$M$24*$M$39*E$44 -> 0 | O88: =+$M$24*$M$39*F$44 -> 0 | P88: =+$M$24*$M$39*G$44 -> 0 | Q88: =SUM(D88:P88) -> 0
C89: Ano 10 | N89: =+$M$24*$N$39*E$45 -> 0 | O89: =+$M$24*$N$39*F$45 -> 0 | P89: =+$M$24*$N$39*G$45 -> 0 | Q89: =SUM(D89:P89) -> 0
C90: Ano 10 | O90: =+$M$24*$O$39*F$46 -> 0 | P90: =+$M$24*$O$39*G$46 -> 0 | Q90: =SUM(D90:P90) -> 0
C91: Ano 10 | P91: =+$M$24*$P$39*G$47 -> 0 | Q91: =SUM(D91:P91) -> 0
D92: =SUM(D52:D91) -> 2.375 | E92: =SUM(E52:E91) -> 4.86875 | F92: =SUM(F52:F91) -> 6.29375 | G92: =SUM(G52:G91) -> 33.9625 | H92: =SUM(H52:H91) -> 0 | I92: =SUM(I52:I91) -> 0 | J92: =SUM(J52:J91) -> 0 | K92: =SUM(K52:K91) -> 0 | ... M92: =SUM(M52:M91) -> 0
C94: Custo Terreno/ VGV | F94: 0.15
C96: Percentual Medio Permuta | F96: 0.35
C98: Parcela Cash | F98: 1 | G98: (mesmo ano)
D100: Ano 1 | E100: Ano 2 | F100: Ano 3 | G100: Ano 4 | H100: Ano 5 | I100: Ano 6 | J100: Ano 7 | K100: Ano 8 | L100: Ano 9 | M100: Ano 10
C101: Permuta | D101: =-$F$94*$F$96*D104 -> -0.1246875 | E101: =-$F$94*$F$96*E104 -> -0.25560938 | F101: =-$F$94*$F$96*F104 -> -0.33042187 | G101: =-$F$94*$F$96*G104 -> -1.7830312 | H101: =-$F$94*$F$96*H104 -> 0 | I101: =-$F$94*$F$96*I104 -> 0 | J101: =-$F$94*$F$96*J104 -> 0 | K101: =-$F$94*$F$96*K104 -> 0 | ... M101: =-$F$94*$F$96*M104 -> 0
C102: Cash | D102: =-$F$94*$F$96*D25 -> -2.49375 | E102: =-$F$94*$F$96*E25 -> 0 | F102: =-$F$94*$F$96*F25 -> 0 | G102: =-$F$94*$F$96*G25 -> 0 | H102: =-$F$94*$F$96*H25 -> 0 | I102: =-$F$94*$F$96*I25 -> 0 | J102: =-$F$94*$F$96*J25 -> 0 | K102: =-$F$94*$F$96*K25 -> 0 | ... M102: =-$F$94*$F$96*M25 -> 0
C104: Receita Bruta | D104: =+D92 -> 2.375 | E104: =+E92 -> 4.86875 | F104: =+F92 -> 6.29375 | G104: =+G92 -> 33.9625 | H104: =+H92 -> 0 | I104: =+I92 -> 0 | J104: =+J92 -> 0 | K104: =+K92 -> 0 | ... M104: =+M92 -> 0
C105: Cresc % | E105: =IFERROR(E104/D104-1,0) -> 1.05 | F105: =IFERROR(F104/E104-1,0) -> 0.29268293 | G105: =IFERROR(G104/F104-1,0) -> 4.3962264 | H105: =IFERROR(H104/G104-1,0) -> -1 | I105: =IFERROR(I104/H104-1,0) -> 0 | J105: =IFERROR(J104/I104-1,0) -> 0 | K105: =IFERROR(K104/J104-1,0) -> 0 | L105: =IFERROR(L104/K104-1,0) -> 0 | M105: =IFERROR(M104/L104-1,0) -> 0
C106: Impostos | D106: =-D107*D104 -> -0.095 | E106: =-E107*E104 -> -0.19475 | F106: =-F107*F104 -> -0.25175 | G106: =-G107*G104 -> -1.3585 | H106: =-H107*H104 -> 0 | I106: =-I107*I104 -> 0 | J106: =-J107*J104 -> 0 | K106: =-K107*K104 -> 0 | ... M106: =-M107*M104 -> 0
C107: Impostos % | D107: 0.04 | E107: =+D107 -> 0.04 | F107: =+E107 -> 0.04 | G107: =+F107 -> 0.04 | H107: =+G107 -> 0.04 | I107: =+H107 -> 0.04 | J107: =+I107 -> 0.04 | K107: =+J107 -> 0.04 | L107: =+K107 -> 0.04 | M107: =+L107 -> 0.04
C109: Receita Líquida | D109: =+D104+D106 -> 2.28 | E109: =+E104+E106 -> 4.674 | F109: =+F104+F106 -> 6.042 | G109: =+G104+G106 -> 32.604 | H109: =+H104+H106 -> 0 | I109: =+I104+I106 -> 0 | J109: =+J104+J106 -> 0 | K109: =+K104+K106 -> 0 | ... M109: =+M104+M106 -> 0
C111: Custo | D111: =D112+D113 -> -2.6184375 | E111: =E112+E113 -> -8.8056094 | F111: =F112+F113 -> -10.780422 | G111: =G112+G113 -> -1.7830312 | H111: =H112+H113 -> 0 | I111: =I112+I113 -> 0 | J111: =J112+J113 -> 0 | K111: =K112+K113 -> 0 | ... M111: =M112+M113 -> 0
C112: Terreno | D112: =+D101+D102 -> -2.6184375 | E112: =+E101+E102 -> -0.25560938 | F112: =+F101+F102 -> -0.33042187 | G112: =+G101+G102 -> -1.7830312 | H112: =+H101+H102 -> 0 | I112: =+I101+I102 -> 0 | J112: =+J101+J102 -> 0 | K112: =+K101+K102 -> 0 | ... M112: =+M101+M102 -> 0
C113: Construção | D113: =+D134 -> 0 | E113: =+E134 -> -8.55 | F113: =+F134 -> -10.45 | G113: =+G134 -> 0 | H113: =+H134 -> 0 | I113: =+I134 -> 0 | J113: =+J134 -> 0 | K113: =+K134 -> 0 | ... M113: =+M134 -> 0
D115: 0.4 | E115: Obra/VGV
D117: 1o Ano | E117: 2o Ano
D118: 0.45 | E118: 0.55 | F118: Custo Obra/ Ano
C120: Custo de Construção
D122: Ano 1 | E122: Ano 2 | F122: Ano 3 | G122: Ano 4 | H122: Ano 5 | I122: Ano 6 | J122: Ano 7 | K122: Ano 8 | L122: Ano 9 | M122: Ano 10
C123: Ano 1 | E123: =-D15*$D$115*$D$118 -> -8.55 | F123: =-D15*$D$115*$E$118 -> -10.45
...

Sheet PROJETO 3
B2: COMPANHIA REAL ESTATE - PROJETO 3
B3: Em Milhoes de Reais
C5: Lançamentos (R$Mn)
D7: Ano 1 | E7: Ano 2 | F7: Ano 3 | G7: Ano 4 | H7: Ano 5 | I7: Ano 6 | J7: Ano 7 | K7: Ano 8 | L7: Ano 9 | M7: Ano 10
E8: 150
C10: Comissão Vendas | E10: 0.045
C12: Lançamentos (R$Mn)
D14: Ano 1 | E14: Ano 2 | F14: Ano 3 | G14: Ano 4 | H14: Ano 5 | I14: Ano 6 | J14: Ano 7 | K14: Ano 8 | L14: Ano 9 | M14: Ano 10
C15: Ano 1 | D15: =+D$8*(1-$E$10) -> 0
C16: Ano 2 | E16: =+E$8*(1-$E$10) -> 143.25
C17: Ano 3 | F17: =+F$8*(1-$E$10) -> 0
C18: Ano 4 | G18: =+G$8*(1-$E$10) -> 0
C19: Ano 5 | H19: =+H$8*(1-$E$10) -> 0
C20: Ano 6 | I20: =+I$8*(1-$E$10) -> 0
C21: Ano 7 | J21: =+J$8*(1-$E$10) -> 0
C22: Ano 8 | K22: =+K$8*(1-$E$10) -> 0
C23: Ano 9 | L23: =+L$8*(1-$E$10) -> 0
C24: Ano 10 | M24: =+M$8*(1-$E$10) -> 0
D25: =SUM(D15:D24) -> 0 | E25: =SUM(E15:E24) -> 143.25 | F25: =SUM(F15:F24) -> 0 | G25: =SUM(G15:G24) -> 0 | H25: =SUM(H15:H24) -> 0 | I25: =SUM(I15:I24) -> 0 | J25: =SUM(J15:J24) -> 0 | K25: =SUM(K15:K24) -> 0 | ... M25: =SUM(M15:M24) -> 0
C27: Vendas %
D29: Ano 1 | E29: Ano 2 | F29: Ano 3 | G29: Ano 4 | H29: Ano 5 | I29: Ano 6 | J29: Ano 7 | K29: Ano 8 | L29: Ano 9 | M29: Ano 10
C30: Ano 1
C31: Ano 2 | E31: 0.6 | F31: 0.4
C32: Ano 3
C33: Ano 4
C34: Ano 5
C35: Ano 6
C36: Ano 7
C37: Ano 8
C38: Ano 9
C39: Ano 10
C41: Captação Pre-Chaves | F41: 0.4
D43: Ano 1 | E43: Ano 2 | F43: Ano 3 | G43: Ano 4 | H43: Ano 5 | I43: Ano 6 | J43: Ano 7 | K43: Ano 8 | L43: Ano 9 | M43: Ano 10 | N43: TOTAL
C44: 1 | D44: =+$F$41/3 -> 0.13333333 | E44: =+F41/3 -> 0.13333333 | F44: =+F41/3 -> 0.13333333 | G44: =+(1-$F$41) -> 0.6 | N44: =SUM(D44:M44) -> 1
C45: 2 | E45: =+$F$41/2 -> 0.2 | F45: =+$F$41/2 -> 0.2 | G45: =+(1-$F$41) -> 0.6 | N45: =SUM(D45:M45) -> 1
C46: 3 | F46: =+$F$41 -> 0.4 | G46: =+(1-$F$41) -> 0.6 | N46: =SUM(D46:M46) -> 1
C47: 4 | G47: 1 | N47: =SUM(D47:M47) -> 1
C49: Receita Bruta (R$Mn)
D51: Ano 1 | E51: Ano 2 | F51: Ano 3 | G51: Ano 4 | H51: Ano 5 | I51: Ano 6 | J51: Ano 7 | K51: Ano 8 | L51: Ano 9 | M51: Ano 10 | Q51: TOTAL
C52: Ano 1 | D52: =+$D$15*$D$30*D$44 -> 0 | E52: =+$D$15*$D$30*E$44 -> 0 | F52: =+$D$15*$D$30*F$44 -> 0 | G52: =+$D$15*$D$30*G$44 -> 0 | Q52: =SUM(D52:P52) -> 0
C53: Ano 1 | E53: =+$D$15*$E$30*$E$45 -> 0 | F53: =+$D$15*$E$30*$F$45 -> 0 | G53: =+$D$15*$E$30*$G$45 -> 0 | Q53: =SUM(D53:P53) -> 0
C54: Ano 1 | F54: =+$D$15*$F$30*$F$46 -> 0 | G54: =+$D$15*$F$30*$G$46 -> 0 | Q54: =SUM(D54:P54) -> 0
C55: Ano 1 | G55: =+$D$15*$G$30*$G$47 -> 0 | Q55: =SUM(D55:P55) -> 0
C56: Ano 2 | E56: =+$E$16*$E$31*D$44 -> 11.46 | F56: =+$E$16*$E$31*E$44 -> 11.46 | G56: =+$E$16*$E$31*F$44 -> 11.46 | H56: =+$E$16*$E$31*G$44 -> 51.57 | Q56: =SUM(D56:P56) -> 85.95
C57: Ano 2 | F57: =+$E$16*$F$31*E$45 -> 11.46 | G57: =+$E$16*$F$31*F$45 -> 11.46 | H57: =+$E$16*$F$31*G$45 -> 34.38 | Q57: =SUM(D57:P57) -> 57.3
C58: Ano 2 | G58: =+$E$16*$G$31*$F$46 -> 0 | H58: =+$E$16*$G$31*$G$46 -> 0 | Q58: =SUM(D58:P58) -> 0
C59: Ano 2 | H59: =+$E$16*$H$31*$G$47 -> 0 | Q59: =SUM(D59:P59) -> 0
C60: Ano 3 | F60: =+$F$17*$F$32*D$44 -> 0 | G60: =+$F$17*$F$32*E$44 -> 0 | H60: =+$F$17*$F$32*F$44 -> 0 | I60: =+$F$17*$F$32*G$44 -> 0 | Q60: =SUM(D60:P60) -> 0
C61: Ano 3 | G61: =+$F$17*$G$32*E$45 -> 0 | H61: =+$F$17*$G$32*F$45 -> 0 | I61: =+$F$17*$G$32*G$45 -> 0 | Q61: =SUM(D61:P61) -> 0
C62: Ano 3 | H62: =+$F$17*$H$32*F$46 -> 0 | I62: =+$F$17*$H$32*G$46 -> 0 | Q62: =SUM(D62:P62) -> 0
C63: Ano 3 | I63: =+$F$17*$I$32*$G$47 -> 0 | Q63: =SUM(D63:P63) -> 0
C64: Ano 4 | G64: =+$G$18*$G$33*D$44 -> 0 | H64: =+$G$18*$G$33*E$44 -> 0 | I64: =+$G$18*$G$33*F$44 -> 0 | J64: =+$G$18*$G$33*G$44 -> 0 | Q64: =SUM(D64:P64) -> 0
C65: Ano 4 | H65: =+$G$18*$H$33*E$45 -> 0 | I65: =+$G$18*$H$33*F$45 -> 0 | J65: =+$G$18*$H$33*G$45 -> 0 | Q65: =SUM(D65:P65) -> 0
C66: Ano 4 | I66: =+$G$18*$I$33*F$46 -> 0 | J66: =+$G$18*$I$33*G$46 -> 0 | Q66: =SUM(D66:P66) -> 0
C67: Ano 4 | J67: =+$G$18*$J$33*G$47 -> 0 | Q67: =SUM(D67:P67) -> 0
C68: Ano 5 | H68: =+$H$19*$H$34*D$44 -> 0 | I68: =+$H$19*$H$34*E$44 -> 0 | J68: =+$H$19*$H$34*F$44 -> 0 | K68: =+$H$19*$H$34*G$44 -> 0 | Q68: =SUM(D68:P68) -> 0
C69: Ano 5 | I69: =+$H$19*$I$34*E$45 -> 0 | J69: =+$H$19*$I$34*F$45 -> 0 | K69: =+$H$19*$I$34*G$45 -> 0 | Q69: =SUM(D69:P69) -> 0
C70: Ano 5 | J70: =+$H$19*$J$34*F$46 -> 0 | K70: =+$H$19*$J$34*G$46 -> 0 | Q70: =SUM(D70:P70) -> 0
C71: Ano 5 | K71: =+$H$19*$K$34*G$47 -> 0 | Q71: =SUM(D71:P71) -> 0
C72: Ano 6 | I72: =+$I$20*$I$35*D$44 -> 0 | J72: =+$I$20*$I$35*E$44 -> 0 | K72: =+$I$20*$I$35*F$44 -> 0 | L72: =+$I$20*$I$35*G$44 -> 0 | Q72: =SUM(D72:P72) -> 0
C73: Ano 6 | J73: =+$I$20*$J$35*E$45 -> 0 | K73: =+$I$20*$J$35*F$45 -> 0 | L73: =+$I$20*$J$35*G$45 -> 0 | Q73: =SUM(D73:P73) -> 0
C74: Ano 6 | K74: =+$I$20*$K$35*F$46 -> 0 | L74: =+$I$20*$K$35*G$46 -> 0 | Q74: =SUM(D74:P74) -> 0
C75: Ano 6 | L75: =+$I$20*$L$35*G$47 -> 0 | Q75: =SUM(D75:P75) -> 0
C76: Ano 7 | J76: =+$J$21*$J$36*D$44 -> 0 | K76: =+$J$21*$J$36*E$44 -> 0 | L76: =+$J$21*$J$36*F$44 -> 0 | M76: =+$J$21*$J$36*G$44 -> 0 | Q76: =SUM(D76:P76) -> 0
C77: Ano 7 | K77: =+$J$21*$K$36*E$45 -> 0 | L77: =+$J$21*$K$36*F$45 -> 0 | M77: =+$J$21*$K$36*G$45 -> 0 | Q77: =SUM(D77:P77) -> 0
C78: Ano 7 | L78: =+$J$21*$L$36*F$46 -> 0 | M78: =+$J$21*$L$36*G$46 -> 0 | Q78: =SUM(D78:P78) -> 0
C79: Ano 7 | M79: =+$J$21*$M$36*G$47 -> 0 | Q79: =SUM(D79:P79) -> 0
C80: Ano 8 | K80: =+$K$22*$K$37*D$44 -> 0 | L80: =+$K$22*$K$37*E$44 -> 0 | M80: =+$K$22*$K$37*F$44 -> 0 | N80: =+$K$22*$K$37*G$44 -> 0 | Q80: =SUM(D80:P80) -> 0
C81: Ano 8 | L81: =+$K$22*$L$37*E$45 -> 0 | M81: =+$K$22*$L$37*F$45 -> 0 | N81: =+$K$22*$L$37*G$45 -> 0 | Q81: =SUM(D81:P81) -> 0
C82: Ano 8 | M82: =+$K$22*$M$37*F$46 -> 0 | N82: =+$K$22*$M$37*G$46 -> 0 | Q82: =SUM(D82:P82) -> 0
C83: Ano 8 | N83: =+$K$22*$N$37*G$47 -> 0 | Q83: =SUM(D83:P83) -> 0
C84: Ano 9 | L84: =+$L$23*$L$38*D$44 -> 0 | M84: =+$L$23*$L$38*E$44 -> 0 | N84: =+$L$23*$L$38*F$44 -> 0 | O84: =+$L$23*$L$38*G$44 -> 0 | Q84: =SUM(D84:P84) -> 0
C85: Ano 9 | M85: =+$L$23*$M$38*E$45 -> 0 | N85: =+$L$23*$M$38*F$45 -> 0 | O85: =+$L$23*$M$38*G$45 -> 0 | Q85: =SUM(D85:P85) -> 0
C86: Ano 9 | N86: =+$L$23*$N$38*F$46 -> 0 | O86: =+$L$23*$N$38*G$46 -> 0 | Q86: =SUM(D86:P86) -> 0
C87: Ano 9 | O87: =+$L$23*$O$38*G$47 -> 0 | Q87: =SUM(D87:P87) -> 0
C88: Ano 10 | M88: =+$M$24*$M$39*D$44 -> 0 | N88: =+$M$24*$M$39*E$44 -> 0 | O88: =+$M$24*$M$39*F$44 -> 0 | P88: =+$M$24*$M$39*G$44 -> 0 | Q88: =SUM(D88:P88) -> 0
C89: Ano 10 | N89: =+$M$24*$N$39*E$45 -> 0 | O89: =+$M$24*$N$39*F$45 -> 0 | P89: =+$M$24*$N$39*G$45 -> 0 | Q89: =SUM(D89:P89) -> 0
C90: Ano 10 | O90: =+$M$24*$O$39*F$46 -> 0 | P90: =+$M$24*$O$39*G$46 -> 0 | Q90: =SUM(D90:P90) -> 0
C91: Ano 10 | P91: =+$M$24*$P$39*G$47 -> 0 | Q91: =SUM(D91:P91) -> 0
D92: =SUM(D52:D91) -> 0 | E92: =SUM(E52:E91) -> 11.46 | F92: =SUM(F52:F91) -> 22.92 | G92: =SUM(G52:G91) -> 22.92 | H92: =SUM(H52:H91) -> 85.95 | I92: =SUM(I52:I91) -> 0 | J92: =SUM(J52:J91) -> 0 | K92: =SUM(K52:K91) -> 0 | ... M92: =SUM(M52:M91) -> 0
C94: Custo Terreno/ VGV | F94: 0.3
C96: Percentual Medio Permuta | F96: 0.2
C98: Parcela Cash | F98: 1 | G98: (mesmo ano)
D100: Ano 1 | E100: Ano 2 | F100: Ano 3 | G100: Ano 4 | H100: Ano 5 | I100: Ano 6 | J100: Ano 7 | K100: Ano 8 | L100: Ano 9 | M100: Ano 10
C101: Permuta | D101: =-$F$94*$F$96*D104 -> 0 | E101: =-$F$94*$F$96*E104 -> -0.6876 | F101: =-$F$94*$F$96*F104 -> -1.3752 | G101: =-$F$94*$F$96*G104 -> -1.3752 | H101: =-$F$94*$F$96*H104 -> -5.157 | I101: =-$F$94*$F$96*I104 -> 0 | J101: =-$F$94*$F$96*J104 -> 0 | K101: =-$F$94*$F$96*K104 -> 0 | ... M101: =-$F$94*$F$96*M104 -> 0
C102: Cash | D102: =-$F$94*$F$96*D25 -> 0 | E102: =-$F$94*$F$96*E25 -> -8.595 | F102: =-$F$94*$F$96*F25 -> 0 | G102: =-$F$94*$F$96*G25 -> 0 | H102: =-$F$94*$F$96*H25 -> 0 | I102: =-$F$94*$F$96*I25 -> 0 | J102: =-$F$94*$F$96*J25 -> 0 | K102: =-$F$94*$F$96*K25 -> 0 | ... M102: =-$F$94*$F$96*M25 -> 0
C104: Receita Bruta | D104: =+D92 -> 0 | E104: =+E92 -> 11.46 | F104: =+F92 -> 22.92 | G104: =+G92 -> 22.92 | H104: =+H92 -> 85.95 | I104: =+I92 -> 0 | J104: =+J92 -> 0 | K104: =+K92 -> 0 | ... M104: =+M92 -> 0
C105: Cresc % | E105: =IFERROR(E104/D104-1,0) -> 0 | F105: =IFERROR(F104/E104-1,0) -> 1 | G105: =IFERROR(G104/F104-1,0) -> 0 | H105: =IFERROR(H104/G104-1,0) -> 2.75 | I105: =IFERROR(I104/H104-1,0) -> -1 | J105: =IFERROR(J104/I104-1,0) -> 0 | K105: =IFERROR(K104/J104-1,0) -> 0 | L105: =IFERROR(L104/K104-1,0) -> 0 | M105: =IFERROR(M104/L104-1,0) -> 0
C106: Impostos | D106: =-D107*D104 -> 0 | E106: =-E107*E104 -> -0.4584 | F106: =-F107*F104 -> -0.9168 | G106: =-G107*G104 -> -0.9168 | H106: =-H107*H104 -> -3.438 | I106: =-I107*I104 -> 0 | J106: =-J107*J104 -> 0 | K106: =-K107*K104 -> 0 | ... M106: =-M107*M104 -> 0
C107: Impostos % | D107: 0.04 | E107: =+D107 -> 0.04 | F107: =+E107 -> 0.04 | G107: =+F107 -> 0.04 | H107: =+G107 -> 0.04 | I107: =+H107 -> 0.04 | J107: =+I107 -> 0.04 | K107: =+J107 -> 0.04 | L107: =+K107 -> 0.04 | M107: =+L107 -> 0.04
C109: Receita Líquida | D109: =+D104+D106 -> 0 | E109: =+E104+E106 -> 11.0016 | F109: =+F104+F106 -> 22.0032 | G109: =+G104+G106 -> 22.0032 | H109: =+H104+H106 -> 82.512 | I109: =+I104+I106 -> 0 | J109: =+J104+J106 -> 0 | K109: =+K104+K106 -> 0 | ... M109: =+M104+M106 -> 0
C111: Custo | D111: =D112+D113 -> 0 | E111: =E112+E113 -> -9.2826 | F111: =F112+F113 -> -22.8627 | G111: =G112+G113 -> -51.5127 | H111: =H112+H113 -> -5.157 | I111: =I112+I113 -> 0 | J111: =J112+J113 -> 0 | K111: =K112+K113 -> 0 | ... M111: =M112+M113 -> 0
C112: Terreno | D112: =+D101+D102 -> 0 | E112: =+E101+E102 -> -9.2826 | F112: =+F101+F102 -> -1.3752 | G112: =+G101+G102 -> -1.3752 | H112: =+H101+H102 -> -5.157 | I112: =+I101+I102 -> 0 | J112: =+J101+J102 -> 0 | K112: =+K101+K102 -> 0 | ... M112: =+M101+M102 -> 0
C113: Construção | D113: =+D134 -> 0 | E113: =+E134 -> 0 | F113: =+F134 -> -21.4875 | G113: =+G134 -> -50.1375 | H113: =+H134 -> 0 | I113: =+I134 -> 0 | J113: =+J134 -> 0 | K113: =+K134 -> 0 | ... M113: =+M134 -> 0
D115: 0.5 | E115: Obra/VGV
D117: 1o Ano | E117: 2o Ano
D118: 0.3 | E118: 0.7 | F118: Custo Obra/ Ano
C120: Custo de Construção
D122: Ano 1 | E122: Ano 2 | F122: Ano 3 | G122: Ano 4 | H122: Ano 5 | I122: Ano 6 | J122: Ano 7 | K122: Ano 8 | L122: Ano 9 | M122: Ano 10
C123: Ano 1 | E123: =-D15*$D$115*$D$118 -> 0 | F123: =-D15*$D$115*$E$118 -> 0
...

Sheet PROJETO 4
B2: COMPANHIA REAL ESTATE - PROJETO 4
B3: Em Milhoes de Reais
C5: Lançamentos (R$Mn)
D7: Ano 1 | E7: Ano 2 | F7: Ano 3 | G7: Ano 4 | H7: Ano 5 | I7: Ano 6 | J7: Ano 7 | K7: Ano 8 | L7: Ano 9 | M7: Ano 10
F8: 200
C10: Comissão Vendas | E10: 0.05
C12: Lançamentos (R$Mn)
D14: Ano 1 | E14: Ano 2 | F14: Ano 3 | G14: Ano 4 | H14: Ano 5 | I14: Ano 6 | J14: Ano 7 | K14: Ano 8 | L14: Ano 9 | M14: Ano 10
C15: Ano 1 | D15: =+D$8*(1-$E$10) -> 0
C16: Ano 2 | E16: =+E$8*(1-$E$10) -> 0
C17: Ano 3 | F17: =+F$8*(1-$E$10) -> 190
C18: Ano 4 | G18: =+G$8*(1-$E$10) -> 0
C19: Ano 5 | H19: =+H$8*(1-$E$10) -> 0
C20: Ano 6 | I20: =+I$8*(1-$E$10) -> 0
C21: Ano 7 | J21: =+J$8*(1-$E$10) -> 0
C22: Ano 8 | K22: =+K$8*(1-$E$10) -> 0
C23: Ano 9 | L23: =+L$8*(1-$E$10) -> 0
C24: Ano 10 | M24: =+M$8*(1-$E$10) -> 0
D25: =SUM(D15:D24) -> 0 | E25: =SUM(E15:E24) -> 0 | F25: =SUM(F15:F24) -> 190 | G25: =SUM(G15:G24) -> 0 | H25: =SUM(H15:H24) -> 0 | I25: =SUM(I15:I24) -> 0 | J25: =SUM(J15:J24) -> 0 | K25: =SUM(K15:K24) -> 0 | ... M25: =SUM(M15:M24) -> 0
C27: Vendas %
D29: Ano 1 | E29: Ano 2 | F29: Ano 3 | G29: Ano 4 | H29: Ano 5 | I29: Ano 6 | J29: Ano 7 | K29: Ano 8 | L29: Ano 9 | M29: Ano 10
C30: Ano 1
C31: Ano 2
C32: Ano 3 | F32: 0.4 | G32: 0.2 | H32: 0.2 | I32: 0.2
C33: Ano 4
C34: Ano 5
C35: Ano 6
C36: Ano 7
C37: Ano 8
C38: Ano 9
C39: Ano 10
C41: Captação Pre-Chaves | F41: 0.5
D43: Ano 1 | E43: Ano 2 | F43: Ano 3 | G43: Ano 4 | H43: Ano 5 | I43: Ano 6 | J43: Ano 7 | K43: Ano 8 | L43: Ano 9 | M43: Ano 10 | N43: TOTAL
C44: 1 | D44: =+$F$41/3 -> 0.16666667 | E44: =+F41/3 -> 0.16666667 | F44: =+F41/3 -> 0.16666667 | G44: =+(1-$F$41) -> 0.5 | N44: =SUM(D44:M44) -> 1
C45: 2 | E45: =+$F$41/2 -> 0.25 | F45: =+$F$41/2 -> 0.25 | G45: =+(1-$F$41) -> 0.5 | N45: =SUM(D45:M45) -> 1
C46: 3 | F46: =+$F$41 -> 0.5 | G46: =+(1-$F$41) -> 0.5 | N46: =SUM(D46:M46) -> 1
C47: 4 | G47: 1 | N47: =SUM(D47:M47) -> 1
C49: Receita Bruta (R$Mn)
D51: Ano 1 | E51: Ano 2 | F51: Ano 3 | G51: Ano 4 | H51: Ano 5 | I51: Ano 6 | J51: Ano 7 | K51: Ano 8 | L51: Ano 9 | M51: Ano 10 | Q51: TOTAL
C52: Ano 1 | D52: =+$D$15*$D$30*D$44 -> 0 | E52: =+$D$15*$D$30*E$44 -> 0 | F52: =+$D$15*$D$30*F$44 -> 0 | G52: =+$D$15*$D$30*G$44 -> 0 | Q52: =SUM(D52:P52) -> 0
C53: Ano 1 | E53: =+$D$15*$E$30*$E$45 -> 0 | F53: =+$D$15*$E$30*$F$45 -> 0 | G53: =+$D$15*$E$30*$G$45 -> 0 | Q53: =SUM(D53:P53) -> 0
C54: Ano 1 | F54: =+$D$15*$F$30*$F$46 -> 0 | G54: =+$D$15*$F$30*$G$46 -> 0 | Q54: =SUM(D54:P54) -> 0
C55: Ano 1 | G55: =+$D$15*$G$30*$G$47 -> 0 | Q55: =SUM(D55:P55) -> 0
C56: Ano 2 | E56: =+$E$16*$E$31*D$44 -> 0 | F56: =+$E$16*$E$31*E$44 -> 0 | G56: =+$E$16*$E$31*F$44 -> 0 | H56: =+$E$16*$E$31*G$44 -> 0 | Q56: =SUM(D56:P56) -> 0
C57: Ano 2 | F57: =+$E$16*$F$31*E$45 -> 0 | G57: =+$E$16*$F$31*F$45 -> 0 | H57: =+$E$16*$F$31*G$45 -> 0 | Q57: =SUM(D57:P57) -> 0
C58: Ano 2 | G58: =+$E$16*$G$31*$F$46 -> 0 | H58: =+$E$16*$G$31*$G$46 -> 0 | Q58: =SUM(D58:P58) -> 0
C59: Ano 2 | H59: =+$E$16*$H$31*$G$47 -> 0 | Q59: =SUM(D59:P59) -> 0
C60: Ano 3 | F60: =+$F$17*$F$32*D$44 -> 12.666667 | G60: =+$F$17*$F$32*E$44 -> 12.666667 | H60: =+$F$17*$F$32*F$44 -> 12.666667 | I60: =+$F$17*$F$32*G$44 -> 38 | Q60: =SUM(D60:P60) -> 76
C61: Ano 3 | G61: =+$F$17*$G$32*E$45 -> 9.5 | H61: =+$F$17*$G$32*F$45 -> 9.5 | I61: =+$F$17*$G$32*G$45 -> 19 | Q61: =SUM(D61:P61) -> 38
C62: Ano 3 | H62: =+$F$17*$H$32*F$46 -> 19 | I62: =+$F$17*$H$32*G$46 -> 19 | Q62: =SUM(D62:P62) -> 38
C63: Ano 3 | I63: =+$F$17*$I$32*$G$47 -> 38 | Q63: =SUM(D63:P63) -> 38
C64: Ano 4 | G64: =+$G$18*$G$33*D$44 -> 0 | H64: =+$G$18*$G$33*E$44 -> 0 | I64: =+$G$18*$G$33*F$44 -> 0 | J64: =+$G$18*$G$33*G$44 -> 0 | Q64: =SUM(D64:P64) -> 0
C65: Ano 4 | H65: =+$G$18*$H$33*E$45 -> 0 | I65: =+$G$18*$H$33*F$45 -> 0 | J65: =+$G$18*$H$33*G$45 -> 0 | Q65: =SUM(D65:P65) -> 0
C66: Ano 4 | I66: =+$G$18*$I$33*F$46 -> 0 | J66: =+$G$18*$I$33*G$46 -> 0 | Q66: =SUM(D66:P66) -> 0
C67: Ano 4 | J67: =+$G$18*$J$33*G$47 -> 0 | Q67: =SUM(D67:P67) -> 0
C68: Ano 5 | H68: =+$H$19*$H$34*D$44 -> 0 | I68: =+$H$19*$H$34*E$44 -> 0 | J68: =+$H$19*$H$34*F$44 -> 0 | K68: =+$H$19*$H$34*G$44 -> 0 | Q68: =SUM(D68:P68) -> 0
C69: Ano 5 | I69: =+$H$19*$I$34*E$45 -> 0 | J69: =+$H$19*$I$34*F$45 -> 0 | K69: =+$H$19*$I$34*G$45 -> 0 | Q69: =SUM(D69:P69) -> 0
C70: Ano 5 | J70: =+$H$19*$J$34*F$46 -> 0 | K70: =+$H$19*$J$34*G$46 -> 0 | Q70: =SUM(D70:P70) -> 0
C71: Ano 5 | K71: =+$H$19*$K$34*G$47 -> 0 | Q71: =SUM(D71:P71) -> 0
C72: Ano 6 | I72: =+$I$20*$I$35*D$44 -> 0 | J72: =+$I$20*$I$35*E$44 -> 0 | K72: =+$I$20*$I$35*F$44 -> 0 | L72: =+$I$20*$I$35*G$44 -> 0 | Q72: =SUM(D72:P72) -> 0
C73: Ano 6 | J73: =+$I$20*$J$35*E$45 -> 0 | K73: =+$I$20*$J$35*F$45 -> 0 | L73: =+$I$20*$J$35*G$45 -> 0 | Q73: =SUM(D73:P73) -> 0
C74: Ano 6 | K74: =+$I$20*$K$35*F$46 -> 0 | L74: =+$I$20*$K$35*G$46 -> 0 | Q74: =SUM(D74:P74) -> 0
C75: Ano 6 | L75: =+$I$20*$L$35*G$47 -> 0 | Q75: =SUM(D75:P75) -> 0
C76: Ano 7 | J76: =+$J$21*$J$36*D$44 -> 0 | K76: =+$J$21*$J$36*E$44 -> 0 | L76: =+$J$21*$J$36*F$44 -> 0 | M76: =+$J$21*$J$36*G$44 -> 0 | Q76: =SUM(D76:P76) -> 0
C77: Ano 7 | K77: =+$J$21*$K$36*E$45 -> 0 | L77: =+$J$21*$K$36*F$45 -> 0 | M77: =+$J$21*$K$36*G$45 -> 0 | Q77: =SUM(D77:P77) -> 0
C78: Ano 7 | L78: =+$J$21*$L$36*F$46 -> 0 | M78: =+$J$21*$L$36*G$46 -> 0 | Q78: =SUM(D78:P78) -> 0
C79: Ano 7 | M79: =+$J$21*$M$36*G$47 -> 0 | Q79: =SUM(D79:P79) -> 0
C80: Ano 8 | K80: =+$K$22*$K$37*D$44 -> 0 | L80: =+$K$22*$K$37*E$44 -> 0 | M80: =+$K$22*$K$37*F$44 -> 0 | N80: =+$K$22*$K$37*G$44 -> 0 | Q80: =SUM(D80:P80) -> 0
C81: Ano 8 | L81: =+$K$22*$L$37*E$45 -> 0 | M81: =+$K$22*$L$37*F$45 -> 0 | N81: =+$K$22*$L$37*G$45 -> 0 | Q81: =SUM(D81:P81) -> 0
C82: Ano 8 | M82: =+$K$22*$M$37*F$46 -> 0 | N82: =+$K$22*$M$37*G$46 -> 0 | Q82: =SUM(D82:P82) -> 0
C83: Ano 8 | N83: =+$K$22*$N$37*G$47 -> 0 | Q83: =SUM(D83:P83) -> 0
C84: Ano 9 | L84: =+$L$23*$L$38*D$44 -> 0 | M84: =+$L$23*$L$38*E$44 -> 0 | N84: =+$L$23*$L$38*F$44 -> 0 | O84: =+$L$23*$L$38*G$44 -> 0 | Q84: =SUM(D84:P84) -> 0
C85: Ano 9 | M85: =+$L$23*$M$38*E$45 -> 0 | N85: =+$L$23*$M$38*F$45 -> 0 | O85: =+$L$23*$M$38*G$45 -> 0 | Q85: =SUM(D85:P85) -> 0
C86: Ano 9 | N86: =+$L$23*$N$38*F$46 -> 0 | O86: =+$L$23*$N$38*G$46 -> 0 | Q86: =SUM(D86:P86) -> 0
C87: Ano 9 | O87: =+$L$23*$O$38*G$47 -> 0 | Q87: =SUM(D87:P87) -> 0
C88: Ano 10 | M88: =+$M$24*$M$39*D$44 -> 0 | N88: =+$M$24*$M$39*E$44 -> 0 | O88: =+$M$24*$M$39*F$44 -> 0 | P88: =+$M$24*$M$39*G$44 -> 0 | Q88: =SUM(D88:P88) -> 0
C89: Ano 10 | N89: =+$M$24*$N$39*E$45 -> 0 | O89: =+$M$24*$N$39*F$45 -> 0 | P89: =+$M$24*$N$39*G$45 -> 0 | Q89: =SUM(D89:P89) -> 0
C90: Ano 10 | O90: =+$M$24*$O$39*F$46 -> 0 | P90: =+$M$24*$O$39*G$46 -> 0 | Q90: =SUM(D90:P90) -> 0
C91: Ano 10 | P91: =+$M$24*$P$39*G$47 -> 0 | Q91: =SUM(D91:P91) -> 0
D92: =SUM(D52:D91) -> 0 | E92: =SUM(E52:E91) -> 0 | F92: =SUM(F52:F91) -> 12.666667 | G92: =SUM(G52:G91) -> 22.166667 | H92: =SUM(H52:H91) -> 41.166667 | I92: =SUM(I52:I91) -> 114 | J92: =SUM(J52:J91) -> 0 | K92: =SUM(K52:K91) -> 0 | ... M92: =SUM(M52:M91) -> 0
C94: Custo Terreno/ VGV | F94: 0.2
C96: Percentual Medio Permuta | F96: 0.2
C98: Parcela Cash | F98: 1 | G98: (mesmo ano)
D100: Ano 1 | E100: Ano 2 | F100: Ano 3 | G100: Ano 4 | H100: Ano 5 | I100: Ano 6 | J100: Ano 7 | K100: Ano 8 | L100: Ano 9 | M100: Ano 10
C101: Permuta | D101: =-$F$94*$F$96*D104 -> 0 | E101: =-$F$94*$F$96*E104 -> 0 | F101: =-$F$94*$F$96*F104 -> -0.50666667 | G101: =-$F$94*$F$96*G104 -> -0.88666667 | H101: =-$F$94*$F$96*H104 -> -1.6466667 | I101: =-$F$94*$F$96*I104 -> -4.56 | J101: =-$F$94*$F$96*J104 -> 0 | K101: =-$F$94*$F$96*K104 -> 0 | ... M101: =-$F$94*$F$96*M104 -> 0
C102: Cash | D102: =-$F$94*$F$96*D25 -> 0 | E102: =-$F$94*$F$96*E25 -> 0 | F102: =-$F$94*$F$96*F25 -> -7.6 | G102: =-$F$94*$F$96*G25 -> 0 | H102: =-$F$94*$F$96*H25 -> 0 | I102: =-$F$94*$F$96*I25 -> 0 | J102: =-$F$94*$F$96*J25 -> 0 | K102: =-$F$94*$F$96*K25 -> 0 | ... M102: =-$F$94*$F$96*M25 -> 0
C104: Receita Bruta | D104: =+D92 -> 0 | E104: =+E92 -> 0 | F104: =+F92 -> 12.666667 | G104: =+G92 -> 22.166667 | H104: =+H92 -> 41.166667 | I104: =+I92 -> 114 | J104: =+J92 -> 0 | K104: =+K92 -> 0 | ... M104: =+M92 -> 0
C105: Cresc % | E105: =IFERROR(E104/D104-1,0) -> 0 | F105: =IFERROR(F104/E104-1,0) -> 0 | G105: =IFERROR(G104/F104-1,0) -> 0.75 | H105: =IFERROR(H104/G104-1,0) -> 0.85714286 | I105: =IFERROR(I104/H104-1,0) -> 1.7692308 | J105: =IFERROR(J104/I104-1,0) -> -1 | K105: =IFERROR(K104/J104-1,0) -> 0 | L105: =IFERROR(L104/K104-1,0) -> 0 | M105: =IFERROR(M104/L104-1,0) -> 0
C106: Impostos | D106: =-D107*D104 -> 0 | E106: =-E107*E104 -> 0 | F106: =-F107*F104 -> -0.50666667 | G106: =-G107*G104 -> -0.88666667 | H106: =-H107*H104 -> -1.6466667 | I106: =-I107*I104 -> -4.56 | J106: =-J107*J104 -> 0 | K106: =-K107*K104 -> 0 | ... M106: =-M107*M104 -> 0
C107: Impostos % | D107: 0.04 | E107: =+D107 -> 0.04 | F107: =+E107 -> 0.04 | G107: =+F107 -> 0.04 | H107: =+G107 -> 0.04 | I107: =+H107 -> 0.04 | J107: =+I107 -> 0.04 | K107: =+J107 -> 0.04 | L107: =+K107 -> 0.04 | M107: =+L107 -> 0.04
C109: Receita Líquida | D109: =+D104+D106 -> 0 | E109: =+E104+E106 -> 0 | F109: =+F104+F106 -> 12.16 | G109: =+G104+G106 -> 21.28 | H109: =+H104+H106 -> 39.52 | I109: =+I104+I106 -> 109.44 | J109: =+J104+J106 -> 0 | K109: =+K104+K106 -> 0 | ... M109: =+M104+M106 -> 0
C111: Custo | D111: =D112+D113 -> 0 | E111: =E112+E113 -> 0 | F111: =F112+F113 -> -8.1066667 | G111: =G112+G113 -> -27.486667 | H111: =H112+H113 -> -41.546667 | I111: =I112+I113 -> -4.56 | J111: =J112+J113 -> 0 | K111: =K112+K113 -> 0 | ... M111: =M112+M113 -> 0
C112: Terreno | D112: =+D101+D102 -> 0 | E112: =+E101+E102 -> 0 | F112: =+F101+F102 -> -8.1066667 | G112: =+G101+G102 -> -0.88666667 | H112: =+H101+H102 -> -1.6466667 | I112: =+I101+I102 -> -4.56 | J112: =+J101+J102 -> 0 | K112: =+K101+K102 -> 0 | ... M112: =+M101+M102 -> 0
C113: Construção | D113: =+D134 -> 0 | E113: =+E134 -> 0 | F113: =+F134 -> 0 | G113: =+G134 -> -26.6 | H113: =+H134 -> -39.9 | I113: =+I134 -> 0 | J113: =+J134 -> 0 | K113: =+K134 -> 0 | ... M113: =+M134 -> 0
D115: 0.35 | E115: Obra/VGV
D117: 1o Ano | E117: 2o Ano
D118: 0.4 | E118: 0.6 | F118: Custo Obra/ Ano
C120: Custo de Construção
D122: Ano 1 | E122: Ano 2 | F122: Ano 3 | G122: Ano 4 | H122: Ano 5 | I122: Ano 6 | J122: Ano 7 | K122: Ano 8 | L122: Ano 9 | M122: Ano 10
C123: Ano 1 | E123: =-D15*$D$115*$D$118 -> 0 | F123: =-D15*$D$115*$E$118 -> 0
...

Sheet A CONTRATAR
B2: COMPANHIA REAL ESTATE - A CONTRATAR
B3: Em Milhoes de Reais
C5: Lançamentos (R$Mn)
D7: Ano 1 | E7: Ano 2 | F7: Ano 3 | G7: Ano 4 | H7: Ano 5 | I7: Ano 6 | J7: Ano 7 | K7: Ano 8 | L7: Ano 9 | M7: Ano 10
G8: 250 | H8: 200 | I8: 250 | J8: 300 | K8: 350 | L8: 400 | M8: 450
C10: Comissão Vendas | E10: 0.0525
C12: Lançamentos (R$Mn)
D14: Ano 1 | E14: Ano 2 | F14: Ano 3 | G14: Ano 4 | H14: Ano 5 | I14: Ano 6 | J14: Ano 7 | K14: Ano 8 | L14: Ano 9 | M14: Ano 10
C15: Ano 1 | D15: =+D$8*(1-$E$10) -> 0
C16: Ano 2 | E16: =+E$8*(1-$E$10) -> 0
C17: Ano 3 | F17: =+F$8*(1-$E$10) -> 0
C18: Ano 4 | G18: =+G$8*(1-$E$10) -> 236.875
C19: Ano 5 | H19: =+H$8*(1-$E$10) -> 189.5
C20: Ano 6 | I20: =+I$8*(1-$E$10) -> 236.875
C21: Ano 7 | J21: =+J$8*(1-$E$10) -> 284.25
C22: Ano 8 | K22: =+K$8*(1-$E$10) -> 331.625
C23: Ano 9 | L23: =+L$8*(1-$E$10) -> 379
C24: Ano 10 | M24: =+M$8*(1-$E$10) -> 426.375
D25: =SUM(D15:D24) -> 0 | E25: =SUM(E15:E24) -> 0 | F25: =SUM(F15:F24) -> 0 | G25: =SUM(G15:G24) -> 236.875 | H25: =SUM(H15:H24) -> 189.5 | I25: =SUM(I15:I24) -> 236.875 | J25: =SUM(J15:J24) -> 284.25 | K25: =SUM(K15:K24) -> 331.625 | ... M25: =SUM(M15:M24) -> 426.375
C27: Vendas %
D29: Ano 1 | E29: Ano 2 | F29: Ano 3 | G29: Ano 4 | H29: Ano 5 | I29: Ano 6 | J29: Ano 7 | K29: Ano 8 | L29: Ano 9 | M29: Ano 10
C30: Ano 1
C31: Ano 2
C32: Ano 3
C33: Ano 4 | G33: 0.5 | H33: 0.2 | I33: 0.2 | J33: 0.1
C34: Ano 5 | H34: 0.5 | I34: 0.2 | J34: 0.2 | K34: 0.1
C35: Ano 6 | I35: 0.5 | J35: 0.2 | K35: 0.2 | L35: 0.1
C36: Ano 7 | J36: 0.5 | K36: 0.2 | L36: 0.2 | M36: 0.1
C37: Ano 8 | K37: 0.5 | L37: 0.2 | M37: 0.2 | N37: 0.1
C38: Ano 9 | L38: 0.5 | M38: 0.2 | N38: 0.2 | O38: 0.1
C39: Ano 10 | M39: 0.5 | N39: 0.2 | O39: 0.2 | P39: 0.1
C41: Captação Pre-Chaves
D43: Ano 1 | E43: Ano 2 | F43: Ano 3 | G43: Ano 4 | H43: Ano 5 | I43: Ano 6 | J43: Ano 7 | K43: Ano 8 | L43: Ano 9 | M43: Ano 10 | N43: TOTAL
C44: 1 | D44: =+$F$41/3 -> 0 | E44: =+F41/3 -> 0 | F44: =+F41/3 -> 0 | G44: =+(1-$F$41) -> 1 | N44: =SUM(D44:M44) -> 1
C45: 2 | E45: =+$F$41/2 -> 0 | F45: =+$F$41/2 -> 0 | G45: =+(1-$F$41) -> 1 | N45: =SUM(D45:M45) -> 1
C46: 3 | F46: =+$F$41 -> 0 | G46: =+(1-$F$41) -> 1 | N46: =SUM(D46:M46) -> 1
C47: 4 | G47: 1 | N47: =SUM(D47:M47) -> 1
C49: Receita Bruta (R$Mn)
D51: Ano 1 | E51: Ano 2 | F51: Ano 3 | G51: Ano 4 | H51: Ano 5 | I51: Ano 6 | J51: Ano 7 | K51: Ano 8 | L51: Ano 9 | M51: Ano 10 | Q51: TOTAL
C52: Ano 1 | D52: =+$D$15*$D$30*D$44 -> 0 | E52: =+$D$15*$D$30*E$44 -> 0 | F52: =+$D$15*$D$30*F$44 -> 0 | G52: =+$D$15*$D$30*G$44 -> 0 | Q52: =SUM(D52:P52) -> 0
C53: Ano 1 | E53: =+$D$15*$E$30*$E$45 -> 0 | F53: =+$D$15*$E$30*$F$45 -> 0 | G53: =+$D$15*$E$30*$G$45 -> 0 | Q53: =SUM(D53:P53) -> 0
C54: Ano 1 | F54: =+$D$15*$F$30*$F$46 -> 0 | G54: =+$D$15*$F$30*$G$46 -> 0 | Q54: =SUM(D54:P54) -> 0
C55: Ano 1 | G55: =+$D$15*$G$30*$G$47 -> 0 | Q55: =SUM(D55:P55) -> 0
C56: Ano 2 | E56: =+$E$16*$E$31*D$44 -> 0 | F56: =+$E$16*$E$31*E$44 -> 0 | G56: =+$E$16*$E$31*F$44 -> 0 | H56: =+$E$16*$E$31*G$44 -> 0 | Q56: =SUM(D56:P56) -> 0
C57: Ano 2 | F57: =+$E$16*$F$31*E$45 -> 0 | G57: =+$E$16*$F$31*F$45 -> 0 | H57: =+$E$16*$F$31*G$45 -> 0 | Q57: =SUM(D57:P57) -> 0
C58: Ano 2 | G58: =+$E$16*$G$31*$F$46 -> 0 | H58: =+$E$16*$G$31*$G$46 -> 0 | Q58: =SUM(D58:P58) -> 0
C59: Ano 2 | H59: =+$E$16*$H$31*$G$47 -> 0 | Q59: =SUM(D59:P59) -> 0
C60: Ano 3 | F60: =+$F$17*$F$32*D$44 -> 0 | G60: =+$F$17*$F$32*E$44 -> 0 | H60: =+$F$17*$F$32*F$44 -> 0 | I60: =+$F$17*$F$32*G$44 -> 0 | Q60: =SUM(D60:P60) -> 0
C61: Ano 3 | G61: =+$F$17*$G$32*E$45 -> 0 | H61: =+$F$17*$G$32*F$45 -> 0 | I61: =+$F$17*$G$32*G$45 -> 0 | Q61: =SUM(D61:P61) -> 0
C62: Ano 3 | H62: =+$F$17*$H$32*F$46 -> 0 | I62: =+$F$17*$H$32*G$46 -> 0 | Q62: =SUM(D62:P62) -> 0
C63: Ano 3 | I63: =+$F$17*$I$32*$G$47 -> 0 | Q63: =SUM(D63:P63) -> 0
C64: Ano 4 | G64: =+$G$18*$G$33*D$44 -> 0 | H64: =+$G$18*$G$33*E$44 -> 0 | I64: =+$G$18*$G$33*F$44 -> 0 | J64: =+$G$18*$G$33*G$44 -> 118.4375 | Q64: =SUM(D64:P64) -> 118.4375
C65: Ano 4 | H65: =+$G$18*$H$33*E$45 -> 0 | I65: =+$G$18*$H$33*F$45 -> 0 | J65: =+$G$18*$H$33*G$45 -> 47.375 | Q65: =SUM(D65:P65) -> 47.375
C66: Ano 4 | I66: =+$G$18*$I$33*F$46 -> 0 | J66: =+$G$18*$I$33*G$46 -> 47.375 | Q66: =SUM(D66:P66) -> 47.375
C67: Ano 4 | J67: =+$G$18*$J$33*G$47 -> 23.6875 | Q67: =SUM(D67:P67) -> 23.6875
C68: Ano 5 | H68: =+$H$19*$H$34*D$44 -> 0 | I68: =+$H$19*$H$34*E$44 -> 0 | J68: =+$H$19*$H$34*F$44 -> 0 | K68: =+$H$19*$H$34*G$44 -> 94.75 | Q68: =SUM(D68:P68) -> 94.75
C69: Ano 5 | I69: =+$H$19*$I$34*E$45 -> 0 | J69: =+$H$19*$I$34*F$45 -> 0 | K69: =+$H$19*$I$34*G$45 -> 37.9 | Q69: =SUM(D69:P69) -> 37.9
C70: Ano 5 | J70: =+$H$19*$J$34*F$46 -> 0 | K70: =+$H$19*$J$34*G$46 -> 37.9 | Q70: =SUM(D70:P70) -> 37.9
C71: Ano 5 | K71: =+$H$19*$K$34*G$47 -> 18.95 | Q71: =SUM(D71:P71) -> 18.95
C72: Ano 6 | I72: =+$I$20*$I$35*D$44 -> 0 | J72: =+$I$20*$I$35*E$44 -> 0 | K72: =+$I$20*$I$35*F$44 -> 0 | L72: =+$I$20*$I$35*G$44 -> 118.4375 | Q72: =SUM(D72:P72) -> 118.4375
C73: Ano 6 | J73: =+$I$20*$J$35*E$45 -> 0 | K73: =+$I$20*$J$35*F$45 -> 0 | L73: =+$I$20*$J$35*G$45 -> 47.375 | Q73: =SUM(D73:P73) -> 47.375
C74: Ano 6 | K74: =+$I$20*$K$35*F$46 -> 0 | L74: =+$I$20*$K$35*G$46 -> 47.375 | Q74: =SUM(D74:P74) -> 47.375
C75: Ano 6 | L75: =+$I$20*$L$35*G$47 -> 23.6875 | Q75: =SUM(D75:P75) -> 23.6875
C76: Ano 7 | J76: =+$J$21*$J$36*D$44 -> 0 | K76: =+$J$21*$J$36*E$44 -> 0 | L76: =+$J$21*$J$36*F$44 -> 0 | M76: =+$J$21*$J$36*G$44 -> 142.125 | Q76: =SUM(D76:P76) -> 142.125
C77: Ano 7 | K77: =+$J$21*$K$36*E$45 -> 0 | L77: =+$J$21*$K$36*F$45 -> 0 | M77: =+$J$21*$K$36*G$45 -> 56.85 | Q77: =SUM(D77:P77) -> 56.85
C78: Ano 7 | L78: =+$J$21*$L$36*F$46 -> 0 | M78: =+$J$21*$L$36*G$46 -> 56.85 | Q78: =SUM(D78:P78) -> 56.85
C79: Ano 7 | M79: =+$J$21*$M$36*G$47 -> 28.425 | Q79: =SUM(D79:P79) -> 28.425
C80: Ano 8 | K80: =+$K$22*$K$37*D$44 -> 0 | L80: =+$K$22*$K$37*E$44 -> 0 | M80: =+$K$22*$K$37*F$44 -> 0 | N80: =+$K$22*$K$37*G$44 -> 165.8125 | Q80: =SUM(D80:P80) -> 165.8125
C81: Ano 8 | L81: =+$K$22*$L$37*E$45 -> 0 | M81: =+$K$22*$L$37*F$45 -> 0 | N81: =+$K$22*$L$37*G$45 -> 66.325 | Q81: =SUM(D81:P81) -> 66.325
C82: Ano 8 | M82: =+$K$22*$M$37*F$46 -> 0 | N82: =+$K$22*$M$37*G$46 -> 66.325 | Q82: =SUM(D82:P82) -> 66.325
C83: Ano 8 | N83: =+$K$22*$N$37*G$47 -> 33.1625 | Q83: =SUM(D83:P83) -> 33.1625
C84: Ano 9 | L84: =+$L$23*$L$38*D$44 -> 0 | M84: =+$L$23*$L$38*E$44 -> 0 | N84: =+$L$23*$L$38*F$44 -> 0 | O84: =+$L$23*$L$38*G$44 -> 189.5 | Q84: =SUM(D84:P84) -> 189.5
C85: Ano 9 | M85: =+$L$23*$M$38*E$45 -> 0 | N85: =+$L$23*$M$38*F$45 -> 0 | O85: =+$L$23*$M$38*G$45 -> 75.8 | Q85: =SUM(D85:P85) -> 75.8
C86: Ano 9 | N86: =+$L$23*$N$38*F$46 -> 0 | O86: =+$L$23*$N$38*G$46 -> 75.8 | Q86: =SUM(D86:P86) -> 75.8
C87: Ano 9 | O87: =+$L$23*$O$38*G$47 -> 37.9 | Q87: =SUM(D87:P87) -> 37.9
C88: Ano 10 | M88: =+$M$24*$M$39*D$44 -> 0 | N88: =+$M$24*$M$39*E$44 -> 0 | O88: =+$M$24*$M$39*F$44 -> 0 | P88: =+$M$24*$M$39*G$44 -> 213.1875 | Q88: =SUM(D88:P88) -> 213.1875
C89: Ano 10 | N89: =+$M$24*$N$39*E$45 -> 0 | O89: =+$M$24*$N$39*F$45 -> 0 | P89: =+$M$24*$N$39*G$45 -> 85.275 | Q89: =SUM(D89:P89) -> 85.275
C90: Ano 10 | O90: =+$M$24*$O$39*F$46 -> 0 | P90: =+$M$24*$O$39*G$46 -> 85.275 | Q90: =SUM(D90:P90) -> 85.275
C91: Ano 10 | P91: =+$M$24*$P$39*G$47 -> 42.6375 | Q91: =SUM(D91:P91) -> 42.6375
D92: =SUM(D52:D91) -> 0 | E92: =SUM(E52:E91) -> 0 | F92: =SUM(F52:F91) -> 0 | G92: =SUM(G52:G91) -> 0 | H92: =SUM(H52:H91) -> 0 | I92: =SUM(I52:I91) -> 0 | J92: =SUM(J52:J91) -> 236.875 | K92: =SUM(K52:K91) -> 189.5 | ... M92: =SUM(M52:M91) -> 284.25
C94: Custo Terreno/ VGV
C96: Percentual Medio Permuta
C98: Parcela Cash | F98: 1 | G98: (mesmo ano)
D100: Ano 1 | E100: Ano 2 | F100: Ano 3 | G100: Ano 4 | H100: Ano 5 | I100: Ano 6 | J100: Ano 7 | K100: Ano 8 | L100: Ano 9 | M100: Ano 10
C101: Permuta | D101: =-$F$94*$F$96*D104 -> 0 | E101: =-$F$94*$F$96*E104 -> 0 | F101: =-$F$94*$F$96*F104 -> 0 | G101: =-$F$94*$F$96*G104 -> 0 | H101: =-$F$94*$F$96*H104 -> 0 | I101: =-$F$94*$F$96*I104 -> 0 | J101: =-$F$94*$F$96*J104 -> 0 | K101: =-$F$94*$F$96*K104 -> 0 | ... M101: =-$F$94*$F$96*M104 -> 0
C102: Cash | D102: =-$F$94*$F$96*D25 -> 0 | E102: =-$F$94*$F$96*E25 -> 0 | F102: =-$F$94*$F$96*F25 -> 0 | G102: =-$F$94*$F$96*G25 -> 0 | H102: =-$F$94*$F$96*H25 -> 0 | I102: =-$F$94*$F$96*I25 -> 0 | J102: =-$F$94*$F$96*J25 -> 0 | K102: =-$F$94*$F$96*K25 -> 0 | ... M102: =-$F$94*$F$96*M25 -> 0
C104: Receita Bruta | D104: =+D92 -> 0 | E104: =+E92 -> 0 | F104: =+F92 -> 0 | G104: =+G92 -> 0 | H104: =+H92 -> 0 | I104: =+I92 -> 0 | J104: =+J92 -> 236.875 | K104: =+K92 -> 189.5 | ... M104: =+M92 -> 284.25
C105: Cresc % | E105: =IFERROR(E104/D104-1,0) -> 0 | F105: =IFERROR(F104/E104-1,0) -> 0 | G105: =IFERROR(G104/F104-1,0) -> 0 | H105: =IFERROR(H104/G104-1,0) -> 0 | I105: =IFERROR(I104/H104-1,0) -> 0 | J105: =IFERROR(J104/I104-1,0) -> 0 | K105: =IFERROR(K104/J104-1,0) -> -0.2 | L105: =IFERROR(L104/K104-1,0) -> 0.25 | M105: =IFERROR(M104/L104-1,0) -> 0.2
C106: Impostos | D106: =-D107*D104 -> 0 | E106: =-E107*E104 -> 0 | F106: =-F107*F104 -> 0 | G106: =-G107*G104 -> 0 | H106: =-H107*H104 -> 0 | I106: =-I107*I104 -> 0 | J106: =-J107*J104 -> 0 | K106: =-K107*K104 -> 0 | ... M106: =-M107*M104 -> 0
C107: Impostos % | E107: =+D107 -> 0 | F107: =+E107 -> 0 | G107: =+F107 -> 0 | H107: =+G107 -> 0 | I107: =+H107 -> 0 | J107: =+I107 -> 0 | K107: =+J107 -> 0 | L107: =+K107 -> 0 | M107: =+L107 -> 0
C109: Receita Líquida | D109: =+D104+D106 -> 0 | E109: =+E104+E106 -> 0 | F109: =+F104+F106 -> 0 | G109: =+G104+G106 -> 0 | H109: =+H104+H106 -> 0 | I109: =+I104+I106 -> 0 | J109: =+J104+J106 -> 236.875 | K109: =+K104+K106 -> 189.5 | ... M109: =+M104+M106 -> 284.25
C111: Custo | D111: =D112+D113 -> 0 | E111: =E112+E113 -> 0 | F111: =F112+F113 -> 0 | G111: =G112+G113 -> 0 | H111: =H112+H113 -> 0 | I111: =I112+I113 -> 0 | J111: =J112+J113 -> 0 | K111: =K112+K113 -> 0 | ... M111: =M112+M113 -> 0
C112: Terreno | D112: =+D101+D102 -> 0 | E112: =+E101+E102 -> 0 | F112: =+F101+F102 -> 0 | G112: =+G101+G102 -> 0 | H112: =+H101+H102 -> 0 | I112: =+I101+I102 -> 0 | J112: =+J101+J102 -> 0 | K112: =+K101+K102 -> 0 | ... M112: =+M101+M102 -> 0
C113: Construção | D113: =+D134 -> 0 | E113: =+E134 -> 0 | F113: =+F134 -> 0 | G113: =+G134 -> 0 | H113: =+H134 -> 0 | I113: =+I134 -> 0 | J113: =+J134 -> 0 | K113: =+K134 -> 0 | ... M113: =+M134 -> 0
E115: Obra/VGV
D117: 1o Ano | E117: 2o Ano
F118: Custo Obra/ Ano
C120: Custo de Construção
D122: Ano 1 | E122: Ano 2 | F122: Ano 3 | G122: Ano 4 | H122: Ano 5 | I122: Ano 6 | J122: Ano 7 | K122: Ano 8 | L122: Ano 9 | M122: Ano 10
C123: Ano 1 | E123: =-D15*$D$115*$D$118 -> 0 | F123: =-D15*$D$115*$E$118 -> 0
...

Sheet ESTOQUE PRONTO
A2: COMPANHIA REAL ESTATE - ESTOQUE PRONTO
A3: Em Milhoes de Reais
C6: Estoque e Projeção de vendas (%)
A8: Projeto | B8: Entrega | C8: Valor | D8: Ano 1 | E8: Ano 2 | F8: Ano 3 | G8: Ano 4 | H8: Ano 5 | I8: Ano 6 | J8: Ano 7 | K8: Ano 8 | L8: Ano 9 | M8: Ano 10 | N8: TOTAL
A9: Projeto A | B9: 43070 | C9: 25 | D9: 0.5 | E9: 0.35 | F9: 0.15 | N9: =SUM(D9:M9) -> 1
A10: Projeto B | B10: 42887 | C10: 20 | D10: 0.15 | E10: 0.25 | F10: 0.5 | N10: =SUM(D10:M10) -> 0.9
A11: Projeto C | B11: 42795 | C11: 15 | N11: =SUM(D11:M11) -> 0
A12: Projeto D | B12: 42736 | C12: 12 | N12: =SUM(D12:M12) -> 0
A13: Projeto E | B13: 42705 | C13: 10 | N13: =SUM(D13:M13) -> 0
A14: Projeto F | B14: 42552 | C14: 8 | N14: =SUM(D14:M14) -> 0
A15: Projeto G | B15: 42278 | C15: 5 | N15: =SUM(D15:M15) -> 0
A16: Projeto H | B16: 42186 | C16: 10 | N16: =SUM(D16:M16) -> 0
A17: Projeto I | B17: 41913 | C17: 10 | N17: =SUM(D17:M17) -> 0
A18: Projeto J | B18: 41456 | C18: 5 | N18: =SUM(D18:M18) -> 0
C20: Estoque e Projeção de vendas (R$Mn)
A22: Projeto | B22: Entrega | C22: Valor | D22: Ano 1 | E22: Ano 2 | F22: Ano 3 | G22: Ano 4 | H22: Ano 5 | I22: Ano 6 | J22: Ano 7 | K22: Ano 8 | L22: Ano 9 | M22: Ano 10 | N22: TOTAL
A23: Projeto A | B23: 43070 | C23: =C9 -> 25 | D23: =+$C23*D9 -> 12.5 | E23: =+$C23*E9 -> 8.75 | F23: =+$C23*F9 -> 3.75 | G23: =+$C23*G9 -> 0 | H23: =+$C23*H9 -> 0 | I23: =+$C23*I9 -> 0 | J23: =+$C23*J9 -> 0 | K23: =+$C23*K9 -> 0 | ... M23: =+$C23*M9 -> 0 | N23: =SUM(D23:M23) -> 25
A24: Projeto B | B24: 42887 | C24: =C10 -> 20 | D24: =+$C24*D10 -> 3 | E24: =+$C24*E10 -> 5 | F24: =+$C24*F10 -> 10 | G24: =+$C24*G10 -> 0 | H24: =+$C24*H10 -> 0 | I24: =+$C24*I10 -> 0 | J24: =+$C24*J10 -> 0 | K24: =+$C24*K10 -> 0 | ... M24: =+$C24*M10 -> 0 | N24: =SUM(D24:M24) -> 18
A25: Projeto C | B25: 42795 | C25: =C11 -> 15 | D25: =+$C25*D11 -> 0 | E25: =+$C25*E11 -> 0 | F25: =+$C25*F11 -> 0 | G25: =+$C25*G11 -> 0 | H25: =+$C25*H11 -> 0 | I25: =+$C25*I11 -> 0 | J25: =+$C25*J11 -> 0 | K25: =+$C25*K11 -> 0 | ... M25: =+$C25*M11 -> 0 | N25: =SUM(D25:M25) -> 0
A26: Projeto D | B26: 42736 | C26: =C12 -> 12 | D26: =+$C26*D12 -> 0 | E26: =+$C26*E12 -> 0 | F26: =+$C26*F12 -> 0 | G26: =+$C26*G12 -> 0 | H26: =+$C26*H12 -> 0 | I26: =+$C26*I12 -> 0 | J26: =+$C26*J12 -> 0 | K26: =+$C26*K12 -> 0 | ... M26: =+$C26*M12 -> 0 | N26: =SUM(D26:M26) -> 0
A27: Projeto E | B27: 42705 | C27: =C13 -> 10 | D27: =+$C27*D13 -> 0 | E27: =+$C27*E13 -> 0 | F27: =+$C27*F13 -> 0 | G27: =+$C27*G13 -> 0 | H27: =+$C27*H13 -> 0 | I27: =+$C27*I13 -> 0 | J27: =+$C27*J13 -> 0 | K27: =+$C27*K13 -> 0 | ... M27: =+$C27*M13 -> 0 | N27: =SUM(D27:M27) -> 0
A28: Projeto F | B28: 42552 | C28: =C14 -> 8 | D28: =+$C28*D14 -> 0 | E28: =+$C28*E14 -> 0 | F28: =+$C28*F14 -> 0 | G28: =+$C28*G14 -> 0 | H28: =+$C28*H14 -> 0 | I28: =+$C28*I14 -> 0 | J28: =+$C28*J14 -> 0 | K28: =+$C28*K14 -> 0 | ... M28: =+$C28*M14 -> 0 | N28: =SUM(D28:M28) -> 0
A29: Projeto G | B29: 42278 | C29: =C15 -> 5 | D29: =+$C29*D15 -> 0 | E29: =+$C29*E15 -> 0 | F29: =+$C29*F15 -> 0 | G29: =+$C29*G15 -> 0 | H29: =+$C29*H15 -> 0 | I29: =+$C29*I15 -> 0 | J29: =+$C29*J15 -> 0 | K29: =+$C29*K15 -> 0 | ... M29: =+$C29*M15 -> 0 | N29: =SUM(D29:M29) -> 0
A30: Projeto H | B30: 42186 | C30: =C16 -> 10 | D30: =+$C30*D16 -> 0 | E30: =+$C30*E16 -> 0 | F30: =+$C30*F16 -> 0 | G30: =+$C30*G16 -> 0 | H30: =+$C30*H16 -> 0 | I30: =+$C30*I16 -> 0 | J30: =+$C30*J16 -> 0 | K30: =+$C30*K16 -> 0 | ... M30: =+$C30*M16 -> 0 | N30: =SUM(D30:M30) -> 0
A31: Projeto I | B31: 41913 | C31: =C17 -> 10 | D31: =+$C31*D17 -> 0 | E31: =+$C31*E17 -> 0 | F31: =+$C31*F17 -> 0 | G31: =+$C31*G17 -> 0 | H31: =+$C31*H17 -> 0 | I31: =+$C31*I17 -> 0 | J31: =+$C31*J17 -> 0 | K31: =+$C31*K17 -> 0 | ... M31: =+$C31*M17 -> 0 | N31: =SUM(D31:M31) -> 0
A32: Projeto J | B32: 41456 | C32: =C18 -> 5 | D32: =+$C32*D18 -> 0 | E32: =+$C32*E18 -> 0 | F32: =+$C32*F18 -> 0 | G32: =+$C32*G18 -> 0 | H32: =+$C32*H18 -> 0 | I32: =+$C32*I18 -> 0 | J32: =+$C32*J18 -> 0 | K32: =+$C32*K18 -> 0 | ... M32: =+$C32*M18 -> 0 | N32: =SUM(D32:M32) -> 0
C33: =SUM(C23:C32) -> 120 | D33: =SUM(D23:D32) -> 15.5 | E33: =SUM(E23:E32) -> 13.75 | F33: =SUM(F23:F32) -> 13.75 | G33: =SUM(G23:G32) -> 0 | H33: =SUM(H23:H32) -> 0 | I33: =SUM(I23:I32) -> 0 | J33: =SUM(J23:J32) -> 0 | ... M33: =SUM(M23:M32) -> 0 | N33: =SUM(D33:M33) -> 43
C35: Comissão Vendas | E35: 0.06
C36: Despesa Incremental de Vendas | E36: 0.01
C38: Estoque e Projeção de vendas (R$Mn) - PÓS COMISSÕES
A40: Projeto | B40: Entrega | C40: Valor | D40: Ano 1 | E40: Ano 2 | F40: Ano 3 | G40: Ano 4 | H40: Ano 5 | I40: Ano 6 | J40: Ano 7 | K40: Ano 8 | L40: Ano 9 | M40: Ano 10 | N40: TOTAL
A41: Projeto A | B41: 43070 | C41: =SUM(D41:M41) -> 23.25 | D41: =+D23*(1-($E$35+$E$36)) -> 11.625 | E41: =+E23*(1-($E$35+$E$36)) -> 8.1375 | F41: =+F23*(1-($E$35+$E$36)) -> 3.4875 | G41: =+G23*(1-($E$35+$E$36)) -> 0 | H41: =+H23*(1-($E$35+$E$36)) -> 0 | I41: =+I23*(1-($E$35+$E$36)) -> 0 | J41: =+J23*(1-($E$35+$E$36)) -> 0 | K41: =+K23*(1-($E$35+$E$36)) -> 0 | ... M41: =+M23*(1-($E$35+$E$36)) -> 0 | N41: =SUM(D41:M41) -> 23.25
A42: Projeto B | B42: 42887 | C42: =SUM(D42:M42) -> 16.74 | D42: =+D24*(1-($E$35+$E$36)) -> 2.79 | E42: =+E24*(1-($E$35+$E$36)) -> 4.65 | F42: =+F24*(1-($E$35+$E$36)) -> 9.3 | G42: =+G24*(1-($E$35+$E$36)) -> 0 | H42: =+H24*(1-($E$35+$E$36)) -> 0 | I42: =+I24*(1-($E$35+$E$36)) -> 0 | J42: =+J24*(1-($E$35+$E$36)) -> 0 | K42: =+K24*(1-($E$35+$E$36)) -> 0 | ... M42: =+M24*(1-($E$35+$E$36)) -> 0 | N42: =SUM(D42:M42) -> 16.74
A43: Projeto C | B43: 42795 | C43: =SUM(D43:M43) -> 0 | D43: =+D25*(1-($E$35+$E$36)) -> 0 | E43: =+E25*(1-($E$35+$E$36)) -> 0 | F43: =+F25*(1-($E$35+$E$36)) -> 0 | G43: =+G25*(1-($E$35+$E$36)) -> 0 | H43: =+H25*(1-($E$35+$E$36)) -> 0 | I43: =+I25*(1-($E$35+$E$36)) -> 0 | J43: =+J25*(1-($E$35+$E$36)) -> 0 | K43: =+K25*(1-($E$35+$E$36)) -> 0 | ... M43: =+M25*(1-($E$35+$E$36)) -> 0 | N43: =SUM(D43:M43) -> 0
A44: Projeto D | B44: 42736 | C44: =SUM(D44:M44) -> 0 | D44: =+D26*(1-($E$35+$E$36)) -> 0 | E44: =+E26*(1-($E$35+$E$36)) -> 0 | F44: =+F26*(1-($E$35+$E$36)) -> 0 | G44: =+G26*(1-($E$35+$E$36)) -> 0 | H44: =+H26*(1-($E$35+$E$36)) -> 0 | I44: =+I26*(1-($E$35+$E$36)) -> 0 | J44: =+J26*(1-($E$35+$E$36)) -> 0 | K44: =+K26*(1-($E$35+$E$36)) -> 0 | ... M44: =+M26*(1-($E$35+$E$36)) -> 0 | N44: =SUM(D44:M44) -> 0
A45: Projeto E | B45: 42705 | C45: =SUM(D45:M45) -> 0 | D45: =+D27*(1-($E$35+$E$36)) -> 0 | E45: =+E27*(1-($E$35+$E$36)) -> 0 | F45: =+F27*(1-($E$35+$E$36)) -> 0 | G45: =+G27*(1-($E$35+$E$36)) -> 0 | H45: =+H27*(1-($E$35+$E$36)) -> 0 | I45: =+I27*(1-($E$35+$E$36)) -> 0 | J45: =+J27*(1-($E$35+$E$36)) -> 0 | K45: =+K27*(1-($E$35+$E$36)) -> 0 | ... M45: =+M27*(1-($E$35+$E$36)) -> 0 | N45: =SUM(D45:M45) -> 0
A46: Projeto F | B46: 42552 | C46: =SUM(D46:M46) -> 0 | D46: =+D28*(1-($E$35+$E$36)) -> 0 | E46: =+E28*(1-($E$35+$E$36)) -> 0 | F46: =+F28*(1-($E$35+$E$36)) -> 0 | G46: =+G28*(1-($E$35+$E$36)) -> 0 | H46: =+H28*(1-($E$35+$E$36)) -> 0 | I46: =+I28*(1-($E$35+$E$36)) -> 0 | J46: =+J28*(1-($E$35+$E$36)) -> 0 | K46: =+K28*(1-($E$35+$E$36)) -> 0 | ... M46: =+M28*(1-($E$35+$E$36)) -> 0 | N46: =SUM(D46:M46) -> 0
A47: Projeto G | B47: 42278 | C47: =SUM(D47:M47) -> 0 | D47: =+D29*(1-($E$35+$E$36)) -> 0 | E47: =+E29*(1-($E$35+$E$36)) -> 0 | F47: =+F29*(1-($E$35+$E$36)) -> 0 | G47: =+G29*(1-($E$35+$E$36)) -> 0 | H47: =+H29*(1-($E$35+$E$36)) -> 0 | I47: =+I29*(1-($E$35+$E$36)) -> 0 | J47: =+J29*(1-($E$35+$E$36)) -> 0 | K47: =+K29*(1-($E$35+$E$36)) -> 0 | ... M47: =+M29*(1-($E$35+$E$36)) -> 0 | N47: =SUM(D47:M47) -> 0
A48: Projeto H | B48: 42186 | C48: =SUM(D48:M48) -> 0 | D48: =+D30*(1-($E$35+$E$36)) -> 0 | E48: =+E30*(1-($E$35+$E$36)) -> 0 | F48: =+F30*(1-($E$35+$E$36)) -> 0 | G48: =+G30*(1-($E$35+$E$36)) -> 0 | H48: =+H30*(1-($E$35+$E$36)) -> 0 | I48: =+I30*(1-($E$35+$E$36)) -> 0 | J48: =+J30*(1-($E$35+$E$36)) -> 0 | K48: =+K30*(1-($E$35+$E$36)) -> 0 | ... M48: =+M30*(1-($E$35+$E$36)) -> 0 | N48: =SUM(D48:M48) -> 0
A49: Projeto I | B49: 41913 | C49: =SUM(D49:M49) -> 0 | D49: =+D31*(1-($E$35+$E$36)) -> 0 | E49: =+E31*(1-($E$35+$E$36)) -> 0 | F49: =+F31*(1-($E$35+$E$36)) -> 0 | G49: =+G31*(1-($E$35+$E$36)) -> 0 | H49: =+H31*(1-($E$35+$E$36)) -> 0 | I49: =+I31*(1-($E$35+$E$36)) -> 0 | J49: =+J31*(1-($E$35+$E$36)) -> 0 | K49: =+K31*(1-($E$35+$E$36)) -> 0 | ... M49: =+M31*(1-($E$35+$E$36)) -> 0 | N49: =SUM(D49:M49) -> 0
A50: Projeto J | B50: 41456 | C50: =SUM(D50:M50) -> 0 | D50: =+D32*(1-($E$35+$E$36)) -> 0 | E50: =+E32*(1-($E$35+$E$36)) -> 0 | F50: =+F32*(1-($E$35+$E$36)) -> 0 | G50: =+G32*(1-($E$35+$E$36)) -> 0 | H50: =+H32*(1-($E$35+$E$36)) -> 0 | I50: =+I32*(1-($E$35+$E$36)) -> 0 | J50: =+J32*(1-($E$35+$E$36)) -> 0 | K50: =+K32*(1-($E$35+$E$36)) -> 0 | ... M50: =+M32*(1-($E$35+$E$36)) -> 0 | N50: =SUM(D50:M50) -> 0
C51: =SUM(C41:C50) -> 39.99 | D51: =SUM(D41:D50) -> 14.415 | E51: =SUM(E41:E50) -> 12.7875 | F51: =SUM(F41:F50) -> 12.7875 | G51: =SUM(G41:G50) -> 0 | H51: =SUM(H41:H50) -> 0 | I51: =SUM(I41:I50) -> 0 | J51: =SUM(J41:J50) -> 0 | ... M51: =SUM(M41:M50) -> 0 | N51: =SUM(D51:M51) -> 39.99

Sheet JA LANÇADOS
A2: COMPANHIA REAL ESTATE - JÁ LANÇADOS
A3: Em Milhoes de Reais
C6: Comissão Vendas | E6: 0.04
C8: % Vendido
A10: Projeto | B10: Lançamento | C10: Valor | D10: % Vendido
A11: Projeto X | B11: Ano -1 | C11: 120 | D11: 0.65
A12: Projeto Y | B12: Ano -2 | C12: 100 | D12: 0.8
A17: Projeto | B17: Lançamento | C17: Valor | D17: Valor a ser Vendido
A18: Projeto X | B18: Ano -1 | C18: =C11 -> 120 | D18: =C18*(1-D11) -> 42
A19: Projeto Y | B19: Ano -2 | C19: =C12 -> 100 | D19: =C19*(1-D12) -> 20
C21: Captação Pre-Chaves | F21: 0.3
D23: Ano 1 | E23: Ano 2 | F23: Ano 3 | G23: Ano 4 | H23: Ano 5 | I23: Ano 6 | J23: Ano 7 | K23: Ano 8 | L23: Ano 9 | M23: Ano 10 | N23: TOTAL
C24: 1 | D24: =+$F$21/3 -> 0.1 | E24: =+F21/3 -> 0.1 | F24: =+F21/3 -> 0.1 | G24: =+(1-$F$21) -> 0.7 | N24: =SUM(D24:M24) -> 1
C25: 2 | E25: =+$F$21/2 -> 0.15 | F25: =+$F$21/2 -> 0.15 | G25: =+(1-$F$21) -> 0.7 | N25: =SUM(D25:M25) -> 1
C26: 3 | F26: =+$F$21 -> 0.3 | G26: =+(1-$F$21) -> 0.7 | N26: =SUM(D26:M26) -> 1
C27: 4 | G27: 1 | N27: =SUM(D27:M27) -> 1
C29: Receita Bruta (R$Mn)
D31: Ano 1 | E31: Ano 2 | F31: Ano 3 | G31: Ano 4 | H31: Ano 5 | I31: Ano 6 | J31: Ano 7 | K31: Ano 8 | L31: Ano 9 | M31: Ano 10
B32: Vendido | C32: Projeto X | D32: =+$C$11*(1-$E$6)*E24 -> 11.52 | E32: =+$C$11*(1-$E$6)*F24 -> 11.52 | F32: =+$C$11*(1-$E$6)*G24 -> 80.64
B33: Projetado | C33: Projeto X | D33: =+$D$18*(1-$E$6)*E25 -> 6.048 | E33: =+$D$18*(1-$E$6)*F25 -> 6.048 | F33: =+$D$18*(1-$E$6)*G25 -> 28.224
B35: Vendido | C35: Projeto Y | D35: =+$C$12*(1-$E$6)*F24 -> 9.6 | E35: =+$C$12*(1-$E$6)*G24 -> 67.2
B36: Projetado | C36: Projeto Y | D36: =+$D$19*(1-$E$6)*F26 -> 5.76 | E36: =+$D$19*(1-$E$6)*G26 -> 13.44
D38: =SUM(D32:D37) -> 32.928 | E38: =SUM(E32:E37) -> 98.208 | F38: =SUM(F32:F37) -> 108.864 | G38: =SUM(G32:G37) -> 0 | H38: =SUM(H32:H37) -> 0 | I38: =SUM(I32:I37) -> 0 | J38: =SUM(J32:J37) -> 0 | K38: =SUM(K32:K37) -> 0 | ... M38: =SUM(M32:M37) -> 0
C40: Custo Terreno/ VGV | F40: 0.35
C42: Percentual Medio Permuta | F42: 0.15
C44: Parcela Cash | F44: 1 | G44: (mesmo ano)
D46: Ano 1 | E46: Ano 2 | F46: Ano 3 | G46: Ano 4 | H46: Ano 5 | I46: Ano 6 | J46: Ano 7 | K46: Ano 8 | L46: Ano 9 | M46: Ano 10
C47: Permuta | D47: =-$F$40*$F$42*D38 -> -1.72872 | E47: =-$F$40*$F$42*E38 -> -5.15592 | F47: =-$F$40*$F$42*F38 -> -5.71536 | G47: =-$F$40*$F$42*G38 -> 0 | H47: =-$F$40*$F$42*H38 -> 0 | I47: =-$F$40*$F$42*I38 -> 0 | J47: =-$F$40*$F$42*J38 -> 0 | K47: =-$F$40*$F$42*K38 -> 0 | ... M47: =-$F$40*$F$42*M38 -> 0
C48: Cash | D48: =-$F$40*(1-$F$42)*D38 -> -9.79608 | E48: =-$F$40*(1-$F$42)*E38 -> -29.21688 | F48: =-$F$40*(1-$F$42)*F38 -> -32.38704 | G48: =-$F$40*(1-$F$42)*G38 -> 0 | H48: =-$F$40*(1-$F$42)*H38 -> 0 | I48: =-$F$40*(1-$F$42)*I38 -> 0 | J48: =-$F$40*(1-$F$42)*J38 -> 0 | K48: =-$F$40*(1-$F$42)*K38 -> 0 | ... M48: =-$F$40*(1-$F$42)*M38 -> 0
C50: Receita Bruta | D50: =+D38 -> 32.928 | E50: =+E38 -> 98.208 | F50: =+F38 -> 108.864 | G50: =+G38 -> 0 | H50: =+H38 -> 0 | I50: =+I38 -> 0 | J50: =+J38 -> 0 | K50: =+K38 -> 0 | ... M50: =+M38 -> 0
C51: Cresc % | E51: =IFERROR(E50/D50-1,0) -> 1.9825073 | F51: =IFERROR(F50/E50-1,0) -> 0.1085044 | G51: =IFERROR(G50/F50-1,0) -> -1 | H51: =IFERROR(H50/G50-1,0) -> 0 | I51: =IFERROR(I50/H50-1,0) -> 0 | J51: =IFERROR(J50/I50-1,0) -> 0 | K51: =IFERROR(K50/J50-1,0) -> 0 | L51: =IFERROR(L50/K50-1,0) -> 0 | M51: =IFERROR(M50/L50-1,0) -> 0
C52: Impostos | D52: =-D53*D50 -> -1.31712 | E52: =-E53*E50 -> -3.92832 | F52: =-F53*F50 -> -4.35456 | G52: =-G53*G50 -> 0 | H52: =-H53*H50 -> 0 | I52: =-I53*I50 -> 0 | J52: =-J53*J50 -> 0 | K52: =-K53*K50 -> 0 | ... M52: =-M53*M50 -> 0
C53: Impostos % | D53: 0.04 | E53: =+D53 -> 0.04 | F53: =+E53 -> 0.04 | G53: =+F53 -> 0.04 | H53: =+G53 -> 0.04 | I53: =+H53 -> 0.04 | J53: =+I53 -> 0.04 | K53: =+J53 -> 0.04 | L53: =+K53 -> 0.04 | M53: =+L53 -> 0.04
C55: Receita Líquida | D55: =+D50+D52 -> 31.61088 | E55: =+E50+E52 -> 94.27968 | F55: =+F50+F52 -> 104.50944 | G55: =+G50+G52 -> 0 | H55: =+H50+H52 -> 0 | I55: =+I50+I52 -> 0 | J55: =+J50+J52 -> 0 | K55: =+K50+K52 -> 0 | ... M55: =+M50+M52 -> 0
C57: Custo | D57: =D58+D59 -> -33.1248 | E57: =E58+E59 -> -66.7728 | F57: =F58+F59 -> -50.1024 | G57: =G58+G59 -> 0 | H57: =H58+H59 -> 0 | I57: =I58+I59 -> 0 | J57: =J58+J59 -> 0 | K57: =K58+K59 -> 0 | ... M57: =M58+M59 -> 0
C58: Terreno | D58: =+D47+D48 -> -11.5248 | E58: =+E47+E48 -> -34.3728 | F58: =+F47+F48 -> -38.1024 | G58: =+G47+G48 -> 0 | H58: =+H47+H48 -> 0 | I58: =+I47+I48 -> 0 | J58: =+J47+J48 -> 0 | K58: =+K47+K48 -> 0 | ... M58: =+M47+M48 -> 0
C59: Construção | D59: =+D72 -> -21.6 | E59: =+E72 -> -32.4 | F59: =+F72 -> -12 | G59: =+G72 -> 0 | H59: =+H72 -> 0 | I59: =+I72 -> 0 | J59: =+J72 -> 0 | K59: =+K72 -> 0 | ... M59: =+M72 -> 0
D61: 0.3 | E61: Obra/VGV
D63: 1o Ano | E63: 2o Ano
D64: 0.6 | E64: 0.4 | F64: Custo Obra/ Ano
C66: Custo de Construção
D68: Ano 1 | E68: Ano 2 | F68: Ano 3 | G68: Ano 4 | H68: Ano 5 | I68: Ano 6 | J68: Ano 7 | K68: Ano 8 | L68: Ano 9 | M68: Ano 10
C69: Projeto X | D69: =-$C11*$D$61*$D$64 -> -21.6 | E69: =-$C11*$D$61*$E$64 -> -14.4
C70: Projeto Y | E70: =-$C12*$D$61*$D$64 -> -18 | F70: =-$C12*$D$61*$E$64 -> -12
C72: Total | D72: =SUM(D69:D70) -> -21.6 | E72: =SUM(E69:E70) -> -32.4 | F72: =SUM(F69:F70) -> -12 | G72: =SUM(G69:G70) -> 0 | H72: =SUM(H69:H70) -> 0 | I72: =SUM(I69:I70) -> 0 | J72: =SUM(J69:J70) -> 0 | K72: =SUM(K69:K70) -> 0 | ... M72: =SUM(M69:M70) -> 0
C74: Construção Capital Próprio | D74: =+D72*(1-$D$76) -> -10.8 | E74: =+E72*(1-$D$76) -> -16.2 | F74: =+F72*(1-$D$76) -> -6 | G74: =+G72*(1-$D$76) -> 0 | H74: =+H72*(1-$D$76) -> 0 | I74: =+I72*(1-$D$76) -> 0 | J74: =+J72*(1-$D$76) -> 0 | K74: =+K72*(1-$D$76) -> 0 | ... M74: =+M72*(1-$D$76) -> 0
C76: Financiamento | D76: 0.5
C77: Juros | D77: 0.1 | E77: a.a.
C79: Financiamento | D79: =-D72*$D$76 -> 10.8 | E79: =-E72*$D$76 -> 16.2 | F79: =-F72*$D$76 -> 6 | G79: =-G72*$D$76 -> 0 | H79: =-H72*$D$76 -> 0 | I79: =-I72*$D$76 -> 0 | J79: =-J72*$D$76 -> 0 | K79: =-K72*$D$76 -> 0 | ... M79: =-M72*$D$76 -> 0
C80: Repagamento | D80: =+D88 -> 0 | E80: =+E88 -> 0 | F80: =+F88 -> -41.976 | G80: =+G88 -> -34.98 | H80: =+H88 -> 0 | I80: =+I88 -> 0 | J80: =+J88 -> 0 | K80: =+K88 -> 0 | ... M80: =+M88 -> 0
D82: Pagamento de Financ. a Construção
D84: Ano 1 | E84: Ano 2 | F84: Ano 3 | G84: Ano 4 | H84: Ano 5 | I84: Ano 6 | J84: Ano 7 | K84: Ano 8 | L84: Ano 9 | M84: Ano 10
C85: Projeto X | F85: =(D69*(1+$D$77)^2)+(E69*(1+$D$77)^1) -> -41.976
C86: Projeto Y | G86: =(E70*(1+$D$77)^2)+(F70*(1+$D$77)^1) -> -34.98
C88: Total | D88: =SUM(D85:D86) -> 0 | E88: =SUM(E85:E86) -> 0 | F88: =SUM(F85:F86) -> -41.976 | G88: =SUM(G85:G86) -> -34.98 | H88: =SUM(H85:H86) -> 0 | I88: =SUM(I85:I86) -> 0 | J88: =SUM(J85:J86) -> 0 | K88: =SUM(K85:K86) -> 0 | ... M88: =SUM(M85:M86) -> 0
C90: Despesas Comerciais | D90: =-D91*D50 -> -1.31712 | E90: =-E91*E50 -> -3.92832 | F90: =-F91*F50 -> -4.35456 | G90: =-G91*G50 -> 0 | H90: =-H91*H50 -> 0 | I90: =-I91*I50 -> 0 | J90: =-J91*J50 -> 0 | K90: =-K91*K50 -> 0 | ... M90: =-M91*M50 -> 0
C91: % Despesas Comerciais | D91: 0.04 | E91: =+D91 -> 0.04 | F91: =+E91 -> 0.04 | G91: =+F91 -> 0.04 | H91: =+G91 -> 0.04 | I91: =+H91 -> 0.04 | J91: =+I91 -> 0.04 | K91: =+J91 -> 0.04 | L91: =+K91 -> 0.04 | M91: =+L91 -> 0.04
C93: (Fluxo de Caixa Operacional) | D93: =+D55+D57+D90 -> -2.83104 | E93: =+E55+E57+E90 -> 23.57856 | F93: =+F55+F57+F90 -> 50.05248 | G93: =+G55+G57+G90 -> 0 | H93: =+H55+H57+H90 -> 0 | I93: =+I55+I57+I90 -> 0 | J93: =+J55+J57+J90 -> 0 | K93: =+K55+K57+K90 -> 0 | ... M93: =+M55+M57+M90 -> 0
C96: Financiamento | D96: =D97+D98 -> 10.8 | E96: =E97+E98 -> 16.2 | F96: =F97+F98 -> -35.976 | G96: =G97+G98 -> -34.98 | H96: =H97+H98 -> 0 | I96: =I97+I98 -> 0 | J96: =J97+J98 -> 0 | K96: =K97+K98 -> 0 | ... M96: =M97+M98 -> 0
C97: Entradas | D97: =+D79 -> 10.8 | E97: =+E79 -> 16.2 | F97: =+F79 -> 6 | G97: =+G79 -> 0 | H97: =+H79 -> 0 | I97: =+I79 -> 0 | J97: =+J79 -> 0 | K97: =+K79 -> 0 | ... M97: =+M79 -> 0
C98: Saídas | D98: =+D80 -> 0 | E98: =+E80 -> 0 | F98: =+F80 -> -41.976 | G98: =+G80 -> -34.98 | H98: =+H80 -> 0 | I98: =+I80 -> 0 | J98: =+J80 -> 0 | K98: =+K80 -> 0 | ... M98: =+M80 -> 0
C100: Fluxo de Caixa Livre | D100: =+D93+D96 -> 7.96896 | E100: =+E93+E96 -> 39.77856 | F100: =+F93+F96 -> 14.07648 | G100: =+G93+G96 -> -34.98 | H100: =+H93+H96 -> 0 | I100: =+I93+I96 -> 0 | J100: =+J93+J96 -> 0 | K100: =+K93+K96 -> 0 | ... M100: =+M93+M96 -> 0

Sheet ESTRUT. ADM (G&A)
B2: COMPANHIA REAL ESTATE - Estrutura Administrativa (G&A)
B3: Em Milhoes de Reais
D5: Ano 1 | E5: Ano 2 | F5: Ano 3 | G5: Ano 4 | H5: Ano 5 | I5: Ano 6 | J5: Ano 7 | K5: Ano 8 | L5: Ano 9 | M5: Ano 10
C6: Diretor Presidente | D6: 1 | E6: 1 | F6: 1 | G6: 1 | H6: 1 | I6: 1 | J6: 1 | K6: 1 | L6: 1 | M6: 1
C7: Diretor Incorporação | D7: 1 | E7: 1 | F7: 1 | G7: 1 | H7: 1 | I7: 1 | J7: 1 | K7: 1 | L7: 1 | M7: 1
C8: Diretor Comercial | D8: 1 | E8: 1 | F8: 1 | G8: 1 | H8: 1 | I8: 1 | J8: 1 | K8: 1 | L8: 1 | M8: 1
C9: Diretor de Operações | D9: 1 | E9: 1 | F9: 1 | G9: 1 | H9: 1 | I9: 1 | J9: 1 | K9: 1 | L9: 1 | M9: 1
C10: Gerente de Incorporação | D10: 1 | E10: 1 | F10: 1 | G10: 1 | H10: 1 | I10: 1 | J10: 1 | K10: 1 | L10: 1 | M10: 1
C11: Gerente Comercial | D11: 1 | E11: 1 | F11: 1 | G11: 1 | H11: 1 | I11: 1 | J11: 1 | K11: 1 | L11: 1 | M11: 1
C12: Gerente Operações | D12: 1 | E12: 1 | F12: 1 | G12: 1 | H12: 1 | I12: 1 | J12: 1 | K12: 1 | L12: 1 | M12: 1
C13: Supervisor Comercial
C14: (completar)
C15: (completar)
C16: (completar)
C17: (completar)
C18: (completar)
C19: (completar)
C20: (completar)
C23: Correção Real Anual | E23: 0.01 | F23: =E23 -> 0.01 | G23: =F23 -> 0.01 | H23: =G23 -> 0.01 | I23: =H23 -> 0.01 | J23: =I23 -> 0.01 | K23: =J23 -> 0.01 | L23: =K23 -> 0.01 | M23: =L23 -> 0.01
D25: Salários Mensais
D26: Ano 1 | E26: Ano 2 | F26: Ano 3 | G26: Ano 4 | H26: Ano 5 | I26: Ano 6 | J26: Ano 7 | K26: Ano 8 | L26: Ano 9 | M26: Ano 10
C27: Diretor Presidente | D27: 35000 | E27: =D27*(1+E$23) -> 35350 | F27: =E27*(1+F$23) -> 35703.5 | G27: =F27*(1+G$23) -> 36060.535 | H27: =G27*(1+H$23) -> 36421.14 | I27: =H27*(1+I$23) -> 36785.352 | J27: =I27*(1+J$23) -> 37153.205 | K27: =J27*(1+K$23) -> 37524.737 | L27: =K27*(1+L$23) -> 37899.985 | M27: =L27*(1+M$23) -> 38278.985
C28: Diretor Incorporação | D28: 25000 | E28: =D28*(1+E$23) -> 25250 | F28: =E28*(1+F$23) -> 25502.5 | G28: =F28*(1+G$23) -> 25757.525 | H28: =G28*(1+H$23) -> 26015.1 | I28: =H28*(1+I$23) -> 26275.251 | J28: =I28*(1+J$23) -> 26538.004 | K28: =J28*(1+K$23) -> 26803.384 | L28: =K28*(1+L$23) -> 27071.418 | M28: =L28*(1+M$23) -> 27342.132
C29: Diretor Comercial | D29: 25000 | E29: =D29*(1+E$23) -> 25250 | F29: =E29*(1+F$23) -> 25502.5 | G29: =F29*(1+G$23) -> 25757.525 | H29: =G29*(1+H$23) -> 26015.1 | I29: =H29*(1+I$23) -> 26275.251 | J29: =I29*(1+J$23) -> 26538.004 | K29: =J29*(1+K$23) -> 26803.384 | L29: =K29*(1+L$23) -> 27071.418 | M29: =L29*(1+M$23) -> 27342.132
C30: Diretor de Operações | D30: 25000 | E30: =D30*(1+E$23) -> 25250 | F30: =E30*(1+F$23) -> 25502.5 | G30: =F30*(1+G$23) -> 25757.525 | H30: =G30*(1+H$23) -> 26015.1 | I30: =H30*(1+I$23) -> 26275.251 | J30: =I30*(1+J$23) -> 26538.004 | K30: =J30*(1+K$23) -> 26803.384 | L30: =K30*(1+L$23) -> 27071.418 | M30: =L30*(1+M$23) -> 27342.132
C31: Gerente de Incorporação | D31: 15000 | E31: =D31*(1+E$23) -> 15150 | F31: =E31*(1+F$23) -> 15301.5 | G31: =F31*(1+G$23) -> 15454.515 | H31: =G31*(1+H$23) -> 15609.06 | I31: =H31*(1+I$23) -> 15765.151 | J31: =I31*(1+J$23) -> 15922.802 | K31: =J31*(1+K$23) -> 16082.03 | L31: =K31*(1+L$23) -> 16242.851 | M31: =L31*(1+M$23) -> 16405.279
C32: Gerente Comercial | D32: 15000 | E32: =D32*(1+E$23) -> 15150 | F32: =E32*(1+F$23) -> 15301.5 | G32: =F32*(1+G$23) -> 15454.515 | H32: =G32*(1+H$23) -> 15609.06 | I32: =H32*(1+I$23) -> 15765.151 | J32: =I32*(1+J$23) -> 15922.802 | K32: =J32*(1+K$23) -> 16082.03 | L32: =K32*(1+L$23) -> 16242.851 | M32: =L32*(1+M$23) -> 16405.279
C33: Gerente Operações | D33: 15000 | E33: =D33*(1+E$23) -> 15150 | F33: =E33*(1+F$23) -> 15301.5 | G33: =F33*(1+G$23) -> 15454.515 | H33: =G33*(1+H$23) -> 15609.06 | I33: =H33*(1+I$23) -> 15765.151 | J33: =I33*(1+J$23) -> 15922.802 | K33: =J33*(1+K$23) -> 16082.03 | L33: =K33*(1+L$23) -> 16242.851 | M33: =L33*(1+M$23) -> 16405.279
C34: Supervisor Comercial | E34: =D34*(1+E$23) -> 0 | F34: =E34*(1+F$23) -> 0 | G34: =F34*(1+G$23) -> 0 | H34: =G34*(1+H$23) -> 0 | I34: =H34*(1+I$23) -> 0 | J34: =I34*(1+J$23) -> 0 | K34: =J34*(1+K$23) -> 0 | L34: =K34*(1+L$23) -> 0 | M34: =L34*(1+M$23) -> 0
C35: (completar) | E35: =D35*(1+E$23) -> 0 | F35: =E35*(1+F$23) -> 0 | G35: =F35*(1+G$23) -> 0 | H35: =G35*(1+H$23) -> 0 | I35: =H35*(1+I$23) -> 0 | J35: =I35*(1+J$23) -> 0 | K35: =J35*(1+K$23) -> 0 | L35: =K35*(1+L$23) -> 0 | M35: =L35*(1+M$23) -> 0
C36: (completar) | E36: =D36*(1+E$23) -> 0 | F36: =E36*(1+F$23) -> 0 | G36: =F36*(1+G$23) -> 0 | H36: =G36*(1+H$23) -> 0 | I36: =H36*(1+I$23) -> 0 | J36: =I36*(1+J$23) -> 0 | K36: =J36*(1+K$23) -> 0 | L36: =K36*(1+L$23) -> 0 | M36: =L36*(1+M$23) -> 0
C37: (completar) | E37: =D37*(1+E$23) -> 0 | F37: =E37*(1+F$23) -> 0 | G37: =F37*(1+G$23) -> 0 | H37: =G37*(1+H$23) -> 0 | I37: =H37*(1+I$23) -> 0 | J37: =I37*(1+J$23) -> 0 | K37: =J37*(1+K$23) -> 0 | L37: =K37*(1+L$23) -> 0 | M37: =L37*(1+M$23) -> 0
C38: (completar) | E38: =D38*(1+E$23) -> 0 | F38: =E38*(1+F$23) -> 0 | G38: =F38*(1+G$23) -> 0 | H38: =G38*(1+H$23) -> 0 | I38: =H38*(1+I$23) -> 0 | J38: =I38*(1+J$23) -> 0 | K38: =J38*(1+K$23) -> 0 | L38: =K38*(1+L$23) -> 0 | M38: =L38*(1+M$23) -> 0
C39: (completar) | E39: =D39*(1+E$23) -> 0 | F39: =E39*(1+F$23) -> 0 | G39: =F39*(1+G$23) -> 0 | H39: =G39*(1+H$23) -> 0 | I39: =H39*(1+I$23) -> 0 | J39: =I39*(1+J$23) -> 0 | K39: =J39*(1+K$23) -> 0 | L39: =K39*(1+L$23) -> 0 | M39: =L39*(1+M$23) -> 0
C40: (completar) | E40: =D40*(1+E$23) -> 0 | F40: =E40*(1+F$23) -> 0 | G40: =F40*(1+G$23) -> 0 | H40: =G40*(1+H$23) -> 0 | I40: =H40*(1+I$23) -> 0 | J40: =I40*(1+J$23) -> 0 | K40: =J40*(1+K$23) -> 0 | L40: =K40*(1+L$23) -> 0 | M40: =L40*(1+M$23) -> 0
C41: (completar) | E41: =D41*(1+E$23) -> 0 | F41: =E41*(1+F$23) -> 0 | G41: =F41*(1+G$23) -> 0 | H41: =G41*(1+H$23) -> 0 | I41: =H41*(1+I$23) -> 0 | J41: =I41*(1+J$23) -> 0 | K41: =J41*(1+K$23) -> 0 | L41: =K41*(1+L$23) -> 0 | M41: =L41*(1+M$23) -> 0
D43: Encargos
D44: Ano 1 | E44: Ano 2 | F44: Ano 3 | G44: Ano 4 | H44: Ano 5 | I44: Ano 6 | J44: Ano 7 | K44: Ano 8 | L44: Ano 9 | M44: Ano 10
C45: Diretor Presidente | D45: 1.7 | E45: =D45 -> 1.7 | F45: =E45 -> 1.7 | G45: =F45 -> 1.7 | H45: =G45 -> 1.7 | I45: =H45 -> 1.7 | J45: =I45 -> 1.7 | K45: =J45 -> 1.7 | L45: =K45 -> 1.7 | M45: =L45 -> 1.7
C46: Diretor Incorporação | D46: 1.7 | E46: =D46 -> 1.7 | F46: =E46 -> 1.7 | G46: =F46 -> 1.7 | H46: =G46 -> 1.7 | I46: =H46 -> 1.7 | J46: =I46 -> 1.7 | K46: =J46 -> 1.7 | L46: =K46 -> 1.7 | M46: =L46 -> 1.7
C47: Diretor Comercial | D47: 1.7 | E47: =D47 -> 1.7 | F47: =E47 -> 1.7 | G47: =F47 -> 1.7 | H47: =G47 -> 1.7 | I47: =H47 -> 1.7 | J47: =I47 -> 1.7 | K47: =J47 -> 1.7 | L47: =K47 -> 1.7 | M47: =L47 -> 1.7
C48: Diretor de Operações | D48: 1.7 | E48: =D48 -> 1.7 | F48: =E48 -> 1.7 | G48: =F48 -> 1.7 | H48: =G48 -> 1.7 | I48: =H48 -> 1.7 | J48: =I48 -> 1.7 | K48: =J48 -> 1.7 | L48: =K48 -> 1.7 | M48: =L48 -> 1.7
C49: Gerente de Incorporação | D49: 1.7 | E49: =D49 -> 1.7 | F49: =E49 -> 1.7 | G49: =F49 -> 1.7 | H49: =G49 -> 1.7 | I49: =H49 -> 1.7 | J49: =I49 -> 1.7 | K49: =J49 -> 1.7 | L49: =K49 -> 1.7 | M49: =L49 -> 1.7
C50: Gerente Comercial | D50: 1.7 | E50: =D50 -> 1.7 | F50: =E50 -> 1.7 | G50: =F50 -> 1.7 | H50: =G50 -> 1.7 | I50: =H50 -> 1.7 | J50: =I50 -> 1.7 | K50: =J50 -> 1.7 | L50: =K50 -> 1.7 | M50: =L50 -> 1.7
C51: Gerente Operações | D51: 1.7 | E51: =D51 -> 1.7 | F51: =E51 -> 1.7 | G51: =F51 -> 1.7 | H51: =G51 -> 1.7 | I51: =H51 -> 1.7 | J51: =I51 -> 1.7 | K51: =J51 -> 1.7 | L51: =K51 -> 1.7 | M51: =L51 -> 1.7
C52: Supervisor Comercial | D52: 1.7 | E52: =D52 -> 1.7 | F52: =E52 -> 1.7 | G52: =F52 -> 1.7 | H52: =G52 -> 1.7 | I52: =H52 -> 1.7 | J52: =I52 -> 1.7 | K52: =J52 -> 1.7 | L52: =K52 -> 1.7 | M52: =L52 -> 1.7
C53: (completar) | D53: 1.7 | E53: =D53 -> 1.7 | F53: =E53 -> 1.7 | G53: =F53 -> 1.7 | H53: =G53 -> 1.7 | I53: =H53 -> 1.7 | J53: =I53 -> 1.7 | K53: =J53 -> 1.7 | L53: =K53 -> 1.7 | M53: =L53 -> 1.7
C54: (completar) | D54: 1.7 | E54: =D54 -> 1.7 | F54: =E54 -> 1.7 | G54: =F54 -> 1.7 | H54: =G54 -> 1.7 | I54: =H54 -> 1.7 | J54: =I54 -> 1.7 | K54: =J54 -> 1.7 | L54: =K54 -> 1.7 | M54: =L54 -> 1.7
C55: (completar) | D55: 1.7 | E55: =D55 -> 1.7 | F55: =E55 -> 1.7 | G55: =F55 -> 1.7 | H55: =G55 -> 1.7 | I55: =H55 -> 1.7 | J55: =I55 -> 1.7 | K55: =J55 -> 1.7 | L55: =K55 -> 1.7 | M55: =L55 -> 1.7
C56: (completar) | D56: 1.7 | E56: =D56 -> 1.7 | F56: =E56 -> 1.7 | G56: =F56 -> 1.7 | H56: =G56 -> 1.7 | I56: =H56 -> 1.7 | J56: =I56 -> 1.7 | K56: =J56 -> 1.7 | L56: =K56 -> 1.7 | M56: =L56 -> 1.7
... C59: (completar) | D59: 1.7 | E59: =D59 -> 1.7 | F59: =E59 -> 1.7 | G59: =F59 -> 1.7 | H59: =G59 -> 1.7 | I59: =H59 -> 1.7 | J59: =I59 -> 1.7 | K59: =J59 -> 1.7 | L59: =K59 -> 1.7 | M59: =L59 -> 1.7
D61: Salários Totais Anuais em R$
D62: Ano 1 | E62: Ano 2 | F62: Ano 3 | G62: Ano 4 | H62: Ano 5 | I62: Ano 6 | J62: Ano 7 | K62: Ano 8 | L62: Ano 9 | M62: Ano 10
C63: Diretor Presidente | D63: =+D6*D27*D45*12 -> 714000 | E63: =+E6*E27*E45*12 -> 721140 | F63: =+F6*F27*F45*12 -> 728351.4 | G63: =+G6*G27*G45*12 -> 735634.91 | H63: =+H6*H27*H45*12 -> 742991.26 | I63: =+I6*I27*I45*12 -> 750421.18 | J63: =+J6*J27*J45*12 -> 757925.39 | K63: =+K6*K27*K45*12 -> 765504.64 | ... M63: =+M6*M27*M45*12 -> 780891.28
C64: Diretor Incorporação | D64: =+D7*D28*D46*12 -> 510000 | E64: =+E7*E28*E46*12 -> 515100 | F64: =+F7*F28*F46*12 -> 520251 | G64: =+G7*G28*G46*12 -> 525453.51 | H64: =+H7*H28*H46*12 -> 530708.05 | I64: =+I7*I28*I46*12 -> 536015.13 | J64: =+J7*J28*J46*12 -> 541375.28 | K64: =+K7*K28*K46*12 -> 546789.03 | ... M64: =+M7*M28*M46*12 -> 557779.49
C65: Diretor Comercial | D65: =+D8*D29*D47*12 -> 510000 | E65: =+E8*E29*E47*12 -> 515100 | F65: =+F8*F29*F47*12 -> 520251 | G65: =+G8*G29*G47*12 -> 525453.51 | H65: =+H8*H29*H47*12 -> 530708.05 | I65: =+I8*I29*I47*12 -> 536015.13 | J65: =+J8*J29*J47*12 -> 541375.28 | K65: =+K8*K29*K47*12 -> 546789.03 | ... M65: =+M8*M29*M47*12 -> 557779.49
C66: Diretor de Operações | D66: =+D9*D30*D48*12 -> 510000 | E66: =+E9*E30*E48*12 -> 515100 | F66: =+F9*F30*F48*12 -> 520251 | G66: =+G9*G30*G48*12 -> 525453.51 | H66: =+H9*H30*H48*12 -> 530708.05 | I66: =+I9*I30*I48*12 -> 536015.13 | J66: =+J9*J30*J48*12 -> 541375.28 | K66: =+K9*K30*K48*12 -> 546789.03 | ... M66: =+M9*M30*M48*12 -> 557779.49
C67: Gerente de Incorporação | D67: =+D10*D31*D49*12 -> 306000 | E67: =+E10*E31*E49*12 -> 309060 | F67: =+F10*F31*F49*12 -> 312150.6 | G67: =+G10*G31*G49*12 -> 315272.11 | H67: =+H10*H31*H49*12 -> 318424.83 | I67: =+I10*I31*I49*12 -> 321609.08 | J67: =+J10*J31*J49*12 -> 324825.17 | K67: =+K10*K31*K49*12 -> 328073.42 | ... M67: =+M10*M31*M49*12 -> 334667.69
C68: Gerente Comercial | D68: =+D11*D32*D50*12 -> 306000 | E68: =+E11*E32*E50*12 -> 309060 | F68: =+F11*F32*F50*12 -> 312150.6 | G68: =+G11*G32*G50*12 -> 315272.11 | H68: =+H11*H32*H50*12 -> 318424.83 | I68: =+I11*I32*I50*12 -> 321609.08 | J68: =+J11*J32*J50*12 -> 324825.17 | K68: =+K11*K32*K50*12 -> 328073.42 | ... M68: =+M11*M32*M50*12 -> 334667.69
C69: Gerente Operações | D69: =+D12*D33*D51*12 -> 306000 | E69: =+E12*E33*E51*12 -> 309060 | F69: =+F12*F33*F51*12 -> 312150.6 | G69: =+G12*G33*G51*12 -> 315272.11 | H69: =+H12*H33*H51*12 -> 318424.83 | I69: =+I12*I33*I51*12 -> 321609.08 | J69: =+J12*J33*J51*12 -> 324825.17 | K69: =+K12*K33*K51*12 -> 328073.42 | ... M69: =+M12*M33*M51*12 -> 334667.69
C70: Supervisor Comercial | D70: =+D13*D34*D52*12 -> 0 | E70: =+E13*E34*E52*12 -> 0 | F70: =+F13*F34*F52*12 -> 0 | G70: =+G13*G34*G52*12 -> 0 | H70: =+H13*H34*H52*12 -> 0 | I70: =+I13*I34*I52*12 -> 0 | J70: =+J13*J34*J52*12 -> 0 | K70: =+K13*K34*K52*12 -> 0 | ... M70: =+M13*M34*M52*12 -> 0
C71: (completar) | D71: =+D14*D35*D53*12 -> 0 | E71: =+E14*E35*E53*12 -> 0 | F71: =+F14*F35*F53*12 -> 0 | G71: =+G14*G35*G53*12 -> 0 | H71: =+H14*H35*H53*12 -> 0 | I71: =+I14*I35*I53*12 -> 0 | J71: =+J14*J35*J53*12 -> 0 | K71: =+K14*K35*K53*12 -> 0 | ... M71: =+M14*M35*M53*12 -> 0
C72: (completar) | D72: =+D15*D36*D54*12 -> 0 | E72: =+E15*E36*E54*12 -> 0 | F72: =+F15*F36*F54*12 -> 0 | G72: =+G15*G36*G54*12 -> 0 | H72: =+H15*H36*H54*12 -> 0 | I72: =+I15*I36*I54*12 -> 0 | J72: =+J15*J36*J54*12 -> 0 | K72: =+K15*K36*K54*12 -> 0 | ... M72: =+M15*M36*M54*12 -> 0
C73: (completar) | D73: =+D16*D37*D55*12 -> 0 | E73: =+E16*E37*E55*12 -> 0 | F73: =+F16*F37*F55*12 -> 0 | G73: =+G16*G37*G55*12 -> 0 | H73: =+H16*H37*H55*12 -> 0 | I73: =+I16*I37*I55*12 -> 0 | J73: =+J16*J37*J55*12 -> 0 | K73: =+K16*K37*K55*12 -> 0 | ... M73: =+M16*M37*M55*12 -> 0
C74: (completar) | D74: =+D17*D38*D56*12 -> 0 | E74: =+E17*E38*E56*12 -> 0 | F74: =+F17*F38*F56*12 -> 0 | G74: =+G17*G38*G56*12 -> 0 | H74: =+H17*H38*H56*12 -> 0 | I74: =+I17*I38*I56*12 -> 0 | J74: =+J17*J38*J56*12 -> 0 | K74: =+K17*K38*K56*12 -> 0 | ... M74: =+M17*M38*M56*12 -> 0
... C77: (completar) | D77: =+D20*D41*D59*12 -> 0 | E77: =+E20*E41*E59*12 -> 0 | F77: =+F20*F41*F59*12 -> 0 | G77: =+G20*G41*G59*12 -> 0 | H77: =+H20*H41*H59*12 -> 0 | I77: =+I20*I41*I59*12 -> 0 | J77: =+J20*J41*J59*12 -> 0 | K77: =+K20*K41*K59*12 -> 0 | ... M77: =+M20*M41*M59*12 -> 0
C79: TOTAL | D79: =SUM(D63:D77) -> 3162000 | E79: =SUM(E63:E77) -> 3193620 | F79: =SUM(F63:F77) -> 3225556.2 | G79: =SUM(G63:G77) -> 3257811.8 | H79: =SUM(H63:H77) -> 3290389.9 | I79: =SUM(I63:I77) -> 3323293.8 | J79: =SUM(J63:J77) -> 3356526.7 | K79: =SUM(K63:K77) -> 3390092 | ... M79: =SUM(M63:M77) -> 3458232.8
C80: Total em R$Mn | D80: =+D79/1000000 -> 3.162 | E80: =+E79/1000000 -> 3.19362 | F80: =+F79/1000000 -> 3.2255562 | G80: =+G79/1000000 -> 3.2578118 | H80: =+H79/1000000 -> 3.2903899 | I80: =+I79/1000000 -> 3.3232938 | J80: =+J79/1000000 -> 3.3565267 | K80: =+K79/1000000 -> 3.390092 | ... M80: =+M79/1000000 -> 3.4582328

Sheet CONSOLIDADO
B2: COMPANHIA REAL ESTATE - CONSOLIDADO
B3: Em Milhoes de Reais
D6: Ano 1 | E6: Ano 2 | F6: Ano 3 | G6: Ano 4 | H6: Ano 5 | I6: Ano 6 | J6: Ano 7 | K6: Ano 8 | L6: Ano 9 | M6: Ano 10
C7: Projeto 1 | D7: ='PROJETO 1'!D173 -> 4.032 | E7: ='PROJETO 1'!E173 -> 12.336 | F7: ='PROJETO 1'!F173 -> 31.968 | G7: ='PROJETO 1'!G173 -> -37.99488 | H7: ='PROJETO 1'!H173 -> 0 | I7: ='PROJETO 1'!I173 -> 0 | J7: ='PROJETO 1'!J173 -> 0 | K7: ='PROJETO 1'!K173 -> 0 | ... M7: ='PROJETO 1'!M173 -> 0
C8: Projeto 2 | D8: ='PROJETO 2'!D173 -> -0.4690625 | E8: ='PROJETO 2'!E173 -> 1.5856094 | F8: ='PROJETO 2'!F173 -> 2.2304219 | G8: ='PROJETO 2'!G173 -> 7.6943112 | H8: ='PROJETO 2'!H173 -> 0 | I8: ='PROJETO 2'!I173 -> 0 | J8: ='PROJETO 2'!J173 -> 0 | K8: ='PROJETO 2'!K173 -> 0 | ... M8: ='PROJETO 2'!M173 -> 0
C9: Projeto 3 | D9: ='PROJETO 3'!D173 -> 0 | E9: ='PROJETO 3'!E173 -> 1.0314 | F9: ='PROJETO 3'!F173 -> 13.880925 | G9: ='PROJETO 3'!G173 -> 6.718425 | H9: ='PROJETO 3'!H173 -> -6.5313047 | I9: ='PROJETO 3'!I173 -> 0 | J9: ='PROJETO 3'!J173 -> 0 | K9: ='PROJETO 3'!K173 -> 0 | ... M9: ='PROJETO 3'!M173 -> 0
C10: Projeto 4 | D10: ='PROJETO 4'!D173 -> 0 | E10: ='PROJETO 4'!E173 -> 0 | F10: ='PROJETO 4'!F173 -> 3.1666667 | G10: ='PROJETO 4'!G173 -> 14.851667 | H10: ='PROJETO 4'!H173 -> 29.006667 | I10: ='PROJETO 4'!I173 -> 22.294315 | J10: ='PROJETO 4'!J173 -> 0 | K10: ='PROJETO 4'!K173 -> 0 | ... M10: ='PROJETO 4'!M173 -> 0
C11: A Contratar | D11: ='A CONTRATAR'!D173 -> 0 | E11: ='A CONTRATAR'!E173 -> 0 | F11: ='A CONTRATAR'!F173 -> 0 | G11: ='A CONTRATAR'!G173 -> 0 | H11: ='A CONTRATAR'!H173 -> 0 | I11: ='A CONTRATAR'!I173 -> 0 | J11: ='A CONTRATAR'!J173 -> 236.875 | K11: ='A CONTRATAR'!K173 -> 189.5 | ... M11: ='A CONTRATAR'!M173 -> 284.25
C12: Estoque Pronto | D12: ='ESTOQUE PRONTO'!D51 -> 14.415 | E12: ='ESTOQUE PRONTO'!E51 -> 12.7875 | F12: ='ESTOQUE PRONTO'!F51 -> 12.7875 | G12: ='ESTOQUE PRONTO'!G51 -> 0 | H12: ='ESTOQUE PRONTO'!H51 -> 0 | I12: ='ESTOQUE PRONTO'!I51 -> 0 | J12: ='ESTOQUE PRONTO'!J51 -> 0 | K12: ='ESTOQUE PRONTO'!K51 -> 0 | ... M12: ='ESTOQUE PRONTO'!M51 -> 0
C13: Já Lançados | D13: ='JA LANÇADOS'!D100 -> 7.96896 | E13: ='JA LANÇADOS'!E100 -> 39.77856 | F13: ='JA LANÇADOS'!F100 -> 14.07648 | G13: ='JA LANÇADOS'!G100 -> -34.98 | H13: ='JA LANÇADOS'!H100 -> 0 | I13: ='JA LANÇADOS'!I100 -> 0 | J13: ='JA LANÇADOS'!J100 -> 0 | K13: ='JA LANÇADOS'!K100 -> 0 | ... M13: ='JA LANÇADOS'!M100 -> 0
C14: Total Projetos | D14: =SUM(D7:D13) -> 25.946898 | E14: =SUM(E7:E13) -> 67.519069 | F14: =SUM(F7:F13) -> 78.109994 | G14: =SUM(G7:G13) -> -43.710477 | H14: =SUM(H7:H13) -> 22.475362 | I14: =SUM(I7:I13) -> 22.294315 | J14: =SUM(J7:J13) -> 236.875 | K14: =SUM(K7:K13) -> 189.5 | ... M14: =SUM(M7:M13) -> 284.25
C16: Estrutura Administrativa | D16: =-'ESTRUT. ADM (G&A)'!D80 -> -3.162 | E16: =-'ESTRUT. ADM (G&A)'!E80 -> -3.19362 | F16: =-'ESTRUT. ADM (G&A)'!F80 -> -3.2255562 | G16: =-'ESTRUT. ADM (G&A)'!G80 -> -3.2578118 | H16: =-'ESTRUT. ADM (G&A)'!H80 -> -3.2903899 | I16: =-'ESTRUT. ADM (G&A)'!I80 -> -3.3232938 | J16: =-'ESTRUT. ADM (G&A)'!J80 -> -3.3565267 | K16: =-'ESTRUT. ADM (G&A)'!K80 -> -3.390092 | ... M16: =-'ESTRUT. ADM (G&A)'!M80 -> -3.4582328
C18: Gastos Gerais | D18: =SUM(D20:D23) -> -2.58 | E18: =D18*(1+E19) -> -2.6316 | F18: =E18*(1+F19) -> -2.684232 | G18: =F18*(1+G19) -> -2.7379166 | H18: =G18*(1+H19) -> -2.792675 | I18: =H18*(1+I19) -> -2.8485285 | J18: =I18*(1+J19) -> -2.905499 | K18: =J18*(1+K19) -> -2.963609 | L18: =K18*(1+L19) -> -3.0228812 | M18: =L18*(1+M19) -> -3.0833388
C19: Correção Real % | E19: 0.02 | F19: =E19 -> 0.02 | G19: =F19 -> 0.02 | H19: =G19 -> 0.02 | I19: =H19 -> 0.02 | J19: =I19 -> 0.02 | K19: =J19 -> 0.02 | L19: =K19 -> 0.02 | M19: =L19 -> 0.02
C20: Aluguel | D20: =-400*100*12/1000000 -> -0.48 | E20: =+D20 -> -0.48 | F20: =+E20 -> -0.48 | G20: =+F20 -> -0.48 | H20: =+G20 -> -0.48 | I20: =+H20 -> -0.48 | J20: =+I20 -> -0.48 | K20: =+J20 -> -0.48 | L20: =+K20 -> -0.48 | M20: =+L20 -> -0.48
C21: Utilidades | D21: =-50000*12/1000000 -> -0.6 | E21: =+D21 -> -0.6 | F21: =+E21 -> -0.6 | G21: =+F21 -> -0.6 | H21: =+G21 -> -0.6 | I21: =+H21 -> -0.6 | J21: =+I21 -> -0.6 | K21: =+J21 -> -0.6 | L21: =+K21 -> -0.6 | M21: =+L21 -> -0.6
C22: Prospecção | D22: -0.5 | E22: =+D22 -> -0.5 | F22: =+E22 -> -0.5 | G22: =+F22 -> -0.5 | H22: =+G22 -> -0.5 | I22: =+H22 -> -0.5 | J22: =+I22 -> -0.5 | K22: =+J22 -> -0.5 | L22: =+K22 -> -0.5 | M22: =+L22 -> -0.5
C23: Outros | D23: -1 | E23: =+D23 -> -1 | F23: =+E23 -> -1 | G23: =+F23 -> -1 | H23: =+G23 -> -1 | I23: =+H23 -> -1 | J23: =+I23 -> -1 | K23: =+J23 -> -1 | L23: =+K23 -> -1 | M23: =+L23 -> -1
C25: Fluxo de Caixa | D25: =D14+D16+D18 -> 20.204898 | E25: =E14+E16+E18 -> 61.693849 | F25: =F14+F16+F18 -> 72.200205 | G25: =G14+G16+G18 -> -49.706205 | H25: =H14+H16+H18 -> 16.392297 | I25: =I14+I16+I18 -> 16.122493 | J25: =J14+J16+J18 -> 230.61297 | K25: =K14+K16+K18 -> 183.1463 | ... M25: =M14+M16+M18 -> 277.70843 | N25: =+M25*(1+M28) -> 286.03968
C26: Perpetuidade | M26: =(N25/(E29-M28)) -> 4086.2812
C27: Fluxo Total | D27: =+D25+D26 -> 20.204898 | E27: =+E25+E26 -> 61.693849 | F27: =+F25+F26 -> 72.200205 | G27: =+G25+G26 -> -49.706205 | H27: =+H25+H26 -> 16.392297 | I27: =+I25+I26 -> 16.122493 | J27: =+J25+J26 -> 230.61297 | K27: =+K25+K26 -> 183.1463 | ... M27: =+M25+M26 -> 4363.9896
M28: 0.03
C29: Firm Value | D29: =NPV(E29,D27:M27) -> 2092.9398 | E29: 0.1
C30: Caixa Bruto | D30: 50
C31: Dívida Corporativa | D31: 100
C32: Equity Value | D32: =+D29+D30-D31 -> 2042.9398
